{"id":"15_25","col":15,"row":25,"bounds":{"minX":-18148.04,"minZ":-15610.682,"maxX":-15648.04,"maxZ":-13110.682},"roads":[{"id":"road-266","name":"nan","highway":"residential","points":[{"lat":55.485818,"lon":37.308708,"x":-17027.502,"z":-13937.714,"elevation":172.56},{"lat":55.485523,"lon":37.309171,"x":-16975.95,"z":-13995.651,"elevation":172.37}]},{"id":"road-267","name":"Большая Октябрьская улица","highway":"secondary","points":[{"lat":55.485818,"lon":37.308708,"x":-17027.502,"z":-13937.714,"elevation":172.56},{"lat":55.486336,"lon":37.308103,"x":-17094.794,"z":-13835.787,"elevation":172.74}]},{"id":"road-268","name":"Большая Октябрьская улица","highway":"secondary","points":[{"lat":55.485818,"lon":37.308708,"x":-17027.502,"z":-13937.714,"elevation":172.56},{"lat":55.485302,"lon":37.3075,"x":-17161.981,"z":-14038.942,"elevation":172.09},{"lat":55.484787,"lon":37.306292,"x":-17296.461,"z":-14140.169,"elevation":169.14}]},{"id":"road-269","name":"Большая Октябрьская улица","highway":"secondary","points":[{"lat":55.484787,"lon":37.306292,"x":-17296.461,"z":-14140.169,"elevation":169.14},{"lat":55.485302,"lon":37.3075,"x":-17161.981,"z":-14038.942,"elevation":172.09},{"lat":55.485818,"lon":37.308708,"x":-17027.502,"z":-13937.714,"elevation":172.56}]},{"id":"road-270","name":"Октябрьский проспект","highway":"secondary","points":[{"lat":55.484787,"lon":37.306292,"x":-17296.461,"z":-14140.169,"elevation":169.14},{"lat":55.483939,"lon":37.305518,"x":-17382.594,"z":-14306.881,"elevation":169.99},{"lat":55.483397,"lon":37.303807,"x":-17573.045,"z":-14413.284,"elevation":171.62}]},{"id":"road-271","name":"Академическая площадь","highway":"tertiary","points":[{"lat":55.484787,"lon":37.306292,"x":-17296.461,"z":-14140.169,"elevation":169.14},{"lat":55.485742,"lon":37.3059,"x":-17340.076,"z":-13952.665,"elevation":170.85}]},{"id":"road-272","name":"nan","highway":"residential","points":[{"lat":55.487476,"lon":37.297651,"x":-18258.294,"z":-13611.829,"elevation":168.95},{"lat":55.48706,"lon":37.299647,"x":-18036.109,"z":-13693.655,"elevation":168.78},{"lat":55.48671,"lon":37.301668,"x":-17811.131,"z":-13762.421,"elevation":170.0},{"lat":55.486316,"lon":37.303382,"x":-17620.349,"z":-13839.732,"elevation":172.2},{"lat":55.485828,"lon":37.304741,"x":-17469.095,"z":-13935.572,"elevation":172.6}]},{"id":"road-274","name":"улица Полковника Милиции Курочкина","highway":"tertiary","points":[{"lat":55.487476,"lon":37.297651,"x":-18258.294,"z":-13611.829,"elevation":168.95},{"lat":55.488311,"lon":37.299314,"x":-18073.241,"z":-13447.853,"elevation":174.12},{"lat":55.489145,"lon":37.300976,"x":-17888.187,"z":-13283.878,"elevation":170.46},{"lat":55.48998,"lon":37.302639,"x":-17703.133,"z":-13119.902,"elevation":171.72}]},{"id":"road-275","name":"nan","highway":"residential","points":[{"lat":55.485944,"lon":37.305825,"x":-17348.413,"z":-13912.94,"elevation":171.27},{"lat":55.485966,"lon":37.306043,"x":-17324.112,"z":-13908.637,"elevation":171.69}]},{"id":"road-276","name":"Академическая площадь","highway":"tertiary","points":[{"lat":55.485944,"lon":37.305825,"x":-17348.413,"z":-13912.94,"elevation":171.27},{"lat":55.485828,"lon":37.304741,"x":-17469.095,"z":-13935.572,"elevation":172.6}]},{"id":"road-292","name":"Индустриальная улица","highway":"unclassified","points":[{"lat":55.47772,"lon":37.317333,"x":-16067.393,"z":-15528.55,"elevation":187.84},{"lat":55.478646,"lon":37.315756,"x":-16242.886,"z":-15346.515,"elevation":184.06},{"lat":55.479365,"lon":37.313921,"x":-16447.141,"z":-15205.248,"elevation":181.89},{"lat":55.480101,"lon":37.312348,"x":-16622.268,"z":-15060.814,"elevation":178.72},{"lat":55.48138,"lon":37.312095,"x":-16650.442,"z":-14809.536,"elevation":177.34},{"lat":55.482581,"lon":37.311526,"x":-16713.745,"z":-14573.62,"elevation":177.7},{"lat":55.482522,"lon":37.309707,"x":-16916.238,"z":-14585.12,"elevation":175.35}]},{"id":"road-293","name":"Калужское шоссе","highway":"trunk","points":[{"lat":55.47772,"lon":37.317333,"x":-16067.393,"z":-15528.55,"elevation":187.84},{"lat":55.47686,"lon":37.316071,"x":-16207.845,"z":-15697.309,"elevation":188.17},{"lat":55.476001,"lon":37.314809,"x":-16348.297,"z":-15866.069,"elevation":188.59},{"lat":55.475142,"lon":37.313547,"x":-16488.749,"z":-16034.828,"elevation":188.08},{"lat":55.474283,"lon":37.312286,"x":-16629.201,"z":-16203.587,"elevation":187.87},{"lat":55.473424,"lon":37.311024,"x":-16769.652,"z":-16372.347,"elevation":190.94}]},{"id":"road-296","name":"Школьная улица","highway":"residential","points":[{"lat":55.477799,"lon":37.306822,"x":-17237.406,"z":-15512.934,"elevation":189.93},{"lat":55.477911,"lon":37.30688,"x":-17230.938,"z":-15491.032,"elevation":189.87}]},{"id":"road-297","name":"['Центральная улица', 'улица Пушковых']","highway":"residential","points":[{"lat":55.477799,"lon":37.306822,"x":-17237.406,"z":-15512.934,"elevation":189.93},{"lat":55.476947,"lon":37.308488,"x":-17051.999,"z":-15680.272,"elevation":189.67},{"lat":55.47608,"lon":37.30975,"x":-16911.497,"z":-15850.57,"elevation":190.2},{"lat":55.475112,"lon":37.308296,"x":-17073.343,"z":-16040.79,"elevation":191.78}]},{"id":"road-298","name":"улица Пушковых","highway":"residential","points":[{"lat":55.477799,"lon":37.306822,"x":-17237.406,"z":-15512.934,"elevation":189.93},{"lat":55.477943,"lon":37.304981,"x":-17442.401,"z":-15484.727,"elevation":187.89}]},{"id":"road-299","name":"Школьная улица","highway":"residential","points":[{"lat":55.477799,"lon":37.306822,"x":-17237.406,"z":-15512.934,"elevation":189.93},{"lat":55.476882,"lon":37.305449,"x":-17390.247,"z":-15693.015,"elevation":191.31}]},{"id":"road-308","name":"Лесная улица","highway":"residential","points":[{"lat":55.476084,"lon":37.302215,"x":-17750.31,"z":-15849.856,"elevation":189.12},{"lat":55.477013,"lon":37.303598,"x":-17596.355,"z":-15667.291,"elevation":189.67},{"lat":55.477943,"lon":37.304981,"x":-17442.401,"z":-15484.727,"elevation":187.89}]},{"id":"road-317","name":"nan","highway":"tertiary","points":[{"lat":55.485742,"lon":37.3059,"x":-17340.076,"z":-13952.665,"elevation":170.85},{"lat":55.485944,"lon":37.305825,"x":-17348.413,"z":-13912.94,"elevation":171.27}]},{"id":"road-318","name":"Академическая площадь","highway":"tertiary","points":[{"lat":55.485742,"lon":37.3059,"x":-17340.076,"z":-13952.665,"elevation":170.85},{"lat":55.484787,"lon":37.306292,"x":-17296.461,"z":-14140.169,"elevation":169.14}]},{"id":"road-319","name":"nan","highway":"residential","points":[{"lat":55.48432,"lon":37.310539,"x":-16823.642,"z":-14231.975,"elevation":173.94},{"lat":55.484638,"lon":37.310165,"x":-16865.242,"z":-14169.501,"elevation":173.55}]},{"id":"road-722","name":"Большая Октябрьская улица","highway":"secondary","points":[{"lat":55.486514,"lon":37.307896,"x":-17117.826,"z":-13800.874,"elevation":173.61},{"lat":55.486336,"lon":37.308103,"x":-17094.794,"z":-13835.787,"elevation":172.74}]},{"id":"road-723","name":"Большая Октябрьская улица","highway":"secondary","points":[{"lat":55.486514,"lon":37.307896,"x":-17117.826,"z":-13800.874,"elevation":173.61},{"lat":55.487301,"lon":37.306985,"x":-17219.272,"z":-13646.369,"elevation":174.04}]},{"id":"road-724","name":"nan","highway":"residential","points":[{"lat":55.486514,"lon":37.307896,"x":-17117.826,"z":-13800.874,"elevation":173.61},{"lat":55.486176,"lon":37.306939,"x":-17224.459,"z":-13867.202,"elevation":174.31}]},{"id":"road-725","name":"Октябрьский проспект","highway":"secondary","points":[{"lat":55.475735,"lon":37.296474,"x":-18389.329,"z":-15918.405,"elevation":194.36},{"lat":55.476773,"lon":37.297701,"x":-18252.804,"z":-15714.432,"elevation":187.87},{"lat":55.477812,"lon":37.298927,"x":-18116.28,"z":-15510.46,"elevation":186.54},{"lat":55.47885,"lon":37.300154,"x":-17979.756,"z":-15306.487,"elevation":184.58},{"lat":55.479979,"lon":37.301092,"x":-17875.303,"z":-15084.725,"elevation":182.39},{"lat":55.481118,"lon":37.301997,"x":-17774.551,"z":-14860.911,"elevation":177.76},{"lat":55.482258,"lon":37.302902,"x":-17673.798,"z":-14637.098,"elevation":173.64},{"lat":55.483397,"lon":37.303807,"x":-17573.045,"z":-14413.284,"elevation":171.62}]},{"id":"road-1044","name":"Школьная улица","highway":"residential","points":[{"lat":55.476882,"lon":37.305449,"x":-17390.247,"z":-15693.015,"elevation":191.31},{"lat":55.477799,"lon":37.306822,"x":-17237.406,"z":-15512.934,"elevation":189.93}]},{"id":"road-1313","name":"nan","highway":"residential","points":[{"lat":55.485966,"lon":37.306043,"x":-17324.112,"z":-13908.637,"elevation":171.69},{"lat":55.485944,"lon":37.305825,"x":-17348.413,"z":-13912.94,"elevation":171.27}]},{"id":"road-1314","name":"nan","highway":"residential","points":[{"lat":55.485966,"lon":37.306043,"x":-17324.112,"z":-13908.637,"elevation":171.69},{"lat":55.486176,"lon":37.306939,"x":-17224.459,"z":-13867.202,"elevation":174.31}]},{"id":"road-1315","name":"1-я Мичуринская улица","highway":"residential","points":[{"lat":55.488627,"lon":37.305431,"x":-17392.251,"z":-13385.704,"elevation":171.07},{"lat":55.488842,"lon":37.307207,"x":-17194.617,"z":-13343.544,"elevation":170.57},{"lat":55.489274,"lon":37.308512,"x":-17049.343,"z":-13258.64,"elevation":170.53}]},{"id":"road-1316","name":"Большая Октябрьская улица","highway":"secondary","points":[{"lat":55.488627,"lon":37.305431,"x":-17392.251,"z":-13385.704,"elevation":171.07},{"lat":55.487925,"lon":37.306267,"x":-17299.199,"z":-13523.71,"elevation":173.18}]},{"id":"road-1317","name":"Большая Октябрьская улица","highway":"secondary","points":[{"lat":55.488627,"lon":37.305431,"x":-17392.251,"z":-13385.704,"elevation":171.07},{"lat":55.489191,"lon":37.304775,"x":-17465.271,"z":-13274.868,"elevation":169.5},{"lat":55.489755,"lon":37.304119,"x":-17538.291,"z":-13164.032,"elevation":169.66}]},{"id":"road-1318","name":"1-я Мичуринская улица","highway":"residential","points":[{"lat":55.489274,"lon":37.308512,"x":-17049.343,"z":-13258.64,"elevation":170.53},{"lat":55.488842,"lon":37.307207,"x":-17194.617,"z":-13343.544,"elevation":170.57},{"lat":55.488627,"lon":37.305431,"x":-17392.251,"z":-13385.704,"elevation":171.07}]},{"id":"road-1407","name":"улица Академика Харитона","highway":"unclassified","points":[{"lat":55.486675,"lon":37.322435,"x":-15499.341,"z":-13769.302,"elevation":165.99},{"lat":55.486892,"lon":37.320618,"x":-15701.654,"z":-13726.605,"elevation":166.45},{"lat":55.487109,"lon":37.318801,"x":-15903.967,"z":-13683.908,"elevation":167.11},{"lat":55.487327,"lon":37.316983,"x":-16106.28,"z":-13641.212,"elevation":168.22},{"lat":55.487822,"lon":37.315458,"x":-16276.084,"z":-13543.987,"elevation":169.17}]},{"id":"road-1465","name":"nan","highway":"residential","points":[{"lat":55.485523,"lon":37.309171,"x":-16975.95,"z":-13995.651,"elevation":172.37},{"lat":55.485818,"lon":37.308708,"x":-17027.502,"z":-13937.714,"elevation":172.56}]},{"id":"road-1466","name":"nan","highway":"residential","points":[{"lat":55.485523,"lon":37.309171,"x":-16975.95,"z":-13995.651,"elevation":172.37},{"lat":55.484638,"lon":37.310165,"x":-16865.242,"z":-14169.501,"elevation":173.55}]},{"id":"road-1467","name":"Садовая улица","highway":"residential","points":[{"lat":55.485523,"lon":37.309171,"x":-16975.95,"z":-13995.651,"elevation":172.37},{"lat":55.486052,"lon":37.310671,"x":-16808.997,"z":-13891.685,"elevation":171.26},{"lat":55.486603,"lon":37.312009,"x":-16660.057,"z":-13783.498,"elevation":176.46},{"lat":55.487454,"lon":37.31108,"x":-16763.452,"z":-13616.191,"elevation":173.45}]},{"id":"road-1468","name":"Садовая улица","highway":"residential","points":[{"lat":55.485523,"lon":37.309171,"x":-16975.95,"z":-13995.651,"elevation":172.37},{"lat":55.485118,"lon":37.308135,"x":-17091.288,"z":-14075.111,"elevation":172.63},{"lat":55.484714,"lon":37.307099,"x":-17206.626,"z":-14154.57,"elevation":170.2}]},{"id":"road-1524","name":"улица Академика Харитона","highway":"unclassified","points":[{"lat":55.487822,"lon":37.315458,"x":-16276.084,"z":-13543.987,"elevation":169.17},{"lat":55.487327,"lon":37.316983,"x":-16106.28,"z":-13641.212,"elevation":168.22},{"lat":55.487109,"lon":37.318801,"x":-15903.967,"z":-13683.908,"elevation":167.11},{"lat":55.486892,"lon":37.320618,"x":-15701.654,"z":-13726.605,"elevation":166.45},{"lat":55.486675,"lon":37.322435,"x":-15499.341,"z":-13769.302,"elevation":165.99}]},{"id":"road-2469","name":"Садовая улица","highway":"residential","points":[{"lat":55.484714,"lon":37.307099,"x":-17206.626,"z":-14154.57,"elevation":170.2},{"lat":55.485118,"lon":37.308135,"x":-17091.288,"z":-14075.111,"elevation":172.63},{"lat":55.485523,"lon":37.309171,"x":-16975.95,"z":-13995.651,"elevation":172.37}]},{"id":"road-2583","name":"nan","highway":"residential","points":[{"lat":55.485828,"lon":37.304741,"x":-17469.095,"z":-13935.572,"elevation":172.6},{"lat":55.486316,"lon":37.303382,"x":-17620.349,"z":-13839.732,"elevation":172.2},{"lat":55.48671,"lon":37.301668,"x":-17811.131,"z":-13762.421,"elevation":170.0},{"lat":55.48706,"lon":37.299647,"x":-18036.109,"z":-13693.655,"elevation":168.78},{"lat":55.487476,"lon":37.297651,"x":-18258.294,"z":-13611.829,"elevation":168.95}]},{"id":"road-2584","name":"Академическая площадь","highway":"tertiary","points":[{"lat":55.485828,"lon":37.304741,"x":-17469.095,"z":-13935.572,"elevation":172.6},{"lat":55.485742,"lon":37.3059,"x":-17340.076,"z":-13952.665,"elevation":170.85}]},{"id":"road-3179","name":"Большая Октябрьская улица","highway":"secondary","points":[{"lat":55.487925,"lon":37.306267,"x":-17299.199,"z":-13523.71,"elevation":173.18},{"lat":55.487301,"lon":37.306985,"x":-17219.272,"z":-13646.369,"elevation":174.04}]},{"id":"road-3180","name":"Большая Октябрьская улица","highway":"secondary","points":[{"lat":55.487925,"lon":37.306267,"x":-17299.199,"z":-13523.71,"elevation":173.18},{"lat":55.488627,"lon":37.305431,"x":-17392.251,"z":-13385.704,"elevation":171.07}]},{"id":"road-3181","name":"2-я Мичуринская улица","highway":"residential","points":[{"lat":55.487925,"lon":37.306267,"x":-17299.199,"z":-13523.71,"elevation":173.18},{"lat":55.488231,"lon":37.308118,"x":-17093.201,"z":-13463.559,"elevation":171.12},{"lat":55.488537,"lon":37.309968,"x":-16887.203,"z":-13403.407,"elevation":170.76},{"lat":55.487896,"lon":37.310696,"x":-16806.143,"z":-13529.271,"elevation":172.01}]},{"id":"road-4141","name":"['Центральная улица', 'улица Пушковых']","highway":"residential","points":[{"lat":55.475112,"lon":37.308296,"x":-17073.343,"z":-16040.79,"elevation":191.78},{"lat":55.47608,"lon":37.30975,"x":-16911.497,"z":-15850.57,"elevation":190.2},{"lat":55.476947,"lon":37.308488,"x":-17051.999,"z":-15680.272,"elevation":189.67},{"lat":55.477799,"lon":37.306822,"x":-17237.406,"z":-15512.934,"elevation":189.93}]},{"id":"road-4267","name":"Школьная улица","highway":"residential","points":[{"lat":55.477911,"lon":37.30688,"x":-17230.938,"z":-15491.032,"elevation":189.87},{"lat":55.477799,"lon":37.306822,"x":-17237.406,"z":-15512.934,"elevation":189.93}]},{"id":"road-4268","name":"Индустриальная улица","highway":"unclassified","points":[{"lat":55.482522,"lon":37.309707,"x":-16916.238,"z":-14585.12,"elevation":175.35},{"lat":55.482581,"lon":37.311526,"x":-16713.745,"z":-14573.62,"elevation":177.7},{"lat":55.48138,"lon":37.312095,"x":-16650.442,"z":-14809.536,"elevation":177.34},{"lat":55.480101,"lon":37.312348,"x":-16622.268,"z":-15060.814,"elevation":178.72},{"lat":55.479365,"lon":37.313921,"x":-16447.141,"z":-15205.248,"elevation":181.89},{"lat":55.478646,"lon":37.315756,"x":-16242.886,"z":-15346.515,"elevation":184.06},{"lat":55.47772,"lon":37.317333,"x":-16067.393,"z":-15528.55,"elevation":187.84}]},{"id":"road-4282","name":"Большая Октябрьская улица","highway":"secondary","points":[{"lat":55.486336,"lon":37.308103,"x":-17094.794,"z":-13835.787,"elevation":172.74},{"lat":55.485818,"lon":37.308708,"x":-17027.502,"z":-13937.714,"elevation":172.56}]},{"id":"road-4283","name":"Большая Октябрьская улица","highway":"secondary","points":[{"lat":55.486336,"lon":37.308103,"x":-17094.794,"z":-13835.787,"elevation":172.74},{"lat":55.486514,"lon":37.307896,"x":-17117.826,"z":-13800.874,"elevation":173.61}]},{"id":"road-4284","name":"Первомайская улица","highway":"residential","points":[{"lat":55.486336,"lon":37.308103,"x":-17094.794,"z":-13835.787,"elevation":172.74},{"lat":55.486895,"lon":37.309592,"x":-16929.123,"z":-13725.989,"elevation":172.27},{"lat":55.487454,"lon":37.31108,"x":-16763.452,"z":-13616.191,"elevation":173.45}]},{"id":"road-4285","name":"Терновая улица","highway":"residential","points":[{"lat":55.487193,"lon":37.321048,"x":-15653.808,"z":-13667.431,"elevation":165.01},{"lat":55.488206,"lon":37.321236,"x":-15632.874,"z":-13468.498,"elevation":162.31},{"lat":55.489218,"lon":37.321424,"x":-15611.941,"z":-13269.564,"elevation":161.23}]},{"id":"road-4286","name":"8-я Вишнёвая улица","highway":"residential","points":[{"lat":55.487298,"lon":37.320028,"x":-15767.343,"z":-13646.861,"elevation":165.69},{"lat":55.488516,"lon":37.320241,"x":-15743.657,"z":-13407.532,"elevation":162.55},{"lat":55.489734,"lon":37.320454,"x":-15719.971,"z":-13168.203,"elevation":161.63},{"lat":55.490952,"lon":37.320666,"x":-15696.285,"z":-12928.874,"elevation":162.51},{"lat":55.49217,"lon":37.320879,"x":-15672.599,"z":-12689.545,"elevation":160.4}]},{"id":"road-4287","name":"6-я Вишнёвая улица","highway":"residential","points":[{"lat":55.487336,"lon":37.317999,"x":-15993.232,"z":-13639.296,"elevation":167.07},{"lat":55.488496,"lon":37.318214,"x":-15969.274,"z":-13411.398,"elevation":164.8},{"lat":55.489656,"lon":37.318429,"x":-15945.315,"z":-13183.501,"elevation":163.32},{"lat":55.490816,"lon":37.318644,"x":-15921.356,"z":-12955.603,"elevation":161.66},{"lat":55.491976,"lon":37.31886,"x":-15897.397,"z":-12727.705,"elevation":161.23}]},{"id":"road-4288","name":"Большая Октябрьская улица","highway":"secondary","points":[{"lat":55.487301,"lon":37.306985,"x":-17219.272,"z":-13646.369,"elevation":174.04},{"lat":55.486514,"lon":37.307896,"x":-17117.826,"z":-13800.874,"elevation":173.61}]},{"id":"road-4289","name":"Большая Октябрьская улица","highway":"secondary","points":[{"lat":55.487301,"lon":37.306985,"x":-17219.272,"z":-13646.369,"elevation":174.04},{"lat":55.487925,"lon":37.306267,"x":-17299.199,"z":-13523.71,"elevation":173.18}]},{"id":"road-4290","name":"Рабочая улица","highway":"residential","points":[{"lat":55.487301,"lon":37.306985,"x":-17219.272,"z":-13646.369,"elevation":174.04},{"lat":55.487599,"lon":37.308841,"x":-17012.707,"z":-13587.82,"elevation":172.42},{"lat":55.487896,"lon":37.310696,"x":-16806.143,"z":-13529.271,"elevation":172.01}]},{"id":"road-4291","name":"7-я Вишнёвая улица","highway":"residential","points":[{"lat":55.487361,"lon":37.319212,"x":-15858.157,"z":-13634.502,"elevation":165.66},{"lat":55.488541,"lon":37.319381,"x":-15839.325,"z":-13402.557,"elevation":163.31},{"lat":55.489722,"lon":37.319551,"x":-15820.492,"z":-13170.611,"elevation":162.36},{"lat":55.490902,"lon":37.31972,"x":-15801.66,"z":-12938.665,"elevation":161.55},{"lat":55.492083,"lon":37.319889,"x":-15782.827,"z":-12706.719,"elevation":160.57}]},{"id":"road-4295","name":"5-я Вишнёвая улица","highway":"residential","points":[{"lat":55.48743,"lon":37.316975,"x":-16107.246,"z":-13620.847,"elevation":167.49},{"lat":55.488545,"lon":37.317193,"x":-16082.945,"z":-13401.904,"elevation":165.11},{"lat":55.489659,"lon":37.317411,"x":-16058.644,"z":-13182.961,"elevation":163.58},{"lat":55.490773,"lon":37.31763,"x":-16034.343,"z":-12964.018,"elevation":162.86},{"lat":55.491888,"lon":37.317848,"x":-16010.042,"z":-12745.075,"elevation":162.01}]},{"id":"road-4296","name":"nan","highway":"residential","points":[{"lat":55.487454,"lon":37.31108,"x":-16763.452,"z":-13616.191,"elevation":173.45},{"lat":55.487896,"lon":37.310696,"x":-16806.143,"z":-13529.271,"elevation":172.01}]},{"id":"road-4297","name":"Первомайская улица","highway":"residential","points":[{"lat":55.487454,"lon":37.31108,"x":-16763.452,"z":-13616.191,"elevation":173.45},{"lat":55.486895,"lon":37.309592,"x":-16929.123,"z":-13725.989,"elevation":172.27},{"lat":55.486336,"lon":37.308103,"x":-17094.794,"z":-13835.787,"elevation":172.74}]},{"id":"road-4298","name":"Садовая улица","highway":"residential","points":[{"lat":55.487454,"lon":37.31108,"x":-16763.452,"z":-13616.191,"elevation":173.45},{"lat":55.486603,"lon":37.312009,"x":-16660.057,"z":-13783.498,"elevation":176.46},{"lat":55.486052,"lon":37.310671,"x":-16808.997,"z":-13891.685,"elevation":171.26},{"lat":55.485523,"lon":37.309171,"x":-16975.95,"z":-13995.651,"elevation":172.37}]},{"id":"road-4300","name":"nan","highway":"residential","points":[{"lat":55.487896,"lon":37.310696,"x":-16806.143,"z":-13529.271,"elevation":172.01},{"lat":55.487454,"lon":37.31108,"x":-16763.452,"z":-13616.191,"elevation":173.45}]},{"id":"road-4301","name":"2-я Мичуринская улица","highway":"residential","points":[{"lat":55.487896,"lon":37.310696,"x":-16806.143,"z":-13529.271,"elevation":172.01},{"lat":55.488537,"lon":37.309968,"x":-16887.203,"z":-13403.407,"elevation":170.76},{"lat":55.488231,"lon":37.308118,"x":-17093.201,"z":-13463.559,"elevation":171.12},{"lat":55.487925,"lon":37.306267,"x":-17299.199,"z":-13523.71,"elevation":173.18}]},{"id":"road-4302","name":"Рабочая улица","highway":"residential","points":[{"lat":55.487896,"lon":37.310696,"x":-16806.143,"z":-13529.271,"elevation":172.01},{"lat":55.487599,"lon":37.308841,"x":-17012.707,"z":-13587.82,"elevation":172.42},{"lat":55.487301,"lon":37.306985,"x":-17219.272,"z":-13646.369,"elevation":174.04}]},{"id":"road-4306","name":"4-я Вишнёвая улица","highway":"residential","points":[{"lat":55.488055,"lon":37.316058,"x":-16209.315,"z":-13498.208,"elevation":167.06},{"lat":55.489301,"lon":37.316299,"x":-16182.487,"z":-13253.353,"elevation":165.44},{"lat":55.490547,"lon":37.31654,"x":-16155.659,"z":-13008.498,"elevation":164.4},{"lat":55.491793,"lon":37.316781,"x":-16128.831,"z":-12763.644,"elevation":162.81}]},{"id":"road-4307","name":"3-я Вишнёвая улица","highway":"residential","points":[{"lat":55.488304,"lon":37.315061,"x":-16320.211,"z":-13449.147,"elevation":168.09},{"lat":55.489437,"lon":37.315316,"x":-16291.932,"z":-13226.495,"elevation":165.8},{"lat":55.490571,"lon":37.31557,"x":-16263.653,"z":-13003.843,"elevation":164.31},{"lat":55.491704,"lon":37.315824,"x":-16235.374,"z":-12781.191,"elevation":164.03}]},{"id":"road-4312","name":"2-я Вишнёвая улица","highway":"residential","points":[{"lat":55.488675,"lon":37.314127,"x":-16424.217,"z":-13376.391,"elevation":168.26},{"lat":55.489637,"lon":37.314343,"x":-16400.19,"z":-13187.207,"elevation":165.78},{"lat":55.4906,"lon":37.314559,"x":-16376.164,"z":-12998.022,"elevation":163.94},{"lat":55.491563,"lon":37.314775,"x":-16352.137,"z":-12808.838,"elevation":162.8}]},{"id":"road-4319","name":"Терновая улица","highway":"residential","points":[{"lat":55.489218,"lon":37.321424,"x":-15611.941,"z":-13269.564,"elevation":161.23},{"lat":55.488206,"lon":37.321236,"x":-15632.874,"z":-13468.498,"elevation":162.31},{"lat":55.487193,"lon":37.321048,"x":-15653.808,"z":-13667.431,"elevation":165.01}]},{"id":"road-4323","name":"Большая Октябрьская улица","highway":"secondary","points":[{"lat":55.489755,"lon":37.304119,"x":-17538.291,"z":-13164.032,"elevation":169.66},{"lat":55.48987,"lon":37.303986,"x":-17553.086,"z":-13141.456,"elevation":169.56}]},{"id":"road-4324","name":"Большая Октябрьская улица","highway":"secondary","points":[{"lat":55.489755,"lon":37.304119,"x":-17538.291,"z":-13164.032,"elevation":169.66},{"lat":55.489191,"lon":37.304775,"x":-17465.271,"z":-13274.868,"elevation":169.5},{"lat":55.488627,"lon":37.305431,"x":-17392.251,"z":-13385.704,"elevation":171.07}]},{"id":"road-4325","name":"Пионерский проезд","highway":"residential","points":[{"lat":55.489755,"lon":37.304119,"x":-17538.291,"z":-13164.032,"elevation":169.66},{"lat":55.490077,"lon":37.306315,"x":-17293.884,"z":-13100.872,"elevation":168.14},{"lat":55.490398,"lon":37.30851,"x":-17049.476,"z":-13037.711,"elevation":168.41}]},{"id":"road-4333","name":"Пионерский проезд","highway":"residential","points":[{"lat":55.490398,"lon":37.30851,"x":-17049.476,"z":-13037.711,"elevation":168.41},{"lat":55.490077,"lon":37.306315,"x":-17293.884,"z":-13100.872,"elevation":168.14},{"lat":55.489755,"lon":37.304119,"x":-17538.291,"z":-13164.032,"elevation":169.66}]},{"id":"road-4342","name":"2-я Вишнёвая улица","highway":"residential","points":[{"lat":55.491563,"lon":37.314775,"x":-16352.137,"z":-12808.838,"elevation":162.8},{"lat":55.4906,"lon":37.314559,"x":-16376.164,"z":-12998.022,"elevation":163.94},{"lat":55.489637,"lon":37.314343,"x":-16400.19,"z":-13187.207,"elevation":165.78},{"lat":55.488675,"lon":37.314127,"x":-16424.217,"z":-13376.391,"elevation":168.26}]},{"id":"road-4348","name":"3-я Вишнёвая улица","highway":"residential","points":[{"lat":55.491704,"lon":37.315824,"x":-16235.374,"z":-12781.191,"elevation":164.03},{"lat":55.490571,"lon":37.31557,"x":-16263.653,"z":-13003.843,"elevation":164.31},{"lat":55.489437,"lon":37.315316,"x":-16291.932,"z":-13226.495,"elevation":165.8},{"lat":55.488304,"lon":37.315061,"x":-16320.211,"z":-13449.147,"elevation":168.09}]},{"id":"road-4352","name":"4-я Вишнёвая улица","highway":"residential","points":[{"lat":55.491793,"lon":37.316781,"x":-16128.831,"z":-12763.644,"elevation":162.81},{"lat":55.490547,"lon":37.31654,"x":-16155.659,"z":-13008.498,"elevation":164.4},{"lat":55.489301,"lon":37.316299,"x":-16182.487,"z":-13253.353,"elevation":165.44},{"lat":55.488055,"lon":37.316058,"x":-16209.315,"z":-13498.208,"elevation":167.06}]},{"id":"road-4356","name":"5-я Вишнёвая улица","highway":"residential","points":[{"lat":55.491888,"lon":37.317848,"x":-16010.042,"z":-12745.075,"elevation":162.01},{"lat":55.490773,"lon":37.31763,"x":-16034.343,"z":-12964.018,"elevation":162.86},{"lat":55.489659,"lon":37.317411,"x":-16058.644,"z":-13182.961,"elevation":163.58},{"lat":55.488545,"lon":37.317193,"x":-16082.945,"z":-13401.904,"elevation":165.11},{"lat":55.48743,"lon":37.316975,"x":-16107.246,"z":-13620.847,"elevation":167.49}]},{"id":"road-4358","name":"6-я Вишнёвая улица","highway":"residential","points":[{"lat":55.491976,"lon":37.31886,"x":-15897.397,"z":-12727.705,"elevation":161.23},{"lat":55.490816,"lon":37.318644,"x":-15921.356,"z":-12955.603,"elevation":161.66},{"lat":55.489656,"lon":37.318429,"x":-15945.315,"z":-13183.501,"elevation":163.32},{"lat":55.488496,"lon":37.318214,"x":-15969.274,"z":-13411.398,"elevation":164.8},{"lat":55.487336,"lon":37.317999,"x":-15993.232,"z":-13639.296,"elevation":167.07}]},{"id":"road-4362","name":"7-я Вишнёвая улица","highway":"residential","points":[{"lat":55.492083,"lon":37.319889,"x":-15782.827,"z":-12706.719,"elevation":160.57},{"lat":55.490902,"lon":37.31972,"x":-15801.66,"z":-12938.665,"elevation":161.55},{"lat":55.489722,"lon":37.319551,"x":-15820.492,"z":-13170.611,"elevation":162.36},{"lat":55.488541,"lon":37.319381,"x":-15839.325,"z":-13402.557,"elevation":163.31},{"lat":55.487361,"lon":37.319212,"x":-15858.157,"z":-13634.502,"elevation":165.66}]},{"id":"road-4364","name":"8-я Вишнёвая улица","highway":"residential","points":[{"lat":55.49217,"lon":37.320879,"x":-15672.599,"z":-12689.545,"elevation":160.4},{"lat":55.490952,"lon":37.320666,"x":-15696.285,"z":-12928.874,"elevation":162.51},{"lat":55.489734,"lon":37.320454,"x":-15719.971,"z":-13168.203,"elevation":161.63},{"lat":55.488516,"lon":37.320241,"x":-15743.657,"z":-13407.532,"elevation":162.55},{"lat":55.487298,"lon":37.320028,"x":-15767.343,"z":-13646.861,"elevation":165.69}]},{"id":"road-5111","name":"nan","highway":"residential","points":[{"lat":55.484638,"lon":37.310165,"x":-16865.242,"z":-14169.501,"elevation":173.55},{"lat":55.48432,"lon":37.310539,"x":-16823.642,"z":-14231.975,"elevation":173.94}]},{"id":"road-5112","name":"Зелёная улица","highway":"residential","points":[{"lat":55.484638,"lon":37.310165,"x":-16865.242,"z":-14169.501,"elevation":173.55},{"lat":55.484247,"lon":37.309154,"x":-16977.859,"z":-14246.247,"elevation":173.9},{"lat":55.483857,"lon":37.308142,"x":-17090.475,"z":-14322.993,"elevation":174.23}]},{"id":"road-5113","name":"Зелёная улица","highway":"residential","points":[{"lat":55.484638,"lon":37.310165,"x":-16865.242,"z":-14169.501,"elevation":173.55},{"lat":55.485121,"lon":37.311487,"x":-16718.089,"z":-14074.57,"elevation":173.79},{"lat":55.485604,"lon":37.312809,"x":-16570.936,"z":-13979.64,"elevation":176.91}]},{"id":"road-5114","name":"nan","highway":"residential","points":[{"lat":55.484638,"lon":37.310165,"x":-16865.242,"z":-14169.501,"elevation":173.55},{"lat":55.485523,"lon":37.309171,"x":-16975.95,"z":-13995.651,"elevation":172.37}]},{"id":"road-5115","name":"Зелёная улица","highway":"residential","points":[{"lat":55.483857,"lon":37.308142,"x":-17090.475,"z":-14322.993,"elevation":174.23},{"lat":55.484247,"lon":37.309154,"x":-16977.859,"z":-14246.247,"elevation":173.9},{"lat":55.484638,"lon":37.310165,"x":-16865.242,"z":-14169.501,"elevation":173.55}]},{"id":"road-5116","name":"Зелёная улица","highway":"residential","points":[{"lat":55.485604,"lon":37.312809,"x":-16570.936,"z":-13979.64,"elevation":176.91},{"lat":55.485121,"lon":37.311487,"x":-16718.089,"z":-14074.57,"elevation":173.79},{"lat":55.484638,"lon":37.310165,"x":-16865.242,"z":-14169.501,"elevation":173.55}]},{"id":"road-5960","name":"nan","highway":"residential","points":[{"lat":55.486176,"lon":37.306939,"x":-17224.459,"z":-13867.202,"elevation":174.31},{"lat":55.486514,"lon":37.307896,"x":-17117.826,"z":-13800.874,"elevation":173.61}]},{"id":"road-6696","name":"nan","highway":"tertiary_link","points":[{"lat":55.490507,"lon":37.302515,"x":-17716.859,"z":-13016.451,"elevation":170.17},{"lat":55.48998,"lon":37.302639,"x":-17703.133,"z":-13119.902,"elevation":171.72}]},{"id":"road-6699","name":"улица Полковника Милиции Курочкина","highway":"tertiary","points":[{"lat":55.48998,"lon":37.302639,"x":-17703.133,"z":-13119.902,"elevation":171.72},{"lat":55.489145,"lon":37.300976,"x":-17888.187,"z":-13283.878,"elevation":170.46},{"lat":55.488311,"lon":37.299314,"x":-18073.241,"z":-13447.853,"elevation":174.12},{"lat":55.487476,"lon":37.297651,"x":-18258.294,"z":-13611.829,"elevation":168.95}]},{"id":"road-6700","name":"улица Полковника Милиции Курочкина","highway":"tertiary","points":[{"lat":55.48998,"lon":37.302639,"x":-17703.133,"z":-13119.902,"elevation":171.72},{"lat":55.490148,"lon":37.303017,"x":-17661.032,"z":-13086.794,"elevation":170.56}]},{"id":"road-6703","name":"Большая Октябрьская улица","highway":"secondary","points":[{"lat":55.48987,"lon":37.303986,"x":-17553.086,"z":-13141.456,"elevation":169.56},{"lat":55.489755,"lon":37.304119,"x":-17538.291,"z":-13164.032,"elevation":169.66}]},{"id":"road-6704","name":"nan","highway":"secondary_link","points":[{"lat":55.48987,"lon":37.303986,"x":-17553.086,"z":-13141.456,"elevation":169.56},{"lat":55.490483,"lon":37.304659,"x":-17478.223,"z":-13021.068,"elevation":168.41}]},{"id":"road-6705","name":"Большая Октябрьская улица","highway":"secondary","points":[{"lat":55.48987,"lon":37.303986,"x":-17553.086,"z":-13141.456,"elevation":169.56},{"lat":55.49015,"lon":37.303542,"x":-17602.612,"z":-13086.479,"elevation":169.75}]},{"id":"road-8049","name":"nan","highway":"residential","points":[{"lat":55.477943,"lon":37.304981,"x":-17442.401,"z":-15484.727,"elevation":187.89},{"lat":55.477976,"lon":37.303276,"x":-17632.156,"z":-15478.265,"elevation":186.85}]},{"id":"road-8050","name":"улица Пушковых","highway":"residential","points":[{"lat":55.477943,"lon":37.304981,"x":-17442.401,"z":-15484.727,"elevation":187.89},{"lat":55.477799,"lon":37.306822,"x":-17237.406,"z":-15512.934,"elevation":189.93}]},{"id":"road-8051","name":"Лесная улица","highway":"residential","points":[{"lat":55.477943,"lon":37.304981,"x":-17442.401,"z":-15484.727,"elevation":187.89},{"lat":55.477013,"lon":37.303598,"x":-17596.355,"z":-15667.291,"elevation":189.67},{"lat":55.476084,"lon":37.302215,"x":-17750.31,"z":-15849.856,"elevation":189.12}]},{"id":"road-8052","name":"nan","highway":"residential","points":[{"lat":55.477976,"lon":37.303276,"x":-17632.156,"z":-15478.265,"elevation":186.85},{"lat":55.477943,"lon":37.304981,"x":-17442.401,"z":-15484.727,"elevation":187.89}]},{"id":"road-8203","name":"Калужское шоссе","highway":"trunk","points":[{"lat":55.483835,"lon":37.321721,"x":-15578.868,"z":-14327.296,"elevation":178.58},{"lat":55.482612,"lon":37.320843,"x":-15676.573,"z":-14567.546,"elevation":183.16},{"lat":55.481389,"lon":37.319966,"x":-15774.278,"z":-14807.797,"elevation":182.84},{"lat":55.480166,"lon":37.319088,"x":-15871.983,"z":-15048.048,"elevation":186.44},{"lat":55.478943,"lon":37.31821,"x":-15969.688,"z":-15288.299,"elevation":187.89},{"lat":55.47772,"lon":37.317333,"x":-16067.393,"z":-15528.55,"elevation":187.84}]},{"id":"road-8245","name":"Калужское шоссе","highway":"trunk","points":[{"lat":55.474697,"lon":37.313218,"x":-16525.417,"z":-16122.124,"elevation":187.64},{"lat":55.475615,"lon":37.314559,"x":-16376.147,"z":-15941.953,"elevation":188.25},{"lat":55.476532,"lon":37.3159,"x":-16226.877,"z":-15761.782,"elevation":188.17},{"lat":55.477449,"lon":37.317241,"x":-16077.607,"z":-15581.611,"elevation":187.96},{"lat":55.478478,"lon":37.318247,"x":-15965.649,"z":-15379.499,"elevation":187.98},{"lat":55.479588,"lon":37.319009,"x":-15880.756,"z":-15161.47,"elevation":187.28},{"lat":55.480698,"lon":37.319772,"x":-15795.864,"z":-14943.442,"elevation":184.89},{"lat":55.481808,"lon":37.320534,"x":-15710.971,"z":-14725.413,"elevation":181.88},{"lat":55.482918,"lon":37.321297,"x":-15626.078,"z":-14507.385,"elevation":183.78}]},{"id":"road-12488","name":"улица Полковника Милиции Курочкина","highway":"tertiary","points":[{"lat":55.490148,"lon":37.303017,"x":-17661.032,"z":-13086.794,"elevation":170.56},{"lat":55.48998,"lon":37.302639,"x":-17703.133,"z":-13119.902,"elevation":171.72}]},{"id":"road-12490","name":"Большая Октябрьская улица","highway":"secondary","points":[{"lat":55.49015,"lon":37.303542,"x":-17602.612,"z":-13086.479,"elevation":169.75},{"lat":55.48987,"lon":37.303986,"x":-17553.086,"z":-13141.456,"elevation":169.56}]},{"id":"road-13024","name":"улица Профессора Летохова","highway":"residential","points":[{"lat":55.486249,"lon":37.295315,"x":-18518.337,"z":-13852.978,"elevation":173.87},{"lat":55.485788,"lon":37.297146,"x":-18314.577,"z":-13943.437,"elevation":171.47},{"lat":55.485328,"lon":37.298976,"x":-18110.817,"z":-14033.896,"elevation":173.06},{"lat":55.484868,"lon":37.300807,"x":-17907.058,"z":-14124.355,"elevation":174.82},{"lat":55.484193,"lon":37.30238,"x":-17731.957,"z":-14256.926,"elevation":174.5},{"lat":55.483397,"lon":37.303807,"x":-17573.045,"z":-14413.284,"elevation":171.62}]},{"id":"road-13026","name":"Октябрьский проспект","highway":"secondary","points":[{"lat":55.483397,"lon":37.303807,"x":-17573.045,"z":-14413.284,"elevation":171.62},{"lat":55.483939,"lon":37.305518,"x":-17382.594,"z":-14306.881,"elevation":169.99},{"lat":55.484787,"lon":37.306292,"x":-17296.461,"z":-14140.169,"elevation":169.14}]},{"id":"road-13027","name":"улица Профессора Летохова","highway":"residential","points":[{"lat":55.483397,"lon":37.303807,"x":-17573.045,"z":-14413.284,"elevation":171.62},{"lat":55.484193,"lon":37.30238,"x":-17731.957,"z":-14256.926,"elevation":174.5},{"lat":55.484868,"lon":37.300807,"x":-17907.058,"z":-14124.355,"elevation":174.82},{"lat":55.485328,"lon":37.298976,"x":-18110.817,"z":-14033.896,"elevation":173.06},{"lat":55.485788,"lon":37.297146,"x":-18314.577,"z":-13943.437,"elevation":171.47},{"lat":55.486249,"lon":37.295315,"x":-18518.337,"z":-13852.978,"elevation":173.87}]},{"id":"road-13028","name":"Октябрьский проспект","highway":"secondary","points":[{"lat":55.483397,"lon":37.303807,"x":-17573.045,"z":-14413.284,"elevation":171.62},{"lat":55.482258,"lon":37.302902,"x":-17673.798,"z":-14637.098,"elevation":173.64},{"lat":55.481118,"lon":37.301997,"x":-17774.551,"z":-14860.911,"elevation":177.76},{"lat":55.479979,"lon":37.301092,"x":-17875.303,"z":-15084.725,"elevation":182.39},{"lat":55.47885,"lon":37.300154,"x":-17979.756,"z":-15306.487,"elevation":184.58},{"lat":55.477812,"lon":37.298927,"x":-18116.28,"z":-15510.46,"elevation":186.54},{"lat":55.476773,"lon":37.297701,"x":-18252.804,"z":-15714.432,"elevation":187.87},{"lat":55.475735,"lon":37.296474,"x":-18389.329,"z":-15918.405,"elevation":194.36}]}],"buildings":[{"id":"building-1000","name":"","building":"apartments","height":51.0,"heightSource":"building:levels","baseElevation":169.11,"lat":55.484958,"lon":37.304909,"x":-17450.418,"z":-14106.564,"footprint":[{"x":-17459.021,"z":-14006.516},{"x":-17492.995,"z":-14014.119},{"x":-17457.93,"z":-14178.341},{"x":-17479.403,"z":-14200.423},{"x":-17600.285,"z":-14241.11},{"x":-17589.387,"z":-14271.384},{"x":-17431.391,"z":-14211.857},{"x":-17426.682,"z":-14171.898},{"x":-17414.17,"z":-14168.715}]},{"id":"building-1028","name":"","building":"school","height":12.0,"heightSource":"default","baseElevation":168.14,"lat":55.487416,"lon":37.300366,"x":-17956.114,"z":-13623.755,"footprint":[{"x":-17943.127,"z":-13662.991},{"x":-17952.4,"z":-13683.797},{"x":-18017.188,"z":-13663.443},{"x":-18018.446,"z":-13627.862},{"x":-17977.87,"z":-13633.854},{"x":-17973.372,"z":-13560.137},{"x":-17928.922,"z":-13558.565},{"x":-17943.427,"z":-13654.7},{"x":-17854.772,"z":-13640.829},{"x":-17861.975,"z":-13611.299},{"x":-17899.879,"z":-13610.906},{"x":-17899.668,"z":-13590.983},{"x":-17803.154,"z":-13592.005},{"x":-17803.376,"z":-13612.301},{"x":-17847.37,"z":-13611.829},{"x":-17847.681,"z":-13640.613},{"x":-17788.682,"z":-13641.241},{"x":-17789.083,"z":-13679.102},{"x":-17910.9,"z":-13677.805},{"x":-17910.733,"z":-13662.402}]},{"id":"building-1302","name":"","building":"commercial","height":6.0,"heightSource":"building:levels","baseElevation":171.3,"lat":55.486579,"lon":37.304852,"x":-17456.677,"z":-13788.114,"footprint":[{"x":-17450.883,"z":-13891.053},{"x":-17373.794,"z":-13874.019},{"x":-17379.16,"z":-13849.775},{"x":-17362.518,"z":-13846.101},{"x":-17381.32,"z":-13761.6},{"x":-17403.639,"z":-13766.944},{"x":-17393.487,"z":-13809.283},{"x":-17433.128,"z":-13817.849},{"x":-17444.527,"z":-13766.315},{"x":-17383.913,"z":-13752.562},{"x":-17389.969,"z":-13724.133},{"x":-17483.244,"z":-13744.723}]},{"id":"building-2109","name":"","building":"apartments","height":51.0,"heightSource":"building:levels","baseElevation":172.58,"lat":55.485437,"lon":37.307523,"x":-17159.431,"z":-14012.4,"footprint":[{"x":-17259.837,"z":-14062.724},{"x":-17096.575,"z":-13959.777},{"x":-17159.794,"z":-13859.52},{"x":-17133.968,"z":-13843.233},{"x":-17059.027,"z":-13962.076},{"x":-17248.115,"z":-14081.309}]},{"id":"building-3434","name":"","building":"apartments","height":48.0,"heightSource":"building:levels","baseElevation":176.5,"lat":55.486678,"lon":37.307042,"x":-17212.956,"z":-13768.712,"footprint":[{"x":-17234.333,"z":-13775.255},{"x":-17255.851,"z":-13716.235},{"x":-17217.891,"z":-13708.14},{"x":-17169.523,"z":-13804.214},{"x":-17233.298,"z":-13833.213},{"x":-17248.816,"z":-13777.082}]},{"id":"building-3661","name":"","building":"kindergarten","height":12.0,"heightSource":"default","baseElevation":170.68,"lat":55.486323,"lon":37.302427,"x":-17726.633,"z":-13838.469,"footprint":[{"x":-17715.1,"z":-13884.059},{"x":-17737.464,"z":-13884.314},{"x":-17737.842,"z":-13849.638},{"x":-17769.624,"z":-13849.991},{"x":-17769.246,"z":-13883.587},{"x":-17791.443,"z":-13883.843},{"x":-17791.61,"z":-13813.625},{"x":-17769.424,"z":-13813.389},{"x":-17769.257,"z":-13827.81},{"x":-17682.261,"z":-13826.828},{"x":-17682.439,"z":-13811.68},{"x":-17662.334,"z":-13811.464},{"x":-17660.743,"z":-13880.817},{"x":-17680.836,"z":-13881.053},{"x":-17681.181,"z":-13849.166},{"x":-17715.478,"z":-13849.559}]},{"id":"building-3788","name":"","building":"yes","height":12.0,"heightSource":"default","baseElevation":171.59,"lat":55.48577,"lon":37.306503,"x":-17272.946,"z":-13947.036,"footprint":[{"x":-17326.495,"z":-13937.734},{"x":-17246.267,"z":-13906.26},{"x":-17219.394,"z":-13956.339},{"x":-17294.824,"z":-13996.791}]},{"id":"building-4792","name":"","building":"apartments","height":51.0,"heightSource":"building:levels","baseElevation":171.75,"lat":55.48526,"lon":37.303797,"x":-17574.187,"z":-14047.223,"footprint":[{"x":-17495.667,"z":-14046.457},{"x":-17646.427,"z":-14077.989},{"x":-17652.705,"z":-14047.989},{"x":-17501.945,"z":-14016.457}]},{"id":"building-5429","name":"","building":"apartments","height":27.0,"heightSource":"building:levels","baseElevation":172.77,"lat":55.486844,"lon":37.303494,"x":-17607.894,"z":-13736.069,"footprint":[{"x":-17531.779,"z":-13751.973},{"x":-17684.676,"z":-13748.338},{"x":-17684.008,"z":-13720.184},{"x":-17531.111,"z":-13723.799}]},{"id":"building-5702","name":"","building":"apartments","height":36.0,"heightSource":"building:levels","baseElevation":171.9,"lat":55.489125,"lon":37.303805,"x":-17573.335,"z":-13287.945,"footprint":[{"x":-17647.974,"z":-13303.202},{"x":-17498.149,"z":-13300.255},{"x":-17498.695,"z":-13272.688},{"x":-17648.52,"z":-13275.635}]},{"id":"building-5933","name":"","building":"yes","height":9.0,"heightSource":"building:levels","baseElevation":169.0,"lat":55.484448,"lon":37.305778,"x":-17353.68,"z":-14206.71,"footprint":[{"x":-17382.121,"z":-14191.013},{"x":-17393.008,"z":-14240.462},{"x":-17337.471,"z":-14229.696},{"x":-17314.183,"z":-14200.738},{"x":-17337.471,"z":-14171.485}]},{"id":"building-7113","name":"","building":"yes","height":12.0,"heightSource":"default","baseElevation":170.59,"lat":55.486765,"lon":37.31748,"x":-16051.003,"z":-13751.501,"footprint":[{"x":-16094.711,"z":-13747.042},{"x":-16041.2,"z":-13717.198},{"x":-16007.247,"z":-13755.961},{"x":-16048.068,"z":-13791.287}]},{"id":"building-8218","name":"","building":"apartments","height":36.0,"heightSource":"building:levels","baseElevation":171.3,"lat":55.488689,"lon":37.304983,"x":-17442.122,"z":-13373.473,"footprint":[{"x":-17408.749,"z":-13441.19},{"x":-17391.828,"z":-13429.774},{"x":-17475.496,"z":-13305.756},{"x":-17492.416,"z":-13317.172}]},{"id":"building-8228","name":"","building":"apartments","height":36.0,"heightSource":"building:levels","baseElevation":173.93,"lat":55.48793,"lon":37.305838,"x":-17346.919,"z":-13522.63,"footprint":[{"x":-17318.057,"z":-13586.307},{"x":-17300.001,"z":-13574.46},{"x":-17377.479,"z":-13456.358},{"x":-17395.535,"z":-13468.206}]},{"id":"building-9105","name":"","building":"apartments","height":45.0,"heightSource":"building:levels","baseElevation":172.78,"lat":55.486139,"lon":37.3039,"x":-17562.733,"z":-13874.491,"footprint":[{"x":-17549.423,"z":-13921.997},{"x":-17518.688,"z":-13915.494},{"x":-17527.794,"z":-13872.389},{"x":-17547.675,"z":-13876.593},{"x":-17557.349,"z":-13830.757},{"x":-17585.335,"z":-13836.671}]},{"id":"building-10004","name":"","building":"apartments","height":51.0,"heightSource":"building:levels","baseElevation":174.95,"lat":55.487263,"lon":37.3064,"x":-17284.42,"z":-13653.727,"footprint":[{"x":-17289.993,"z":-13696.313},{"x":-17262.453,"z":-13695.075},{"x":-17265.38,"z":-13629.826},{"x":-17306.056,"z":-13619.747}]},{"id":"building-10724","name":"","building":"apartments","height":48.0,"heightSource":"building:levels","baseElevation":175.0,"lat":55.486464,"lon":37.306467,"x":-17276.963,"z":-13810.727,"footprint":[{"x":-17272.605,"z":-13858.341},{"x":-17250.575,"z":-13854.117},{"x":-17262.92,"z":-13789.676},{"x":-17300.802,"z":-13780.677}]},{"id":"building-10743","name":"","building":"apartments","height":9.0,"heightSource":"building:levels","baseElevation":176.87,"lat":55.487528,"lon":37.311662,"x":-16698.629,"z":-13601.583,"footprint":[{"x":-16729.177,"z":-13576.7},{"x":-16701.959,"z":-13562.337},{"x":-16668.073,"z":-13626.467},{"x":-16695.302,"z":-13640.848}]},{"id":"building-11361","name":"","building":"apartments","height":9.0,"heightSource":"building:levels","baseElevation":177.94,"lat":55.487165,"lon":37.31203,"x":-16657.632,"z":-13672.923,"footprint":[{"x":-16687.487,"z":-13650.142},{"x":-16661.205,"z":-13635.544},{"x":-16627.776,"z":-13695.704},{"x":-16654.058,"z":-13710.301}]},{"id":"building-11598","name":"","building":"apartments","height":51.0,"heightSource":"building:levels","baseElevation":175.67,"lat":55.490047,"lon":37.301656,"x":-17812.505,"z":-13106.767,"footprint":[{"x":-17828.601,"z":-13135.68},{"x":-17796.118,"z":-13135.503},{"x":-17796.43,"z":-13073.884},{"x":-17828.913,"z":-13074.042}]},{"id":"building-11934","name":"","building":"yes","height":12.0,"heightSource":"default","baseElevation":174.58,"lat":55.488095,"lon":37.311585,"x":-16707.18,"z":-13490.191,"footprint":[{"x":-16727.562,"z":-13516.264},{"x":-16719.536,"z":-13459.502},{"x":-16686.797,"z":-13464.119},{"x":-16694.823,"z":-13520.881}]},{"id":"building-12110","name":"","building":"apartments","height":51.0,"heightSource":"building:levels","baseElevation":173.5,"lat":55.489143,"lon":37.30214,"x":-17758.676,"z":-13284.32,"footprint":[{"x":-17779.654,"z":-13304.813},{"x":-17779.654,"z":-13261.017},{"x":-17737.698,"z":-13261.017},{"x":-17737.698,"z":-13304.813}]},{"id":"building-12660","name":"","building":"yes","height":12.0,"heightSource":"default","baseElevation":172.66,"lat":55.48837,"lon":37.311165,"x":-16753.974,"z":-13436.278,"footprint":[{"x":-16773.927,"z":-13459.678},{"x":-16764.621,"z":-13407.415},{"x":-16734.019,"z":-13412.877},{"x":-16743.325,"z":-13465.121}]},{"id":"building-12662","name":"","building":"yes","height":12.0,"heightSource":"default","baseElevation":170.71,"lat":55.48696,"lon":37.317019,"x":-16102.255,"z":-13713.366,"footprint":[{"x":-16133.617,"z":-13704.152},{"x":-16094.155,"z":-13692.678},{"x":-16071.779,"z":-13721.441},{"x":-16103.461,"z":-13742.916}]},{"id":"building-13331","name":"","building":"apartments","height":36.0,"heightSource":"building:levels","baseElevation":173.45,"lat":55.488689,"lon":37.298768,"x":-18133.995,"z":-13373.66,"footprint":[{"x":-18147.231,"z":-13402.169},{"x":-18121.416,"z":-13402.464},{"x":-18120.759,"z":-13345.151},{"x":-18146.574,"z":-13344.856}]},{"id":"building-13377","name":"","building":"apartments","height":51.0,"heightSource":"building:levels","baseElevation":169.84,"lat":55.487703,"lon":37.298946,"x":-18114.194,"z":-13567.259,"footprint":[{"x":-18130.099,"z":-13590.964},{"x":-18128.663,"z":-13542.651},{"x":-18098.295,"z":-13543.554},{"x":-18099.72,"z":-13591.868}]},{"id":"building-14155","name":"","building":"apartments","height":36.0,"heightSource":"building:levels","baseElevation":172.57,"lat":55.486394,"lon":37.300816,"x":-17906.024,"z":-13824.539,"footprint":[{"x":-17893.601,"z":-13850.817},{"x":-17918.447,"z":-13850.817},{"x":-17918.447,"z":-13798.261},{"x":-17893.601,"z":-13798.261}]},{"id":"building-14292","name":"","building":"apartments","height":36.0,"heightSource":"building:levels","baseElevation":169.61,"lat":55.486462,"lon":37.299753,"x":-18024.387,"z":-13811.11,"footprint":[{"x":-18037.247,"z":-13785.059},{"x":-18035.789,"z":-13837.81},{"x":-18011.555,"z":-13837.162},{"x":-18012.957,"z":-13784.41}]},{"id":"building-14400","name":"","building":"yes","height":12.0,"heightSource":"default","baseElevation":170.4,"lat":55.488036,"lon":37.314754,"x":-16354.464,"z":-13501.901,"footprint":[{"x":-16370.372,"z":-13482.293},{"x":-16376.361,"z":-13514.456},{"x":-16338.556,"z":-13521.51},{"x":-16332.567,"z":-13489.346}]},{"id":"building-14490","name":"","building":"service","height":12.0,"heightSource":"default","baseElevation":168.5,"lat":55.4874,"lon":37.29888,"x":-18121.561,"z":-13626.85,"footprint":[{"x":-18147.776,"z":-13614.953},{"x":-18095.256,"z":-13615.13},{"x":-18095.345,"z":-13638.746},{"x":-18147.866,"z":-13638.569}]},{"id":"building-14509","name":"","building":"yes","height":12.0,"heightSource":"default","baseElevation":167.25,"lat":55.489092,"lon":37.313944,"x":-16444.639,"z":-13294.409,"footprint":[{"x":-16463.479,"z":-13279.192},{"x":-16423.126,"z":-13283.279},{"x":-16425.82,"z":-13309.823},{"x":-16456.021,"z":-13317.348}]},{"id":"building-14662","name":"","building":"apartments","height":36.0,"heightSource":"building:levels","baseElevation":169.82,"lat":55.486727,"lon":37.299531,"x":-18049.07,"z":-13759.036,"footprint":[{"x":-18037.247,"z":-13785.059},{"x":-18060.135,"z":-13785.393},{"x":-18060.892,"z":-13733.014},{"x":-18038.004,"z":-13732.68}]},{"id":"building-15052","name":"","building":"yes","height":6.0,"heightSource":"building:levels","baseElevation":170.85,"lat":55.484613,"lon":37.307419,"x":-17171.004,"z":-14174.461,"footprint":[{"x":-17193.958,"z":-14168.499},{"x":-17166.072,"z":-14151.269},{"x":-17148.05,"z":-14180.424},{"x":-17175.935,"z":-14197.653}]},{"id":"building-16087","name":"","building":"yes","height":6.0,"heightSource":"building:levels","baseElevation":173.56,"lat":55.484536,"lon":37.309356,"x":-16955.361,"z":-14189.599,"footprint":[{"x":-16977.775,"z":-14187.045},{"x":-16950.19,"z":-14167.634},{"x":-16927.949,"z":-14199.264},{"x":-16942.409,"z":-14209.421}]},{"id":"building-16334","name":"","building":"yes","height":12.0,"heightSource":"default","baseElevation":163.88,"lat":55.487548,"lon":37.320872,"x":-15673.437,"z":-13597.654,"footprint":[{"x":-15688.851,"z":-13582.456},{"x":-15656.346,"z":-13584.382},{"x":-15658.016,"z":-13612.831},{"x":-15690.532,"z":-13610.926}]},{"id":"building-16376","name":"","building":"civic","height":6.0,"heightSource":"building:levels","baseElevation":168.41,"lat":55.487977,"lon":37.31553,"x":-16268.102,"z":-13513.484,"footprint":[{"x":-16274.692,"z":-13502.825},{"x":-16284.043,"z":-13534.025},{"x":-16245.059,"z":-13539.743},{"x":-16241.942,"z":-13524.142}]},{"id":"building-16857","name":"","building":"service","height":12.0,"heightSource":"default","baseElevation":173.81,"lat":55.485939,"lon":37.307271,"x":-17187.496,"z":-13913.833,"footprint":[{"x":-17206.915,"z":-13905.179},{"x":-17184.907,"z":-13892.723},{"x":-17168.076,"z":-13922.488},{"x":-17190.084,"z":-13934.944}]},{"id":"building-17211","name":"","building":"yes","height":6.0,"heightSource":"building:levels","baseElevation":172.94,"lat":55.487525,"lon":37.309492,"x":-16940.183,"z":-13602.182,"footprint":[{"x":-16956.959,"z":-13590.139},{"x":-16932.969,"z":-13582.83},{"x":-16923.407,"z":-13614.226},{"x":-16947.396,"z":-13621.535}]},{"id":"building-17567","name":"","building":"yes","height":6.0,"heightSource":"building:levels","baseElevation":174.11,"lat":55.484883,"lon":37.311465,"x":-16720.572,"z":-14121.279,"footprint":[{"x":-16741.533,"z":-14117.871},{"x":-16714.327,"z":-14100.975},{"x":-16699.61,"z":-14124.688},{"x":-16725.024,"z":-14136.044}]},{"id":"building-18639","name":"","building":"yes","height":12.0,"heightSource":"default","baseElevation":172.6,"lat":55.489452,"lon":37.300939,"x":-17892.276,"z":-13223.646,"footprint":[{"x":-17911.011,"z":-13224.884},{"x":-17896.016,"z":-13242.037},{"x":-17873.541,"z":-13222.408},{"x":-17888.525,"z":-13205.255}]},{"id":"building-18756","name":"","building":"yes","height":6.0,"heightSource":"building:levels","baseElevation":172.15,"lat":55.486882,"lon":37.309074,"x":-16986.734,"z":-13728.563,"footprint":[{"x":-17012.073,"z":-13707.571},{"x":-16998.28,"z":-13704.289},{"x":-16971.508,"z":-13733.269},{"x":-16989.275,"z":-13744.291}]},{"id":"building-18758","name":"","building":"yes","height":12.0,"heightSource":"default","baseElevation":161.43,"lat":55.489404,"lon":37.321067,"x":-15651.679,"z":-13233.067,"footprint":[{"x":-15667.534,"z":-13244.689},{"x":-15663.17,"z":-13218.832},{"x":-15636.153,"z":-13223.39},{"x":-15639.715,"z":-13244.512}]},{"id":"building-18860","name":"","building":"yes","height":12.0,"heightSource":"default","baseElevation":171.97,"lat":55.487825,"lon":37.314728,"x":-16357.374,"z":-13543.348,"footprint":[{"x":-16369.926,"z":-13529.801},{"x":-16373.667,"z":-13552.042},{"x":-16344.813,"z":-13556.875},{"x":-16341.083,"z":-13534.654}]},{"id":"building-19043","name":"","building":"yes","height":12.0,"heightSource":"default","baseElevation":163.6,"lat":55.489052,"lon":37.318572,"x":-15929.465,"z":-13302.327,"footprint":[{"x":-15942.849,"z":-13314.539},{"x":-15938.775,"z":-13286.796},{"x":-15916.077,"z":-13290.116},{"x":-15920.162,"z":-13317.879}]},{"id":"building-19216","name":"","building":"yes","height":6.0,"heightSource":"building:levels","baseElevation":172.14,"lat":55.487026,"lon":37.310557,"x":-16821.604,"z":-13700.321,"footprint":[{"x":-16838.826,"z":-13695.743},{"x":-16819.323,"z":-13682.638},{"x":-16804.384,"z":-13704.899},{"x":-16823.887,"z":-13717.984}]},{"id":"building-19320","name":"","building":"yes","height":6.0,"heightSource":"building:levels","baseElevation":174.34,"lat":55.485101,"lon":37.311849,"x":-16677.828,"z":-14078.412,"footprint":[{"x":-16689.024,"z":-14089.129},{"x":-16678.226,"z":-14064.335},{"x":-16660.492,"z":-14092.488},{"x":-16679.417,"z":-14104.394}]},{"id":"building-19432","name":"","building":"yes","height":6.0,"heightSource":"building:levels","baseElevation":174.08,"lat":55.484724,"lon":37.311029,"x":-16769.085,"z":-14152.536,"footprint":[{"x":-16785.749,"z":-14146.652},{"x":-16766.758,"z":-14135.022},{"x":-16752.42,"z":-14158.42},{"x":-16771.411,"z":-14170.051}]},{"id":"building-19471","name":"","building":"yes","height":12.0,"heightSource":"default","baseElevation":173.46,"lat":55.485175,"lon":37.311021,"x":-16770.021,"z":-14064.031,"footprint":[{"x":-16786.417,"z":-14057.636},{"x":-16767.07,"z":-14046.673},{"x":-16753.622,"z":-14070.425},{"x":-16772.981,"z":-14081.388}]},{"id":"building-19487","name":"","building":"yes","height":6.0,"heightSource":"building:levels","baseElevation":171.83,"lat":55.488176,"lon":37.30648,"x":-17275.444,"z":-13474.434,"footprint":[{"x":-17290.305,"z":-13465.416},{"x":-17261.54,"z":-13460.582},{"x":-17264.534,"z":-13487.5},{"x":-17277.637,"z":-13490.899}]},{"id":"building-19502","name":"","building":"yes","height":12.0,"heightSource":"default","baseElevation":164.29,"lat":55.487813,"lon":37.319902,"x":-15781.322,"z":-13545.686,"footprint":[{"x":-15793.826,"z":-13533.495},{"x":-15767.476,"z":-13535.047},{"x":-15768.812,"z":-13557.877},{"x":-15795.173,"z":-13556.325}]},{"id":"building-19562","name":"","building":"yes","height":6.0,"heightSource":"building:levels","baseElevation":171.87,"lat":55.487969,"lon":37.309351,"x":-16955.923,"z":-13514.987,"footprint":[{"x":-16974.836,"z":-13512.256},{"x":-16942.832,"z":-13501.056},{"x":-16937.01,"z":-13517.718},{"x":-16969.014,"z":-13528.917}]},{"id":"building-19670","name":"","building":"yes","height":6.0,"heightSource":"building:levels","baseElevation":171.0,"lat":55.48839,"lon":37.307894,"x":-17118.084,"z":-13432.338,"footprint":[{"x":-17136.528,"z":-13428.222},{"x":-17112.027,"z":-13423.939},{"x":-17099.692,"z":-13436.14},{"x":-17133.044,"z":-13448.165}]},{"id":"building-19698","name":"","building":"yes","height":6.0,"heightSource":"building:levels","baseElevation":171.88,"lat":55.486329,"lon":37.308636,"x":-17035.444,"z":-13837.28,"footprint":[{"x":-17051.124,"z":-13826.612},{"x":-17035.806,"z":-13818.321},{"x":-17019.765,"z":-13847.948},{"x":-17035.083,"z":-13856.239}]},{"id":"building-19803","name":"","building":"yes","height":6.0,"heightSource":"building:levels","baseElevation":172.08,"lat":55.486141,"lon":37.308915,"x":-17004.444,"z":-13874.275,"footprint":[{"x":-17022.047,"z":-13869.461},{"x":-16995.186,"z":-13863.783},{"x":-16986.837,"z":-13879.088},{"x":-17009.947,"z":-13891.682}]},{"id":"building-19816","name":"","building":"detached","height":6.0,"heightSource":"building:levels","baseElevation":173.66,"lat":55.486145,"lon":37.311636,"x":-16701.53,"z":-13873.351,"footprint":[{"x":-16718.523,"z":-13870.935},{"x":-16695.736,"z":-13857.202},{"x":-16684.537,"z":-13875.768},{"x":-16707.325,"z":-13889.501}]},{"id":"building-19844","name":"","building":"yes","height":6.0,"heightSource":"building:levels","baseElevation":173.0,"lat":55.485007,"lon":37.308483,"x":-17052.532,"z":-14097.026,"footprint":[{"x":-17068.857,"z":-14086.221},{"x":-17055.22,"z":-14077.636},{"x":-17036.207,"z":-14107.832},{"x":-17049.843,"z":-14116.417}]},{"id":"building-19869","name":"","building":"yes","height":6.0,"heightSource":"building:levels","baseElevation":172.44,"lat":55.487033,"lon":37.309485,"x":-16941.032,"z":-13698.995,"footprint":[{"x":-16958.662,"z":-13694.466},{"x":-16938.747,"z":-13680.929},{"x":-16923.407,"z":-13703.523},{"x":-16948.431,"z":-13709.516}]},{"id":"building-19954","name":"","building":"yes","height":12.0,"heightSource":"default","baseElevation":168.51,"lat":55.486427,"lon":37.320374,"x":-15728.837,"z":-13818.006,"footprint":[{"x":-15729.85,"z":-13834.844},{"x":-15712.151,"z":-13820.423},{"x":-15727.824,"z":-13801.169},{"x":-15745.524,"z":-13815.59}]},{"id":"building-19968","name":"","building":"yes","height":6.0,"heightSource":"building:levels","baseElevation":170.28,"lat":55.489503,"lon":37.308152,"x":-17089.345,"z":-13213.547,"footprint":[{"x":-17105.526,"z":-13204.98},{"x":-17073.432,"z":-13204.489},{"x":-17073.165,"z":-13222.113},{"x":-17105.258,"z":-13222.585}]},{"id":"building-19978","name":"","building":"yes","height":6.0,"heightSource":"building:levels","baseElevation":171.88,"lat":55.485923,"lon":37.309282,"x":-16963.546,"z":-13917.006,"footprint":[{"x":-16977.23,"z":-13912.173},{"x":-16956.691,"z":-13900.169},{"x":-16950.747,"z":-13930.287},{"x":-16962.591,"z":-13937.203}]},{"id":"building-19984","name":"","building":"yes","height":6.0,"heightSource":"building:levels","baseElevation":172.8,"lat":55.485212,"lon":37.309004,"x":-16994.501,"z":-14056.722,"footprint":[{"x":-16994.584,"z":-14074.414},{"x":-16978.61,"z":-14064.492},{"x":-16994.418,"z":-14039.031},{"x":-17010.392,"z":-14048.952}]},{"id":"building-20108","name":"","building":"yes","height":6.0,"heightSource":"building:levels","baseElevation":171.52,"lat":55.487902,"lon":37.308227,"x":-17080.976,"z":-13528.151,"footprint":[{"x":-17094.215,"z":-13515.262},{"x":-17078.185,"z":-13509.878},{"x":-17067.744,"z":-13541.039},{"x":-17083.763,"z":-13546.403}]},{"id":"building-20144","name":"","building":"detached","height":6.0,"heightSource":"building:levels","baseElevation":166.53,"lat":55.488593,"lon":37.315963,"x":-16219.84,"z":-13392.414,"footprint":[{"x":-16229.118,"z":-13378.611},{"x":-16206.443,"z":-13382.56},{"x":-16210.561,"z":-13406.217},{"x":-16233.237,"z":-13402.267}]},{"id":"building-20356","name":"","building":"yes","height":12.0,"heightSource":"default","baseElevation":162.44,"lat":55.488781,"lon":37.320041,"x":-15765.87,"z":-13355.476,"footprint":[{"x":-15779.209,"z":-13365.722},{"x":-15777.473,"z":-13344.129},{"x":-15753.617,"z":-13346.035},{"x":-15756.211,"z":-13367.569}]},{"id":"building-20473","name":"","building":"yes","height":12.0,"heightSource":"default","baseElevation":165.06,"lat":55.487739,"lon":37.318878,"x":-15895.368,"z":-13560.304,"footprint":[{"x":-15906.648,"z":-13548.643},{"x":-15883.538,"z":-13549.193},{"x":-15884.095,"z":-13571.965},{"x":-15907.193,"z":-13571.415}]},{"id":"building-20620","name":"","building":"detached","height":6.0,"heightSource":"building:levels","baseElevation":171.23,"lat":55.488415,"lon":37.310302,"x":-16850.076,"z":-13427.485,"footprint":[{"x":-16863.561,"z":-13418.791},{"x":-16840.563,"z":-13414.567},{"x":-16836.589,"z":-13436.18},{"x":-16859.587,"z":-13440.424}]},{"id":"building-20649","name":"","building":"yes","height":6.0,"heightSource":"building:levels","baseElevation":172.59,"lat":55.48517,"lon":37.309996,"x":-16884.055,"z":-14064.993,"footprint":[{"x":-16899.317,"z":-14059.266},{"x":-16882.619,"z":-14048.756},{"x":-16868.793,"z":-14070.72},{"x":-16885.491,"z":-14081.231}]},{"id":"building-20670","name":"","building":"yes","height":6.0,"heightSource":"building:levels","baseElevation":169.28,"lat":55.489017,"lon":37.30656,"x":-17266.624,"z":-13309.126,"footprint":[{"x":-17281.767,"z":-13302.809},{"x":-17255.785,"z":-13296.797},{"x":-17251.488,"z":-13315.443},{"x":-17277.458,"z":-13321.435}]},{"id":"building-20696","name":"","building":"yes","height":6.0,"heightSource":"building:levels","baseElevation":170.67,"lat":55.488612,"lon":37.309364,"x":-16954.404,"z":-13388.74,"footprint":[{"x":-16968.168,"z":-13380.714},{"x":-16946.016,"z":-13375.192},{"x":-16940.639,"z":-13396.766},{"x":-16962.792,"z":-13402.287}]},{"id":"building-20816","name":"","building":"yes","height":12.0,"heightSource":"default","baseElevation":165.86,"lat":55.487399,"lon":37.318814,"x":-15902.49,"z":-13627.066,"footprint":[{"x":-15916.355,"z":-13635.328},{"x":-15914.496,"z":-13616.289},{"x":-15888.625,"z":-13618.804},{"x":-15890.484,"z":-13637.842}]},{"id":"building-20865","name":"","building":"yes","height":12.0,"heightSource":"default","baseElevation":166.5,"lat":55.489028,"lon":37.314857,"x":-16342.948,"z":-13306.935,"footprint":[{"x":-16352.917,"z":-13319.431},{"x":-16352.316,"z":-13293.967},{"x":-16332.979,"z":-13294.439},{"x":-16333.58,"z":-13319.883}]},{"id":"building-21040","name":"","building":"yes","height":6.0,"heightSource":"building:levels","baseElevation":173.47,"lat":55.485348,"lon":37.31155,"x":-16711.131,"z":-14030.052,"footprint":[{"x":-16726.182,"z":-14026.418},{"x":-16707.926,"z":-14014.905},{"x":-16696.081,"z":-14033.687},{"x":-16714.327,"z":-14045.2}]},{"id":"building-21072","name":"","building":"yes","height":12.0,"heightSource":"default","baseElevation":163.3,"lat":55.48942,"lon":37.318568,"x":-15929.919,"z":-13229.963,"footprint":[{"x":-15939.509,"z":-13217.692},{"x":-15919.75,"z":-13218.164},{"x":-15920.329,"z":-13242.233},{"x":-15940.088,"z":-13241.762}]},{"id":"building-21076","name":"","building":"detached","height":6.0,"heightSource":"building:levels","baseElevation":171.56,"lat":55.486053,"lon":37.309664,"x":-16921.108,"z":-13891.397,"footprint":[{"x":-16937.244,"z":-13888.008},{"x":-16915.781,"z":-13875.788},{"x":-16904.972,"z":-13894.786},{"x":-16929.897,"z":-13900.916}]},{"id":"building-21146","name":"","building":"yes","height":12.0,"heightSource":"default","baseElevation":162.29,"lat":55.48938,"lon":37.319146,"x":-15865.482,"z":-13237.793,"footprint":[{"x":-15874.454,"z":-13224.903},{"x":-15855.897,"z":-13225.355},{"x":-15856.51,"z":-13250.682},{"x":-15875.067,"z":-13250.23}]},{"id":"building-21167","name":"","building":"yes","height":12.0,"heightSource":"default","baseElevation":163.69,"lat":55.489428,"lon":37.318101,"x":-15981.811,"z":-13228.273,"footprint":[{"x":-15991.863,"z":-13216.69},{"x":-15971.213,"z":-13217.182},{"x":-15971.759,"z":-13239.856},{"x":-15992.409,"z":-13239.365}]},{"id":"building-21209","name":"","building":"yes","height":12.0,"heightSource":"default","baseElevation":163.98,"lat":55.488424,"lon":37.319015,"x":-15880.059,"z":-13425.727,"footprint":[{"x":-15891.642,"z":-13415.608},{"x":-15867.998,"z":-13416.178},{"x":-15868.477,"z":-13435.846},{"x":-15892.121,"z":-13435.276}]},{"id":"building-21272","name":"","building":"yes","height":12.0,"heightSource":"default","baseElevation":164.04,"lat":55.48913,"lon":37.317529,"x":-16045.51,"z":-13286.923,"footprint":[{"x":-16054.859,"z":-13274.948},{"x":-16034.064,"z":-13276.932},{"x":-16036.168,"z":-13298.899},{"x":-16056.952,"z":-13296.914}]},{"id":"building-21297","name":"","building":"yes","height":12.0,"heightSource":"default","baseElevation":164.72,"lat":55.487684,"lon":37.319376,"x":-15839.923,"z":-13571.002,"footprint":[{"x":-15851.2,"z":-13560.648},{"x":-15827.511,"z":-13562.043},{"x":-15828.646,"z":-13581.356},{"x":-15852.335,"z":-13579.961}]},{"id":"building-21305","name":"","building":"yes","height":6.0,"heightSource":"building:levels","baseElevation":172.15,"lat":55.486831,"lon":37.310195,"x":-16861.919,"z":-13738.544,"footprint":[{"x":-16874.961,"z":-13732.699},{"x":-16853.988,"z":-13718.946},{"x":-16847.476,"z":-13728.868},{"x":-16862.727,"z":-13751.364}]},{"id":"building-21320","name":"","building":"yes","height":6.0,"heightSource":"building:levels","baseElevation":172.47,"lat":55.487804,"lon":37.306953,"x":-17222.898,"z":-13547.454,"footprint":[{"x":-17236.604,"z":-13541.059},{"x":-17216.311,"z":-13533.829},{"x":-17209.197,"z":-13553.85},{"x":-17229.48,"z":-13561.06}]},{"id":"building-21326","name":"","building":"detached","height":6.0,"heightSource":"building:levels","baseElevation":170.84,"lat":55.488702,"lon":37.307345,"x":-17179.172,"z":-13371.007,"footprint":[{"x":-17192.177,"z":-13363.227},{"x":-17170.224,"z":-13358.786},{"x":-17166.172,"z":-13378.788},{"x":-17188.113,"z":-13383.228}]},{"id":"building-21331","name":"","building":"yes","height":12.0,"heightSource":"default","baseElevation":161.85,"lat":55.489011,"lon":37.320988,"x":-15660.491,"z":-13310.354,"footprint":[{"x":-15673.712,"z":-13317.899},{"x":-15670.15,"z":-13298.584},{"x":-15647.274,"z":-13302.809},{"x":-15650.825,"z":-13322.103}]},{"id":"building-21347","name":"","building":"yes","height":12.0,"heightSource":"default","baseElevation":166.43,"lat":55.489242,"lon":37.314524,"x":-16380.004,"z":-13264.986,"footprint":[{"x":-16389.274,"z":-13253.04},{"x":-16368.657,"z":-13255.005},{"x":-16370.739,"z":-13276.912},{"x":-16391.344,"z":-13274.967}]},{"id":"building-21369","name":"","building":"yes","height":6.0,"heightSource":"building:levels","baseElevation":171.8,"lat":55.486504,"lon":37.310543,"x":-16823.214,"z":-13802.79,"footprint":[{"x":-16837.624,"z":-13798.379},{"x":-16819.267,"z":-13788.241},{"x":-16808.803,"z":-13807.201},{"x":-16827.16,"z":-13817.338}]},{"id":"building-21439","name":"","building":"yes","height":12.0,"heightSource":"default","baseElevation":166.34,"lat":55.487646,"lon":37.317809,"x":-16014.338,"z":-13578.527,"footprint":[{"x":-16024.391,"z":-13567.406},{"x":-16003.763,"z":-13567.898},{"x":-16004.286,"z":-13589.647},{"x":-16024.914,"z":-13589.156}]},{"id":"building-21494","name":"","building":"detached","height":6.0,"heightSource":"building:levels","baseElevation":172.26,"lat":55.487628,"lon":37.310517,"x":-16826.079,"z":-13582.054,"footprint":[{"x":-16843.012,"z":-13582.987},{"x":-16816.039,"z":-13568.389},{"x":-16809.148,"z":-13581.12},{"x":-16836.121,"z":-13595.738}]},{"id":"building-21527","name":"","building":"yes","height":12.0,"heightSource":"default","baseElevation":161.16,"lat":55.489589,"lon":37.321112,"x":-15646.647,"z":-13196.826,"footprint":[{"x":-15653.363,"z":-13182.659},{"x":-15636.91,"z":-13184.526},{"x":-15639.926,"z":-13211.012},{"x":-15656.391,"z":-13209.126}]},{"id":"building-23332","name":"","building":"yes","height":12.0,"heightSource":"default","baseElevation":164.59,"lat":55.487402,"lon":37.320636,"x":-15699.666,"z":-13626.339,"footprint":[{"x":-15704.959,"z":-13615.287},{"x":-15693.115,"z":-13615.995},{"x":-15694.373,"z":-13637.391},{"x":-15706.217,"z":-13636.683}]},{"id":"building-23336","name":"","building":"yes","height":12.0,"heightSource":"default","baseElevation":163.39,"lat":55.487816,"lon":37.320706,"x":-15691.846,"z":-13545.028,"footprint":[{"x":-15700.974,"z":-13537.817},{"x":-15681.938,"z":-13538.937},{"x":-15682.718,"z":-13552.239},{"x":-15701.753,"z":-13551.119}]},{"id":"building-23525","name":"","building":"yes","height":12.0,"heightSource":"default","baseElevation":162.39,"lat":55.488169,"lon":37.320916,"x":-15668.524,"z":-13475.711,"footprint":[{"x":-15678.977,"z":-13479.876},{"x":-15676.551,"z":-13467.832},{"x":-15658.072,"z":-13471.546},{"x":-15660.498,"z":-13483.59}]},{"id":"building-23761","name":"","building":"yes","height":12.0,"heightSource":"default","baseElevation":161.9,"lat":55.489275,"lon":37.320644,"x":-15698.748,"z":-13258.365,"footprint":[{"x":-15705.271,"z":-13250.623},{"x":-15691.367,"z":-13251.429},{"x":-15692.224,"z":-13266.106},{"x":-15706.128,"z":-13265.3}]},{"id":"building-23928","name":"","building":"yes","height":12.0,"heightSource":"default","baseElevation":162.19,"lat":55.488842,"lon":37.320426,"x":-15722.987,"z":-13343.579,"footprint":[{"x":-15730.273,"z":-13349.67},{"x":-15715.702,"z":-13337.488},{"x":-15716.47,"z":-13350.495}]},{"id":"building-23970","name":"","building":"yes","height":12.0,"heightSource":"default","baseElevation":161.88,"lat":55.488637,"lon":37.321118,"x":-15646.049,"z":-13383.788,"footprint":[{"x":-15652.706,"z":-13390.42},{"x":-15639.392,"z":-13377.157},{"x":-15640.216,"z":-13391.147}]},{"id":"building-24074","name":"","building":"yes","height":12.0,"heightSource":"default","baseElevation":164.22,"lat":55.487576,"lon":37.320495,"x":-15715.321,"z":-13592.202,"footprint":[{"x":-15722.125,"z":-13598.115},{"x":-15708.522,"z":-13586.288},{"x":-15709.256,"z":-13598.882}]},{"id":"building-24085","name":"","building":"yes","height":12.0,"heightSource":"default","baseElevation":163.66,"lat":55.487709,"lon":37.320699,"x":-15692.689,"z":-13566.198,"footprint":[{"x":-15700.952,"z":-13570.786},{"x":-15684.421,"z":-13561.61},{"x":-15685.022,"z":-13571.729}]},{"id":"building-24096","name":"","building":"yes","height":12.0,"heightSource":"default","baseElevation":161.63,"lat":55.489238,"lon":37.321068,"x":-15651.62,"z":-13265.762,"footprint":[{"x":-15645.815,"z":-13272.61},{"x":-15657.426,"z":-13258.934},{"x":-15644.902,"z":-13259.819}]},{"id":"building-24195","name":"","building":"yes","height":12.0,"heightSource":"default","baseElevation":162.2,"lat":55.488249,"lon":37.32105,"x":-15653.524,"z":-13460.012,"footprint":[{"x":-15661.522,"z":-13464.315},{"x":-15645.526,"z":-13455.71},{"x":-15646.082,"z":-13465.239}]},{"id":"building-24299","name":"","building":"yes","height":12.0,"heightSource":"default","baseElevation":161.65,"lat":55.48947,"lon":37.320812,"x":-15680.029,"z":-13220.158,"footprint":[{"x":-15687.126,"z":-13224.648},{"x":-15672.933,"z":-13215.669},{"x":-15673.512,"z":-13225.454}]},{"id":"building-24411","name":"","building":"yes","height":12.0,"heightSource":"default","baseElevation":162.18,"lat":55.488593,"lon":37.320612,"x":-15702.279,"z":-13392.375,"footprint":[{"x":-15708.755,"z":-13396.864},{"x":-15695.798,"z":-13387.885},{"x":-15696.377,"z":-13397.591}]},{"id":"building-24476","name":"","building":"yes","height":12.0,"heightSource":"default","baseElevation":161.8,"lat":55.489404,"lon":37.320583,"x":-15705.594,"z":-13233.028,"footprint":[{"x":-15711.138,"z":-13238.087},{"x":-15700.05,"z":-13227.969},{"x":-15700.685,"z":-13238.697}]}]}