{"id":"33_48","col":33,"row":48,"bounds":{"minX":26851.96,"minZ":41889.318,"maxX":29351.96,"maxZ":44389.318},"roads":[{"id":"road-18240","name":"проспект Будённого","highway":"secondary","points":[{"lat":55.778807,"lon":37.72074,"x":28839.713,"z":43840.092,"elevation":145.16},{"lat":55.779414,"lon":37.72078,"x":28844.199,"z":43960.243,"elevation":145.17}]},{"id":"road-19144","name":"Гольяновская улица","highway":"tertiary","points":[{"lat":55.777037,"lon":37.702801,"x":26842.697,"z":43489.567,"elevation":129.46},{"lat":55.777021,"lon":37.703173,"x":26884.219,"z":43486.44,"elevation":130.37}]},{"id":"road-19145","name":"Семёновская набережная","highway":"secondary","points":[{"lat":55.777037,"lon":37.702801,"x":26842.697,"z":43489.567,"elevation":129.46},{"lat":55.777156,"lon":37.702916,"x":26855.588,"z":43513.141,"elevation":129.15}]},{"id":"road-21961","name":"Боровая улица","highway":"tertiary","points":[{"lat":55.766496,"lon":37.717579,"x":28487.854,"z":41403.515,"elevation":147.8},{"lat":55.767673,"lon":37.717151,"x":28440.237,"z":41636.474,"elevation":147.2},{"lat":55.768825,"lon":37.716593,"x":28378.04,"z":41864.511,"elevation":148.05},{"lat":55.769908,"lon":37.715664,"x":28274.702,"z":42078.657,"elevation":150.82},{"lat":55.77099,"lon":37.714736,"x":28171.363,"z":42292.803,"elevation":151.81},{"lat":55.772072,"lon":37.713808,"x":28068.025,"z":42506.949,"elevation":150.28},{"lat":55.773154,"lon":37.71288,"x":27964.687,"z":42721.095,"elevation":148.65},{"lat":55.774236,"lon":37.711951,"x":27861.348,"z":42935.241,"elevation":146.56}]},{"id":"road-21964","name":"Ухтомская улица","highway":"residential","points":[{"lat":55.767542,"lon":37.715234,"x":28226.766,"z":41610.577,"elevation":148.99},{"lat":55.768541,"lon":37.714405,"x":28134.497,"z":41808.257,"elevation":149.86},{"lat":55.76954,"lon":37.713576,"x":28042.228,"z":42005.936,"elevation":150.37},{"lat":55.770539,"lon":37.712747,"x":27949.959,"z":42203.616,"elevation":150.39}]},{"id":"road-21969","name":"Княжекозловский переулок","highway":"residential","points":[{"lat":55.76968,"lon":37.712097,"x":27877.612,"z":42033.544,"elevation":149.93},{"lat":55.770478,"lon":37.711226,"x":27780.653,"z":42191.445,"elevation":148.63}]},{"id":"road-21970","name":"Лонгиновская улица","highway":"residential","points":[{"lat":55.76968,"lon":37.712097,"x":27877.612,"z":42033.544,"elevation":149.93},{"lat":55.768781,"lon":37.711436,"x":27803.974,"z":41855.679,"elevation":148.69}]},{"id":"road-21971","name":"Лонгиновская улица","highway":"residential","points":[{"lat":55.76968,"lon":37.712097,"x":27877.612,"z":42033.544,"elevation":149.93},{"lat":55.770539,"lon":37.712747,"x":27949.959,"z":42203.616,"elevation":150.39}]},{"id":"road-21973","name":"Лонгиновская улица","highway":"residential","points":[{"lat":55.768781,"lon":37.711436,"x":27803.974,"z":41855.679,"elevation":148.69},{"lat":55.76968,"lon":37.712097,"x":27877.612,"z":42033.544,"elevation":149.93}]},{"id":"road-21974","name":"Крюковская улица","highway":"residential","points":[{"lat":55.768781,"lon":37.711436,"x":27803.974,"z":41855.679,"elevation":148.69},{"lat":55.769381,"lon":37.71073,"x":27725.377,"z":41974.385,"elevation":149.87},{"lat":55.769981,"lon":37.710024,"x":27646.78,"z":42093.091,"elevation":149.99}]},{"id":"road-21978","name":"улица Госпитальный Вал","highway":"secondary","points":[{"lat":55.77354,"lon":37.71013,"x":27658.635,"z":42797.552,"elevation":147.03},{"lat":55.774412,"lon":37.711816,"x":27846.242,"z":42970.213,"elevation":147.15}]},{"id":"road-21979","name":"улица Госпитальный Вал","highway":"secondary","points":[{"lat":55.77354,"lon":37.71013,"x":27658.635,"z":42797.552,"elevation":147.03},{"lat":55.772863,"lon":37.70877,"x":27507.23,"z":42663.576,"elevation":149.55},{"lat":55.772186,"lon":37.70741,"x":27355.824,"z":42529.601,"elevation":147.82}]},{"id":"road-21980","name":"Ухтомская улица","highway":"residential","points":[{"lat":55.77354,"lon":37.71013,"x":27658.635,"z":42797.552,"elevation":147.03},{"lat":55.77254,"lon":37.711003,"x":27755.743,"z":42599.573,"elevation":147.4},{"lat":55.771539,"lon":37.711875,"x":27852.851,"z":42401.595,"elevation":146.98},{"lat":55.770539,"lon":37.712747,"x":27949.959,"z":42203.616,"elevation":150.39}]},{"id":"road-21992","name":"улица Госпитальный Вал","highway":"secondary","points":[{"lat":55.774412,"lon":37.711816,"x":27846.242,"z":42970.213,"elevation":147.15},{"lat":55.77354,"lon":37.71013,"x":27658.635,"z":42797.552,"elevation":147.03}]},{"id":"road-21993","name":"Боровая улица","highway":"tertiary","points":[{"lat":55.774412,"lon":37.711816,"x":27846.242,"z":42970.213,"elevation":147.15},{"lat":55.774236,"lon":37.711951,"x":27861.348,"z":42935.241,"elevation":146.56}]},{"id":"road-21994","name":"Гольяновская улица","highway":"tertiary","points":[{"lat":55.774412,"lon":37.711816,"x":27846.242,"z":42970.213,"elevation":147.15},{"lat":55.775036,"lon":37.710188,"x":27665.1,"z":43093.548,"elevation":151.85},{"lat":55.775654,"lon":37.708556,"x":27483.394,"z":43215.877,"elevation":146.18},{"lat":55.776109,"lon":37.706762,"x":27283.669,"z":43306.065,"elevation":141.15},{"lat":55.776565,"lon":37.704968,"x":27083.944,"z":43396.252,"elevation":140.57},{"lat":55.777021,"lon":37.703173,"x":26884.219,"z":43486.44,"elevation":130.37}]},{"id":"road-21995","name":"улица Госпитальный Вал","highway":"secondary","points":[{"lat":55.774412,"lon":37.711816,"x":27846.242,"z":42970.213,"elevation":147.15},{"lat":55.7745,"lon":37.712174,"x":27886.139,"z":42987.432,"elevation":147.23}]},{"id":"road-22000","name":"улица Госпитальный Вал","highway":"secondary","points":[{"lat":55.770029,"lon":37.702518,"x":26811.305,"z":42102.689,"elevation":138.02},{"lat":55.770626,"lon":37.704311,"x":27010.807,"z":42220.751,"elevation":143.48},{"lat":55.771394,"lon":37.705876,"x":27185.078,"z":42372.803,"elevation":147.34},{"lat":55.772186,"lon":37.70741,"x":27355.824,"z":42529.601,"elevation":147.82}]},{"id":"road-22001","name":"Княжекозловский переулок","highway":"residential","points":[{"lat":55.772531,"lon":37.709054,"x":27538.789,"z":42597.879,"elevation":148.21},{"lat":55.771504,"lon":37.71014,"x":27659.721,"z":42394.662,"elevation":148.32},{"lat":55.770478,"lon":37.711226,"x":27780.653,"z":42191.445,"elevation":148.63}]},{"id":"road-22151","name":"Крюковская улица","highway":"residential","points":[{"lat":55.772186,"lon":37.70741,"x":27355.824,"z":42529.601,"elevation":147.82},{"lat":55.771992,"lon":37.707663,"x":27383.944,"z":42491.247,"elevation":147.96}]},{"id":"road-22152","name":"улица Госпитальный Вал","highway":"secondary","points":[{"lat":55.772186,"lon":37.70741,"x":27355.824,"z":42529.601,"elevation":147.82},{"lat":55.771394,"lon":37.705876,"x":27185.078,"z":42372.803,"elevation":147.34},{"lat":55.770626,"lon":37.704311,"x":27010.807,"z":42220.751,"elevation":143.48},{"lat":55.770029,"lon":37.702518,"x":26811.305,"z":42102.689,"elevation":138.02}]},{"id":"road-22153","name":"улица Госпитальный Вал","highway":"secondary","points":[{"lat":55.772186,"lon":37.70741,"x":27355.824,"z":42529.601,"elevation":147.82},{"lat":55.772863,"lon":37.70877,"x":27507.23,"z":42663.576,"elevation":149.55},{"lat":55.77354,"lon":37.71013,"x":27658.635,"z":42797.552,"elevation":147.03}]},{"id":"road-22154","name":"Ухтомский переулок","highway":"residential","points":[{"lat":55.769981,"lon":37.710024,"x":27646.78,"z":42093.091,"elevation":149.99},{"lat":55.770478,"lon":37.711226,"x":27780.653,"z":42191.445,"elevation":148.63}]},{"id":"road-22155","name":"Крюковская улица","highway":"residential","points":[{"lat":55.769981,"lon":37.710024,"x":27646.78,"z":42093.091,"elevation":149.99},{"lat":55.770986,"lon":37.708843,"x":27515.362,"z":42292.169,"elevation":149.56},{"lat":55.771992,"lon":37.707663,"x":27383.944,"z":42491.247,"elevation":147.96}]},{"id":"road-22185","name":"Измайловское шоссе","highway":"secondary","points":[{"lat":55.77972,"lon":37.721153,"x":28885.632,"z":44020.833,"elevation":145.41},{"lat":55.779803,"lon":37.720537,"x":28817.115,"z":44037.243,"elevation":145.05}]},{"id":"road-22186","name":"Вельяминовская улица","highway":"tertiary","points":[{"lat":55.77972,"lon":37.721153,"x":28885.632,"z":44020.833,"elevation":145.41},{"lat":55.780567,"lon":37.721724,"x":28949.207,"z":44188.478,"elevation":143.75},{"lat":55.781414,"lon":37.722295,"x":29012.781,"z":44356.122,"elevation":143.99},{"lat":55.782298,"lon":37.722517,"x":29037.505,"z":44531.033,"elevation":141.99}]},{"id":"road-22187","name":"Измайловское шоссе","highway":"secondary","points":[{"lat":55.779643,"lon":37.721037,"x":28872.819,"z":44005.512,"elevation":145.43},{"lat":55.779608,"lon":37.721392,"x":28912.293,"z":43998.624,"elevation":145.17}]},{"id":"road-24352","name":"Золотая улица","highway":"tertiary","points":[{"lat":55.766796,"lon":37.725959,"x":29420.667,"z":41462.839,"elevation":151.84},{"lat":55.766392,"lon":37.724008,"x":29203.496,"z":41383.047,"elevation":149.01},{"lat":55.766972,"lon":37.722286,"x":29011.841,"z":41497.67,"elevation":147.2},{"lat":55.768045,"lon":37.721287,"x":28900.646,"z":41709.986,"elevation":148.85},{"lat":55.769117,"lon":37.720288,"x":28789.451,"z":41922.303,"elevation":149.07},{"lat":55.77019,"lon":37.71929,"x":28678.256,"z":42134.619,"elevation":148.6},{"lat":55.771263,"lon":37.718291,"x":28567.061,"z":42346.935,"elevation":148.95},{"lat":55.772336,"lon":37.717292,"x":28455.866,"z":42559.251,"elevation":151.56},{"lat":55.773409,"lon":37.716293,"x":28344.671,"z":42771.567,"elevation":152.55},{"lat":55.774482,"lon":37.715294,"x":28233.476,"z":42983.883,"elevation":148.01},{"lat":55.775554,"lon":37.714295,"x":28122.281,"z":43196.199,"elevation":145.48}]},{"id":"road-25264","name":"Семёновский проезд","highway":"secondary","points":[{"lat":55.776136,"lon":37.715126,"x":28214.777,"z":43311.253,"elevation":146.62},{"lat":55.775671,"lon":37.714197,"x":28111.372,"z":43219.337,"elevation":145.63}]},{"id":"road-25265","name":"nan","highway":"tertiary_link","points":[{"lat":55.776136,"lon":37.715126,"x":28214.777,"z":43311.253,"elevation":146.62},{"lat":55.776382,"lon":37.714709,"x":28168.356,"z":43360.102,"elevation":147.32}]},{"id":"road-25266","name":"улица Семёновский Вал","highway":"tertiary","points":[{"lat":55.776382,"lon":37.714709,"x":28168.356,"z":43360.102,"elevation":147.32},{"lat":55.775944,"lon":37.714388,"x":28132.645,"z":43273.291,"elevation":146.27}]},{"id":"road-25267","name":"улица Семёновский Вал","highway":"tertiary","points":[{"lat":55.776382,"lon":37.714709,"x":28168.356,"z":43360.102,"elevation":147.32},{"lat":55.777435,"lon":37.715259,"x":28229.588,"z":43568.432,"elevation":146.74},{"lat":55.778487,"lon":37.715809,"x":28290.819,"z":43776.763,"elevation":142.84},{"lat":55.77954,"lon":37.716359,"x":28352.05,"z":43985.093,"elevation":142.47},{"lat":55.780592,"lon":37.716909,"x":28413.281,"z":44193.423,"elevation":142.46}]},{"id":"road-27658","name":"Вольная улица","highway":"residential","points":[{"lat":55.775851,"lon":37.723109,"x":29103.462,"z":43254.904,"elevation":147.77},{"lat":55.776079,"lon":37.725241,"x":29340.776,"z":43300.031,"elevation":153.61},{"lat":55.776307,"lon":37.727373,"x":29578.09,"z":43345.159,"elevation":153.33},{"lat":55.776535,"lon":37.729505,"x":29815.403,"z":43390.286,"elevation":154.49},{"lat":55.776763,"lon":37.731637,"x":30052.717,"z":43435.414,"elevation":153.72}]},{"id":"road-27659","name":"nan","highway":"residential","points":[{"lat":55.775851,"lon":37.723109,"x":29103.462,"z":43254.904,"elevation":147.77},{"lat":55.775816,"lon":37.722763,"x":29064.857,"z":43247.996,"elevation":147.38}]},{"id":"road-27660","name":"проспект Будённого","highway":"secondary","points":[{"lat":55.775851,"lon":37.723109,"x":29103.462,"z":43254.904,"elevation":147.77},{"lat":55.776993,"lon":37.722032,"x":28983.577,"z":43480.921,"elevation":146.49},{"lat":55.778135,"lon":37.720955,"x":28863.691,"z":43706.939,"elevation":146.41}]},{"id":"road-27682","name":"Вольная улица","highway":"residential","points":[{"lat":55.776763,"lon":37.731637,"x":30052.717,"z":43435.414,"elevation":153.72},{"lat":55.776535,"lon":37.729505,"x":29815.403,"z":43390.286,"elevation":154.49},{"lat":55.776307,"lon":37.727373,"x":29578.09,"z":43345.159,"elevation":153.33},{"lat":55.776079,"lon":37.725241,"x":29340.776,"z":43300.031,"elevation":153.61},{"lat":55.775851,"lon":37.723109,"x":29103.462,"z":43254.904,"elevation":147.77}]},{"id":"road-27715","name":"проспект Будённого","highway":"secondary","points":[{"lat":55.772526,"lon":37.726131,"x":29439.87,"z":42596.791,"elevation":153.07},{"lat":55.773634,"lon":37.725124,"x":29327.734,"z":42816.162,"elevation":154.2},{"lat":55.774743,"lon":37.724117,"x":29215.598,"z":43035.533,"elevation":150.35},{"lat":55.775851,"lon":37.723109,"x":29103.462,"z":43254.904,"elevation":147.77}]},{"id":"road-27735","name":"Золотая улица","highway":"unclassified","points":[{"lat":55.780477,"lon":37.708756,"x":27505.66,"z":44170.541,"elevation":133.01},{"lat":55.779646,"lon":37.709663,"x":27606.616,"z":44006.059,"elevation":135.64},{"lat":55.778825,"lon":37.711015,"x":27757.097,"z":43843.589,"elevation":137.99},{"lat":55.777849,"lon":37.711992,"x":27865.916,"z":43650.455,"elevation":139.72},{"lat":55.776874,"lon":37.71297,"x":27974.734,"z":43457.321,"elevation":143.88},{"lat":55.775898,"lon":37.713947,"x":28083.553,"z":43264.186,"elevation":145.61}]},{"id":"road-27736","name":"Золотая улица","highway":"unclassified","points":[{"lat":55.780477,"lon":37.708756,"x":27505.66,"z":44170.541,"elevation":133.01},{"lat":55.78058,"lon":37.708819,"x":27512.64,"z":44191.008,"elevation":133.12}]},{"id":"road-27842","name":"Вельяминовская улица","highway":"tertiary","points":[{"lat":55.782298,"lon":37.722517,"x":29037.505,"z":44531.033,"elevation":141.99},{"lat":55.781414,"lon":37.722295,"x":29012.781,"z":44356.122,"elevation":143.99},{"lat":55.780567,"lon":37.721724,"x":28949.207,"z":44188.478,"elevation":143.75},{"lat":55.77972,"lon":37.721153,"x":28885.632,"z":44020.833,"elevation":145.41}]},{"id":"road-27843","name":"Измайловское шоссе","highway":"secondary","points":[{"lat":55.780126,"lon":37.718153,"x":28551.741,"z":44101.061,"elevation":145.21},{"lat":55.779721,"lon":37.72024,"x":28784.053,"z":44021.011,"elevation":144.24}]},{"id":"road-27882","name":"Кирпичная улица","highway":"residential","points":[{"lat":55.778135,"lon":37.720955,"x":28863.691,"z":43706.939,"elevation":146.41},{"lat":55.777937,"lon":37.722717,"x":29059.844,"z":43667.728,"elevation":147.65},{"lat":55.777739,"lon":37.72448,"x":29255.996,"z":43628.517,"elevation":148.48},{"lat":55.77754,"lon":37.726242,"x":29452.148,"z":43589.306,"elevation":152.86}]},{"id":"road-27883","name":"проспект Будённого","highway":"secondary","points":[{"lat":55.778135,"lon":37.720955,"x":28863.691,"z":43706.939,"elevation":146.41},{"lat":55.778807,"lon":37.72074,"x":28839.713,"z":43840.092,"elevation":145.16}]},{"id":"road-27884","name":"nan","highway":"secondary","points":[{"lat":55.778135,"lon":37.720955,"x":28863.691,"z":43706.939,"elevation":146.41},{"lat":55.779426,"lon":37.721347,"x":28907.262,"z":43962.46,"elevation":145.12}]},{"id":"road-27893","name":"проспект Будённого","highway":"secondary","points":[{"lat":55.779414,"lon":37.72078,"x":28844.199,"z":43960.243,"elevation":145.17},{"lat":55.779537,"lon":37.720771,"x":28843.108,"z":43984.412,"elevation":145.29}]},{"id":"road-27894","name":"nan","highway":"secondary_link","points":[{"lat":55.779414,"lon":37.72078,"x":28844.199,"z":43960.243,"elevation":145.17},{"lat":55.779532,"lon":37.72087,"x":28854.218,"z":43983.58,"elevation":145.42}]},{"id":"road-27895","name":"nan","highway":"residential","points":[{"lat":55.775816,"lon":37.722763,"x":29064.857,"z":43247.996,"elevation":147.38},{"lat":55.775851,"lon":37.723109,"x":29103.462,"z":43254.904,"elevation":147.77}]},{"id":"road-27896","name":"проспект Будённого","highway":"secondary","points":[{"lat":55.775816,"lon":37.722763,"x":29064.857,"z":43247.996,"elevation":147.38},{"lat":55.774688,"lon":37.723778,"x":29177.865,"z":43024.792,"elevation":150.67},{"lat":55.77356,"lon":37.724793,"x":29290.872,"z":42801.589,"elevation":153.44},{"lat":55.772433,"lon":37.725808,"x":29403.88,"z":42578.385,"elevation":152.95}]},{"id":"road-31897","name":"проектируемый проезд № 789","highway":"unclassified","points":[{"lat":55.777733,"lon":37.703302,"x":26898.468,"z":43627.349,"elevation":128.87},{"lat":55.778056,"lon":37.703531,"x":26924.06,"z":43691.381,"elevation":130.82}]},{"id":"road-31898","name":"Семёновская набережная","highway":"secondary","points":[{"lat":55.777733,"lon":37.703302,"x":26898.468,"z":43627.349,"elevation":128.87},{"lat":55.778682,"lon":37.703291,"x":26897.244,"z":43815.27,"elevation":128.39}]},{"id":"road-31899","name":"проектируемый проезд № 789","highway":"unclassified","points":[{"lat":55.778056,"lon":37.703531,"x":26924.06,"z":43691.381,"elevation":130.82},{"lat":55.778644,"lon":37.703753,"x":26948.707,"z":43807.689,"elevation":132.78}]},{"id":"road-31900","name":"nan","highway":"residential","points":[{"lat":55.778056,"lon":37.703531,"x":26924.06,"z":43691.381,"elevation":130.82},{"lat":55.777835,"lon":37.705625,"x":27157.158,"z":43647.671,"elevation":135.75},{"lat":55.77822,"lon":37.707624,"x":27379.643,"z":43723.855,"elevation":133.64},{"lat":55.778644,"lon":37.709616,"x":27601.44,"z":43807.828,"elevation":135.31}]},{"id":"road-31901","name":"проектируемый проезд № 789","highway":"unclassified","points":[{"lat":55.778644,"lon":37.703753,"x":26948.707,"z":43807.689,"elevation":132.78},{"lat":55.778682,"lon":37.703291,"x":26897.244,"z":43815.27,"elevation":128.39}]},{"id":"road-31902","name":"проектируемый проезд № 789","highway":"residential","points":[{"lat":55.778644,"lon":37.703753,"x":26948.707,"z":43807.689,"elevation":132.78},{"lat":55.779821,"lon":37.704127,"x":26990.362,"z":44040.8,"elevation":133.96},{"lat":55.780999,"lon":37.704501,"x":27032.018,"z":44273.91,"elevation":129.12}]},{"id":"road-32208","name":"Измайловское шоссе","highway":"secondary","points":[{"lat":55.779673,"lon":37.720732,"x":28838.789,"z":44011.451,"elevation":145.36},{"lat":55.779643,"lon":37.721037,"x":28872.819,"z":44005.512,"elevation":145.43}]},{"id":"road-32209","name":"Измайловское шоссе","highway":"secondary","points":[{"lat":55.779673,"lon":37.720732,"x":28838.789,"z":44011.451,"elevation":145.36},{"lat":55.779803,"lon":37.720537,"x":28817.115,"z":44037.243,"elevation":145.05}]},{"id":"road-32829","name":"Измайловское шоссе","highway":"secondary","points":[{"lat":55.779206,"lon":37.731096,"x":29992.538,"z":43918.991,"elevation":150.1},{"lat":55.778964,"lon":37.728933,"x":29751.711,"z":43870.994,"elevation":151.04},{"lat":55.778955,"lon":37.726775,"x":29511.478,"z":43869.362,"elevation":150.49},{"lat":55.779229,"lon":37.724623,"x":29271.959,"z":43923.512,"elevation":149.66},{"lat":55.779502,"lon":37.722471,"x":29032.44,"z":43977.662,"elevation":145.97}]},{"id":"road-34466","name":"Княжекозловский переулок","highway":"residential","points":[{"lat":55.770478,"lon":37.711226,"x":27780.653,"z":42191.445,"elevation":148.63},{"lat":55.76968,"lon":37.712097,"x":27877.612,"z":42033.544,"elevation":149.93}]},{"id":"road-34467","name":"Княжекозловский переулок","highway":"residential","points":[{"lat":55.770478,"lon":37.711226,"x":27780.653,"z":42191.445,"elevation":148.63},{"lat":55.771504,"lon":37.71014,"x":27659.721,"z":42394.662,"elevation":148.32},{"lat":55.772531,"lon":37.709054,"x":27538.789,"z":42597.879,"elevation":148.21}]},{"id":"road-34468","name":"Ухтомский переулок","highway":"residential","points":[{"lat":55.770478,"lon":37.711226,"x":27780.653,"z":42191.445,"elevation":148.63},{"lat":55.769981,"lon":37.710024,"x":27646.78,"z":42093.091,"elevation":149.99}]},{"id":"road-34730","name":"nan","highway":"residential","points":[{"lat":55.778644,"lon":37.709616,"x":27601.44,"z":43807.828,"elevation":135.31},{"lat":55.77822,"lon":37.707624,"x":27379.643,"z":43723.855,"elevation":133.64},{"lat":55.777835,"lon":37.705625,"x":27157.158,"z":43647.671,"elevation":135.75},{"lat":55.778056,"lon":37.703531,"x":26924.06,"z":43691.381,"elevation":130.82}]},{"id":"road-35249","name":"Семёновская набережная","highway":"secondary","points":[{"lat":55.778682,"lon":37.703291,"x":26897.244,"z":43815.27,"elevation":128.39},{"lat":55.779667,"lon":37.702675,"x":26828.747,"z":44010.281,"elevation":127.97},{"lat":55.780559,"lon":37.701781,"x":26729.186,"z":44186.877,"elevation":127.17},{"lat":55.781336,"lon":37.700539,"x":26590.984,"z":44340.57,"elevation":125.28},{"lat":55.782251,"lon":37.699789,"x":26507.503,"z":44521.69,"elevation":124.97}]},{"id":"road-36555","name":"улица Семёновский Вал","highway":"tertiary","points":[{"lat":55.775944,"lon":37.714388,"x":28132.645,"z":43273.291,"elevation":146.27},{"lat":55.775671,"lon":37.714197,"x":28111.372,"z":43219.337,"elevation":145.63}]},{"id":"road-36556","name":"nan","highway":"unclassified","points":[{"lat":55.775944,"lon":37.714388,"x":28132.645,"z":43273.291,"elevation":146.27},{"lat":55.775898,"lon":37.713947,"x":28083.553,"z":43264.186,"elevation":145.61}]},{"id":"road-36653","name":"Измайловское шоссе","highway":"secondary","points":[{"lat":55.779803,"lon":37.720537,"x":28817.115,"z":44037.243,"elevation":145.05},{"lat":55.780167,"lon":37.718424,"x":28581.953,"z":44109.216,"elevation":145.0}]},{"id":"road-36654","name":"улица Семёновский Вал","highway":"tertiary","points":[{"lat":55.780592,"lon":37.716909,"x":28413.281,"z":44193.423,"elevation":142.46},{"lat":55.77954,"lon":37.716359,"x":28352.05,"z":43985.093,"elevation":142.47},{"lat":55.778487,"lon":37.715809,"x":28290.819,"z":43776.763,"elevation":142.84},{"lat":55.777435,"lon":37.715259,"x":28229.588,"z":43568.432,"elevation":146.74},{"lat":55.776382,"lon":37.714709,"x":28168.356,"z":43360.102,"elevation":147.32}]},{"id":"road-36655","name":"Большая Семёновская улица","highway":"secondary","points":[{"lat":55.780592,"lon":37.716909,"x":28413.281,"z":44193.423,"elevation":142.46},{"lat":55.780969,"lon":37.715112,"x":28213.211,"z":44267.946,"elevation":139.98},{"lat":55.781345,"lon":37.713315,"x":28013.14,"z":44342.468,"elevation":137.57},{"lat":55.781722,"lon":37.711518,"x":27813.069,"z":44416.991,"elevation":135.63}]},{"id":"road-36656","name":"Большая Семёновская улица","highway":"secondary","points":[{"lat":55.780592,"lon":37.716909,"x":28413.281,"z":44193.423,"elevation":142.46},{"lat":55.780262,"lon":37.71782,"x":28514.66,"z":44127.942,"elevation":144.32}]},{"id":"road-37354","name":"Золотая улица","highway":"unclassified","points":[{"lat":55.782093,"lon":37.709462,"x":27584.207,"z":44490.531,"elevation":135.92},{"lat":55.781337,"lon":37.70914,"x":27548.424,"z":44340.77,"elevation":133.97},{"lat":55.78058,"lon":37.708819,"x":27512.64,"z":44191.008,"elevation":133.12}]},{"id":"road-37397","name":"Гольяновский проезд","highway":"unclassified","points":[{"lat":55.780189,"lon":37.706773,"x":27284.936,"z":44113.571,"elevation":133.99},{"lat":55.780594,"lon":37.705637,"x":27158.477,"z":44193.741,"elevation":132.45},{"lat":55.780999,"lon":37.704501,"x":27032.018,"z":44273.91,"elevation":129.12}]},{"id":"road-37398","name":"проектируемый проезд № 789","highway":"residential","points":[{"lat":55.780999,"lon":37.704501,"x":27032.018,"z":44273.91,"elevation":129.12},{"lat":55.779821,"lon":37.704127,"x":26990.362,"z":44040.8,"elevation":133.96},{"lat":55.778644,"lon":37.703753,"x":26948.707,"z":43807.689,"elevation":132.78}]},{"id":"road-37399","name":"Гольяновский проезд","highway":"unclassified","points":[{"lat":55.780999,"lon":37.704501,"x":27032.018,"z":44273.91,"elevation":129.12},{"lat":55.781239,"lon":37.703144,"x":26880.952,"z":44321.369,"elevation":128.86},{"lat":55.781478,"lon":37.701787,"x":26729.886,"z":44368.828,"elevation":126.4}]},{"id":"road-37400","name":"Гольяновский проезд","highway":"unclassified","points":[{"lat":55.780999,"lon":37.704501,"x":27032.018,"z":44273.91,"elevation":129.12},{"lat":55.780594,"lon":37.705637,"x":27158.477,"z":44193.741,"elevation":132.45},{"lat":55.780189,"lon":37.706773,"x":27284.936,"z":44113.571,"elevation":133.99}]},{"id":"road-37983","name":"Кирпичная улица","highway":"unclassified","points":[{"lat":55.77808,"lon":37.720745,"x":28840.292,"z":43696.032,"elevation":145.81},{"lat":55.778135,"lon":37.720955,"x":28863.691,"z":43706.939,"elevation":146.41}]},{"id":"road-37984","name":"проспект Будённого","highway":"secondary","points":[{"lat":55.77808,"lon":37.720745,"x":28840.292,"z":43696.032,"elevation":145.81},{"lat":55.776948,"lon":37.721754,"x":28952.574,"z":43472.014,"elevation":145.87},{"lat":55.775816,"lon":37.722763,"x":29064.857,"z":43247.996,"elevation":147.38}]},{"id":"road-37985","name":"проспект Будённого","highway":"secondary","points":[{"lat":55.779721,"lon":37.72024,"x":28784.053,"z":44021.011,"elevation":144.24},{"lat":55.779499,"lon":37.720517,"x":28814.878,"z":43976.989,"elevation":144.64}]},{"id":"road-37986","name":"Измайловское шоссе","highway":"secondary","points":[{"lat":55.779721,"lon":37.72024,"x":28784.053,"z":44021.011,"elevation":144.24},{"lat":55.779673,"lon":37.720732,"x":28838.789,"z":44011.451,"elevation":145.36}]},{"id":"road-37987","name":"проспект Будённого","highway":"secondary","points":[{"lat":55.779499,"lon":37.720517,"x":28814.878,"z":43976.989,"elevation":144.64},{"lat":55.778949,"lon":37.720507,"x":28813.798,"z":43868.101,"elevation":144.38}]},{"id":"road-37988","name":"проспект Будённого","highway":"secondary","points":[{"lat":55.778949,"lon":37.720507,"x":28813.798,"z":43868.101,"elevation":144.38},{"lat":55.77867,"lon":37.720506,"x":28813.72,"z":43812.855,"elevation":144.58}]},{"id":"road-37989","name":"Семёновский проезд","highway":"secondary","points":[{"lat":55.778949,"lon":37.720507,"x":28813.798,"z":43868.101,"elevation":144.38},{"lat":55.778246,"lon":37.719162,"x":28664.043,"z":43728.889,"elevation":145.33},{"lat":55.777542,"lon":37.717817,"x":28514.287,"z":43589.677,"elevation":146.48},{"lat":55.776839,"lon":37.716471,"x":28364.532,"z":43450.465,"elevation":146.45},{"lat":55.776136,"lon":37.715126,"x":28214.777,"z":43311.253,"elevation":146.62}]},{"id":"road-38301","name":"Большая Семёновская улица","highway":"secondary","points":[{"lat":55.780262,"lon":37.71782,"x":28514.66,"z":44127.942,"elevation":144.32},{"lat":55.780126,"lon":37.718153,"x":28551.741,"z":44101.061,"elevation":145.21}]},{"id":"road-38302","name":"nan","highway":"secondary_link","points":[{"lat":55.780262,"lon":37.71782,"x":28514.66,"z":44127.942,"elevation":144.32},{"lat":55.780248,"lon":37.718145,"x":28550.806,"z":44125.171,"elevation":144.65}]},{"id":"road-38303","name":"Большая Семёновская улица","highway":"secondary","points":[{"lat":55.781722,"lon":37.711518,"x":27813.069,"z":44416.991,"elevation":135.63},{"lat":55.781345,"lon":37.713315,"x":28013.14,"z":44342.468,"elevation":137.57},{"lat":55.780969,"lon":37.715112,"x":28213.211,"z":44267.946,"elevation":139.98},{"lat":55.780592,"lon":37.716909,"x":28413.281,"z":44193.423,"elevation":142.46}]},{"id":"road-38530","name":"Измайловское шоссе","highway":"secondary","points":[{"lat":55.779502,"lon":37.722471,"x":29032.44,"z":43977.662,"elevation":145.97},{"lat":55.779229,"lon":37.724623,"x":29271.959,"z":43923.512,"elevation":149.66},{"lat":55.778955,"lon":37.726775,"x":29511.478,"z":43869.362,"elevation":150.49},{"lat":55.778964,"lon":37.728933,"x":29751.711,"z":43870.994,"elevation":151.04},{"lat":55.779206,"lon":37.731096,"x":29992.538,"z":43918.991,"elevation":150.1}]},{"id":"road-38531","name":"Измайловское шоссе","highway":"secondary","points":[{"lat":55.779502,"lon":37.722471,"x":29032.44,"z":43977.662,"elevation":145.97},{"lat":55.77972,"lon":37.721153,"x":28885.632,"z":44020.833,"elevation":145.41}]},{"id":"road-39956","name":"проспект Будённого","highway":"secondary","points":[{"lat":55.778317,"lon":37.720564,"x":28820.11,"z":43743.003,"elevation":145.06},{"lat":55.77808,"lon":37.720745,"x":28840.292,"z":43696.032,"elevation":145.81}]},{"id":"road-40048","name":"улица Измайловский Вал","highway":"secondary","points":[{"lat":55.782245,"lon":37.718698,"x":28612.454,"z":44520.542,"elevation":137.65},{"lat":55.781246,"lon":37.718422,"x":28581.63,"z":44322.856,"elevation":140.36},{"lat":55.780248,"lon":37.718145,"x":28550.806,"z":44125.171,"elevation":144.65}]},{"id":"road-40598","name":"Гольяновский проезд","highway":"residential","points":[{"lat":55.775602,"lon":37.712503,"x":27922.774,"z":43205.739,"elevation":146.27},{"lat":55.775021,"lon":37.712893,"x":27966.156,"z":43090.667,"elevation":146.49}]},{"id":"road-40850","name":"Крюковская улица","highway":"residential","points":[{"lat":55.771992,"lon":37.707663,"x":27383.944,"z":42491.247,"elevation":147.96},{"lat":55.772186,"lon":37.70741,"x":27355.824,"z":42529.601,"elevation":147.82}]},{"id":"road-40860","name":"Гольяновская улица","highway":"tertiary","points":[{"lat":55.777021,"lon":37.703173,"x":26884.219,"z":43486.44,"elevation":130.37},{"lat":55.776565,"lon":37.704968,"x":27083.944,"z":43396.252,"elevation":140.57},{"lat":55.776109,"lon":37.706762,"x":27283.669,"z":43306.065,"elevation":141.15},{"lat":55.775654,"lon":37.708556,"x":27483.394,"z":43215.877,"elevation":146.18},{"lat":55.775036,"lon":37.710188,"x":27665.1,"z":43093.548,"elevation":151.85},{"lat":55.774412,"lon":37.711816,"x":27846.242,"z":42970.213,"elevation":147.15}]},{"id":"road-40861","name":"Гольяновская улица","highway":"tertiary","points":[{"lat":55.777021,"lon":37.703173,"x":26884.219,"z":43486.44,"elevation":130.37},{"lat":55.777156,"lon":37.702916,"x":26855.588,"z":43513.141,"elevation":129.15}]},{"id":"road-40909","name":"Лонгиновская улица","highway":"residential","points":[{"lat":55.770539,"lon":37.712747,"x":27949.959,"z":42203.616,"elevation":150.39},{"lat":55.76968,"lon":37.712097,"x":27877.612,"z":42033.544,"elevation":149.93}]},{"id":"road-40910","name":"Ухтомская улица","highway":"residential","points":[{"lat":55.770539,"lon":37.712747,"x":27949.959,"z":42203.616,"elevation":150.39},{"lat":55.771539,"lon":37.711875,"x":27852.851,"z":42401.595,"elevation":146.98},{"lat":55.77254,"lon":37.711003,"x":27755.743,"z":42599.573,"elevation":147.4},{"lat":55.77354,"lon":37.71013,"x":27658.635,"z":42797.552,"elevation":147.03}]},{"id":"road-40911","name":"Ухтомская улица","highway":"residential","points":[{"lat":55.770539,"lon":37.712747,"x":27949.959,"z":42203.616,"elevation":150.39},{"lat":55.76954,"lon":37.713576,"x":28042.228,"z":42005.936,"elevation":150.37},{"lat":55.768541,"lon":37.714405,"x":28134.497,"z":41808.257,"elevation":149.86},{"lat":55.767542,"lon":37.715234,"x":28226.766,"z":41610.577,"elevation":148.99}]},{"id":"road-42513","name":"Кирпичная улица","highway":"residential","points":[{"lat":55.77754,"lon":37.726242,"x":29452.148,"z":43589.306,"elevation":152.86},{"lat":55.777739,"lon":37.72448,"x":29255.996,"z":43628.517,"elevation":148.48},{"lat":55.777937,"lon":37.722717,"x":29059.844,"z":43667.728,"elevation":147.65},{"lat":55.778135,"lon":37.720955,"x":28863.691,"z":43706.939,"elevation":146.41}]},{"id":"road-42938","name":"Боровая улица","highway":"tertiary","points":[{"lat":55.774236,"lon":37.711951,"x":27861.348,"z":42935.241,"elevation":146.56},{"lat":55.773154,"lon":37.71288,"x":27964.687,"z":42721.095,"elevation":148.65},{"lat":55.772072,"lon":37.713808,"x":28068.025,"z":42506.949,"elevation":150.28},{"lat":55.77099,"lon":37.714736,"x":28171.363,"z":42292.803,"elevation":151.81},{"lat":55.769908,"lon":37.715664,"x":28274.702,"z":42078.657,"elevation":150.82},{"lat":55.768825,"lon":37.716593,"x":28378.04,"z":41864.511,"elevation":148.05},{"lat":55.767673,"lon":37.717151,"x":28440.237,"z":41636.474,"elevation":147.2},{"lat":55.766496,"lon":37.717579,"x":28487.854,"z":41403.515,"elevation":147.8}]},{"id":"road-42939","name":"Боровая улица","highway":"tertiary","points":[{"lat":55.774236,"lon":37.711951,"x":27861.348,"z":42935.241,"elevation":146.56},{"lat":55.7745,"lon":37.712174,"x":27886.139,"z":42987.432,"elevation":147.23}]},{"id":"road-43498","name":"nan","highway":"secondary_link","points":[{"lat":55.779532,"lon":37.72087,"x":28854.218,"z":43983.58,"elevation":145.42},{"lat":55.779643,"lon":37.721037,"x":28872.819,"z":44005.512,"elevation":145.43}]},{"id":"road-43499","name":"nan","highway":"secondary","points":[{"lat":55.779608,"lon":37.721392,"x":28912.293,"z":43998.624,"elevation":145.17},{"lat":55.779426,"lon":37.721347,"x":28907.262,"z":43962.46,"elevation":145.12}]},{"id":"road-43500","name":"Измайловское шоссе","highway":"secondary","points":[{"lat":55.779608,"lon":37.721392,"x":28912.293,"z":43998.624,"elevation":145.17},{"lat":55.779502,"lon":37.722471,"x":29032.44,"z":43977.662,"elevation":145.97}]},{"id":"road-48775","name":"Золотая улица","highway":"unclassified","points":[{"lat":55.78058,"lon":37.708819,"x":27512.64,"z":44191.008,"elevation":133.12},{"lat":55.781337,"lon":37.70914,"x":27548.424,"z":44340.77,"elevation":133.97},{"lat":55.782093,"lon":37.709462,"x":27584.207,"z":44490.531,"elevation":135.92}]},{"id":"road-48776","name":"Золотая улица","highway":"unclassified","points":[{"lat":55.78058,"lon":37.708819,"x":27512.64,"z":44191.008,"elevation":133.12},{"lat":55.780477,"lon":37.708756,"x":27505.66,"z":44170.541,"elevation":133.01}]},{"id":"road-48777","name":"nan","highway":"secondary","points":[{"lat":55.779426,"lon":37.721347,"x":28907.262,"z":43962.46,"elevation":145.12},{"lat":55.779608,"lon":37.721392,"x":28912.293,"z":43998.624,"elevation":145.17}]},{"id":"road-48778","name":"nan","highway":"secondary","points":[{"lat":55.779426,"lon":37.721347,"x":28907.262,"z":43962.46,"elevation":145.12},{"lat":55.778135,"lon":37.720955,"x":28863.691,"z":43706.939,"elevation":146.41}]},{"id":"road-48779","name":"nan","highway":"secondary_link","points":[{"lat":55.779426,"lon":37.721347,"x":28907.262,"z":43962.46,"elevation":145.12},{"lat":55.779532,"lon":37.72087,"x":28854.218,"z":43983.58,"elevation":145.42}]},{"id":"road-50469","name":"Золотая улица","highway":"unclassified","points":[{"lat":55.775898,"lon":37.713947,"x":28083.553,"z":43264.186,"elevation":145.61},{"lat":55.776874,"lon":37.71297,"x":27974.734,"z":43457.321,"elevation":143.88},{"lat":55.777849,"lon":37.711992,"x":27865.916,"z":43650.455,"elevation":139.72},{"lat":55.778825,"lon":37.711015,"x":27757.097,"z":43843.589,"elevation":137.99},{"lat":55.779646,"lon":37.709663,"x":27606.616,"z":44006.059,"elevation":135.64},{"lat":55.780477,"lon":37.708756,"x":27505.66,"z":44170.541,"elevation":133.01}]},{"id":"road-50470","name":"Золотая улица","highway":"residential","points":[{"lat":55.775898,"lon":37.713947,"x":28083.553,"z":43264.186,"elevation":145.61},{"lat":55.775671,"lon":37.714197,"x":28111.372,"z":43219.337,"elevation":145.63}]},{"id":"road-50472","name":"Гольяновский проезд","highway":"residential","points":[{"lat":55.775021,"lon":37.712893,"x":27966.156,"z":43090.667,"elevation":146.49},{"lat":55.774902,"lon":37.712987,"x":27976.631,"z":43067.035,"elevation":146.48}]},{"id":"road-50473","name":"Гольяновский проезд","highway":"residential","points":[{"lat":55.775021,"lon":37.712893,"x":27966.156,"z":43090.667,"elevation":146.49},{"lat":55.775602,"lon":37.712503,"x":27922.774,"z":43205.739,"elevation":146.27}]},{"id":"road-50474","name":"улица Госпитальный Вал","highway":"secondary","points":[{"lat":55.775021,"lon":37.712893,"x":27966.156,"z":43090.667,"elevation":146.49},{"lat":55.774412,"lon":37.711816,"x":27846.242,"z":42970.213,"elevation":147.15}]},{"id":"road-50475","name":"Гольяновский проезд","highway":"residential","points":[{"lat":55.774902,"lon":37.712987,"x":27976.631,"z":43067.035,"elevation":146.48},{"lat":55.775021,"lon":37.712893,"x":27966.156,"z":43090.667,"elevation":146.49}]},{"id":"road-50476","name":"['улица Госпитальный Вал', 'Семёновский путепровод', 'Семёновский проезд']","highway":"secondary","points":[{"lat":55.774902,"lon":37.712987,"x":27976.631,"z":43067.035,"elevation":146.48},{"lat":55.775554,"lon":37.714295,"x":28122.281,"z":43196.199,"elevation":145.48}]},{"id":"road-50477","name":"['Семёновский проезд', 'улица Госпитальный Вал', 'Семёновский путепровод']","highway":"secondary","points":[{"lat":55.775671,"lon":37.714197,"x":28111.372,"z":43219.337,"elevation":145.63},{"lat":55.775021,"lon":37.712893,"x":27966.156,"z":43090.667,"elevation":146.49}]},{"id":"road-50478","name":"Золотая улица","highway":"residential","points":[{"lat":55.775671,"lon":37.714197,"x":28111.372,"z":43219.337,"elevation":145.63},{"lat":55.775554,"lon":37.714295,"x":28122.281,"z":43196.199,"elevation":145.48}]},{"id":"road-50479","name":"Семёновский проезд","highway":"secondary","points":[{"lat":55.775554,"lon":37.714295,"x":28122.281,"z":43196.199,"elevation":145.48},{"lat":55.776047,"lon":37.715281,"x":28231.998,"z":43293.776,"elevation":146.34}]},{"id":"road-50480","name":"Золотая улица","highway":"tertiary","points":[{"lat":55.775554,"lon":37.714295,"x":28122.281,"z":43196.199,"elevation":145.48},{"lat":55.774482,"lon":37.715294,"x":28233.476,"z":42983.883,"elevation":148.01},{"lat":55.773409,"lon":37.716293,"x":28344.671,"z":42771.567,"elevation":152.55},{"lat":55.772336,"lon":37.717292,"x":28455.866,"z":42559.251,"elevation":151.56},{"lat":55.771263,"lon":37.718291,"x":28567.061,"z":42346.935,"elevation":148.95},{"lat":55.77019,"lon":37.71929,"x":28678.256,"z":42134.619,"elevation":148.6},{"lat":55.769117,"lon":37.720288,"x":28789.451,"z":41922.303,"elevation":149.07},{"lat":55.768045,"lon":37.721287,"x":28900.646,"z":41709.986,"elevation":148.85},{"lat":55.766972,"lon":37.722286,"x":29011.841,"z":41497.67,"elevation":147.2},{"lat":55.766392,"lon":37.724008,"x":29203.496,"z":41383.047,"elevation":149.01},{"lat":55.766796,"lon":37.725959,"x":29420.667,"z":41462.839,"elevation":151.84}]},{"id":"road-50481","name":"Семёновский проезд","highway":"secondary","points":[{"lat":55.776047,"lon":37.715281,"x":28231.998,"z":43293.776,"elevation":146.34},{"lat":55.776847,"lon":37.716885,"x":28410.58,"z":43452.036,"elevation":146.62},{"lat":55.777646,"lon":37.718489,"x":28589.163,"z":43610.297,"elevation":147.37},{"lat":55.778446,"lon":37.720093,"x":28767.745,"z":43768.557,"elevation":143.32}]},{"id":"road-50482","name":"nan","highway":"tertiary_link","points":[{"lat":55.776047,"lon":37.715281,"x":28231.998,"z":43293.776,"elevation":146.34},{"lat":55.776136,"lon":37.715126,"x":28214.777,"z":43311.253,"elevation":146.62}]},{"id":"road-50483","name":"проспект Будённого","highway":"secondary","points":[{"lat":55.77867,"lon":37.720506,"x":28813.72,"z":43812.855,"elevation":144.58},{"lat":55.778317,"lon":37.720564,"x":28820.11,"z":43743.003,"elevation":145.06}]},{"id":"road-50484","name":"Семёновский проезд","highway":"secondary","points":[{"lat":55.77867,"lon":37.720506,"x":28813.72,"z":43812.855,"elevation":144.58},{"lat":55.778807,"lon":37.72074,"x":28839.713,"z":43840.092,"elevation":145.16}]},{"id":"road-50485","name":"Семёновский проезд","highway":"secondary","points":[{"lat":55.778446,"lon":37.720093,"x":28767.745,"z":43768.557,"elevation":143.32},{"lat":55.77867,"lon":37.720506,"x":28813.72,"z":43812.855,"elevation":144.58}]},{"id":"road-50486","name":"nan","highway":"secondary_link","points":[{"lat":55.778446,"lon":37.720093,"x":28767.745,"z":43768.557,"elevation":143.32},{"lat":55.778317,"lon":37.720564,"x":28820.11,"z":43743.003,"elevation":145.06}]},{"id":"road-50487","name":"улица Госпитальный Вал","highway":"secondary","points":[{"lat":55.7745,"lon":37.712174,"x":27886.139,"z":42987.432,"elevation":147.23},{"lat":55.774902,"lon":37.712987,"x":27976.631,"z":43067.035,"elevation":146.48}]},{"id":"road-50488","name":"улица Измайловский Вал","highway":"secondary","points":[{"lat":55.780248,"lon":37.718145,"x":28550.806,"z":44125.171,"elevation":144.65},{"lat":55.780126,"lon":37.718153,"x":28551.741,"z":44101.061,"elevation":145.21}]},{"id":"road-50489","name":"Большая Семёновская улица","highway":"secondary","points":[{"lat":55.780248,"lon":37.718145,"x":28550.806,"z":44125.171,"elevation":144.65},{"lat":55.780592,"lon":37.716909,"x":28413.281,"z":44193.423,"elevation":142.46}]},{"id":"road-50490","name":"nan","highway":"secondary_link","points":[{"lat":55.780248,"lon":37.718145,"x":28550.806,"z":44125.171,"elevation":144.65},{"lat":55.78031,"lon":37.718353,"x":28574.049,"z":44137.503,"elevation":144.47}]},{"id":"road-50491","name":"улица Измайловский Вал","highway":"secondary","points":[{"lat":55.78031,"lon":37.718353,"x":28574.049,"z":44137.503,"elevation":144.47},{"lat":55.781207,"lon":37.718748,"x":28617.931,"z":44315.155,"elevation":139.93},{"lat":55.782105,"lon":37.719142,"x":28661.813,"z":44492.808,"elevation":137.54}]},{"id":"road-50515","name":"улица Измайловский Вал","highway":"secondary","points":[{"lat":55.780167,"lon":37.718424,"x":28581.953,"z":44109.216,"elevation":145.0},{"lat":55.78031,"lon":37.718353,"x":28574.049,"z":44137.503,"elevation":144.47}]},{"id":"road-50516","name":"['Измайловское шоссе', 'Большая Семёновская улица']","highway":"secondary","points":[{"lat":55.780167,"lon":37.718424,"x":28581.953,"z":44109.216,"elevation":145.0},{"lat":55.780248,"lon":37.718145,"x":28550.806,"z":44125.171,"elevation":144.65}]},{"id":"road-51526","name":"Семёновская набережная","highway":"secondary","points":[{"lat":55.777156,"lon":37.702916,"x":26855.588,"z":43513.141,"elevation":129.15},{"lat":55.777733,"lon":37.703302,"x":26898.468,"z":43627.349,"elevation":128.87}]},{"id":"road-51639","name":"Гольяновский проезд","highway":"unclassified","points":[{"lat":55.781478,"lon":37.701787,"x":26729.886,"z":44368.828,"elevation":126.4},{"lat":55.781239,"lon":37.703144,"x":26880.952,"z":44321.369,"elevation":128.86},{"lat":55.780999,"lon":37.704501,"x":27032.018,"z":44273.91,"elevation":129.12}]},{"id":"road-51860","name":"проспект Будённого","highway":"secondary","points":[{"lat":55.779537,"lon":37.720771,"x":28843.108,"z":43984.412,"elevation":145.29},{"lat":55.779673,"lon":37.720732,"x":28838.789,"z":44011.451,"elevation":145.36}]},{"id":"road-51861","name":"nan","highway":"secondary_link","points":[{"lat":55.779537,"lon":37.720771,"x":28843.108,"z":43984.412,"elevation":145.29},{"lat":55.779499,"lon":37.720517,"x":28814.878,"z":43976.989,"elevation":144.64}]}],"buildings":[]}