{"id":"29_50","col":29,"row":50,"bounds":{"minX":15102.073,"minZ":40844.93,"maxX":17602.073,"maxZ":43344.93},"roads":[{"id":"road-19618","name":"2-я улица Марьиной Рощи","highway":"tertiary","points":[{"lat":55.793174,"lon":37.619599,"x":15830.917,"z":40639.937,"elevation":162.65},{"lat":55.794454,"lon":37.61923,"x":15789.762,"z":40893.418,"elevation":163.7}]},{"id":"road-19626","name":"Шереметьевская улица","highway":"secondary","points":[{"lat":55.793357,"lon":37.616298,"x":15463.385,"z":40676.194,"elevation":162.0},{"lat":55.794381,"lon":37.616255,"x":15458.565,"z":40879.003,"elevation":161.99}]},{"id":"road-19632","name":"Октябрьская улица","highway":"tertiary","points":[{"lat":55.793277,"lon":37.61313,"x":15110.736,"z":40660.313,"elevation":164.12},{"lat":55.794402,"lon":37.613008,"x":15097.177,"z":40883.042,"elevation":166.11}]},{"id":"road-19701","name":"Водопроводный переулок","highway":"secondary","points":[{"lat":55.795286,"lon":37.636004,"x":17657.002,"z":41058.173,"elevation":159.32},{"lat":55.795664,"lon":37.635482,"x":17598.938,"z":41132.967,"elevation":159.12}]},{"id":"road-19713","name":"проспект Мира","highway":"primary","points":[{"lat":55.79468,"lon":37.6346,"x":17500.754,"z":40938.211,"elevation":158.14},{"lat":55.795889,"lon":37.634865,"x":17530.263,"z":41177.621,"elevation":158.7},{"lat":55.797098,"lon":37.63513,"x":17559.771,"z":41417.031,"elevation":158.49},{"lat":55.798307,"lon":37.635395,"x":17589.28,"z":41656.441,"elevation":160.87},{"lat":55.799516,"lon":37.63566,"x":17618.788,"z":41895.851,"elevation":163.04},{"lat":55.800725,"lon":37.635925,"x":17648.297,"z":42135.261,"elevation":165.77}]},{"id":"road-19714","name":"nan","highway":"secondary_link","points":[{"lat":55.795664,"lon":37.635482,"x":17598.938,"z":41132.967,"elevation":159.12},{"lat":55.795158,"lon":37.635386,"x":17588.296,"z":41032.766,"elevation":159.38}]},{"id":"road-19715","name":"Водопроводный переулок","highway":"secondary","points":[{"lat":55.795664,"lon":37.635482,"x":17598.938,"z":41132.967,"elevation":159.12},{"lat":55.796246,"lon":37.634182,"x":17454.202,"z":41248.233,"elevation":158.01},{"lat":55.795209,"lon":37.633971,"x":17430.7,"z":41042.837,"elevation":157.63},{"lat":55.794162,"lon":37.633784,"x":17409.895,"z":40835.498,"elevation":157.45}]},{"id":"road-19716","name":"Водопроводный переулок","highway":"secondary","points":[{"lat":55.795664,"lon":37.635482,"x":17598.938,"z":41132.967,"elevation":159.12},{"lat":55.795286,"lon":37.636004,"x":17657.002,"z":41058.173,"elevation":159.32}]},{"id":"road-19717","name":"nan","highway":"secondary_link","points":[{"lat":55.793587,"lon":37.634657,"x":17507.066,"z":40721.638,"elevation":157.71},{"lat":55.794582,"lon":37.635273,"x":17575.65,"z":40918.805,"elevation":159.15}]},{"id":"road-19718","name":"проспект Мира","highway":"primary","points":[{"lat":55.793587,"lon":37.634657,"x":17507.066,"z":40721.638,"elevation":157.71},{"lat":55.79468,"lon":37.6346,"x":17500.754,"z":40938.211,"elevation":158.14}]},{"id":"road-19720","name":"Водопроводный переулок","highway":"secondary","points":[{"lat":55.794162,"lon":37.633784,"x":17409.895,"z":40835.498,"elevation":157.45},{"lat":55.795209,"lon":37.633971,"x":17430.7,"z":41042.837,"elevation":157.63},{"lat":55.796246,"lon":37.634182,"x":17454.202,"z":41248.233,"elevation":158.01},{"lat":55.795664,"lon":37.635482,"x":17598.938,"z":41132.967,"elevation":159.12}]},{"id":"road-19916","name":"1-й проезд Марьиной Рощи","highway":"tertiary","points":[{"lat":55.794454,"lon":37.61923,"x":15789.762,"z":40893.418,"elevation":163.7},{"lat":55.794503,"lon":37.620753,"x":15959.308,"z":40903.102,"elevation":164.02},{"lat":55.794552,"lon":37.622276,"x":16128.853,"z":40912.785,"elevation":163.05}]},{"id":"road-19917","name":"2-я улица Марьиной Рощи","highway":"tertiary","points":[{"lat":55.794454,"lon":37.61923,"x":15789.762,"z":40893.418,"elevation":163.7},{"lat":55.795496,"lon":37.619163,"x":15782.304,"z":41099.758,"elevation":162.99}]},{"id":"road-19918","name":"1-й проезд Марьиной Рощи","highway":"tertiary","points":[{"lat":55.794454,"lon":37.61923,"x":15789.762,"z":40893.418,"elevation":163.7},{"lat":55.794418,"lon":37.617742,"x":15624.163,"z":40886.21,"elevation":159.79},{"lat":55.794381,"lon":37.616255,"x":15458.565,"z":40879.003,"elevation":161.99}]},{"id":"road-19919","name":"5-й проезд Марьиной Рощи","highway":"tertiary","points":[{"lat":55.798505,"lon":37.619022,"x":15766.675,"z":41695.678,"elevation":162.48},{"lat":55.798475,"lon":37.617528,"x":15600.375,"z":41689.687,"elevation":162.28},{"lat":55.798445,"lon":37.616035,"x":15434.074,"z":41683.696,"elevation":164.2}]},{"id":"road-19920","name":"5-й проезд Марьиной Рощи","highway":"living_street","points":[{"lat":55.798505,"lon":37.619022,"x":15766.675,"z":41695.678,"elevation":162.48},{"lat":55.798555,"lon":37.620684,"x":15951.677,"z":41705.639,"elevation":163.46}]},{"id":"road-19921","name":"2-я улица Марьиной Рощи","highway":"residential","points":[{"lat":55.798505,"lon":37.619022,"x":15766.675,"z":41695.678,"elevation":162.48},{"lat":55.799556,"lon":37.618981,"x":15762.122,"z":41903.841,"elevation":162.96}]},{"id":"road-19922","name":"2-я улица Марьиной Рощи","highway":"tertiary","points":[{"lat":55.798505,"lon":37.619022,"x":15766.675,"z":41695.678,"elevation":162.48},{"lat":55.797519,"lon":37.619073,"x":15772.296,"z":41500.432,"elevation":161.78}]},{"id":"road-19923","name":"Шереметьевская улица","highway":"secondary","points":[{"lat":55.798445,"lon":37.616035,"x":15434.074,"z":41683.696,"elevation":164.2},{"lat":55.798676,"lon":37.616024,"x":15432.872,"z":41729.444,"elevation":164.09}]},{"id":"road-19927","name":"nan","highway":"tertiary","points":[{"lat":55.800327,"lon":37.633955,"x":17428.975,"z":42056.437,"elevation":163.24},{"lat":55.800049,"lon":37.634439,"x":17482.854,"z":42001.32,"elevation":161.41}]},{"id":"road-19928","name":"Мурманский проезд","highway":"tertiary","points":[{"lat":55.800327,"lon":37.633955,"x":17428.975,"z":42056.437,"elevation":163.24},{"lat":55.80121,"lon":37.632414,"x":17257.449,"z":42231.259,"elevation":164.95},{"lat":55.802092,"lon":37.630873,"x":17085.922,"z":42406.082,"elevation":161.6}]},{"id":"road-19929","name":"nan","highway":"tertiary","points":[{"lat":55.800623,"lon":37.634793,"x":17522.239,"z":42115.079,"elevation":166.23},{"lat":55.800486,"lon":37.634708,"x":17512.821,"z":42087.887,"elevation":165.08}]},{"id":"road-19930","name":"nan","highway":"tertiary","points":[{"lat":55.800623,"lon":37.634793,"x":17522.239,"z":42115.079,"elevation":166.23},{"lat":55.800411,"lon":37.635555,"x":17607.109,"z":42073.113,"elevation":164.81}]},{"id":"road-19931","name":"nan","highway":"tertiary","points":[{"lat":55.802196,"lon":37.635484,"x":17599.127,"z":42426.561,"elevation":166.42},{"lat":55.801409,"lon":37.635138,"x":17560.683,"z":42270.82,"elevation":167.09},{"lat":55.800623,"lon":37.634793,"x":17522.239,"z":42115.079,"elevation":166.23}]},{"id":"road-20405","name":"nan","highway":"secondary","points":[{"lat":55.807077,"lon":37.615399,"x":15363.364,"z":43393.328,"elevation":166.28},{"lat":55.80681,"lon":37.615471,"x":15371.346,"z":43340.638,"elevation":166.05}]},{"id":"road-21526","name":"nan","highway":"tertiary","points":[{"lat":55.802663,"lon":37.635789,"x":17633.091,"z":42519.213,"elevation":165.66},{"lat":55.802196,"lon":37.635484,"x":17599.127,"z":42426.561,"elevation":166.42}]},{"id":"road-26541","name":"проспект Мира","highway":"primary","points":[{"lat":55.794298,"lon":37.634283,"x":17465.432,"z":40862.607,"elevation":157.3},{"lat":55.793337,"lon":37.634372,"x":17475.41,"z":40672.139,"elevation":156.74},{"lat":55.792375,"lon":37.634462,"x":17485.388,"z":40481.672,"elevation":156.9},{"lat":55.791413,"lon":37.634552,"x":17495.366,"z":40291.204,"elevation":159.83}]},{"id":"road-26542","name":"Рижская площадь","highway":"primary_link","points":[{"lat":55.794298,"lon":37.634283,"x":17465.432,"z":40862.607,"elevation":157.3},{"lat":55.793999,"lon":37.634159,"x":17451.696,"z":40803.241,"elevation":156.81}]},{"id":"road-29228","name":"3-й проезд Марьиной Рощи","highway":"tertiary","points":[{"lat":55.796311,"lon":37.612825,"x":15076.783,"z":41261.13,"elevation":166.09},{"lat":55.796363,"lon":37.614411,"x":15253.308,"z":41271.447,"elevation":164.54},{"lat":55.796415,"lon":37.615997,"x":15429.833,"z":41281.765,"elevation":161.71}]},{"id":"road-29536","name":"12-й проезд Марьиной Рощи","highway":"residential","points":[{"lat":55.804718,"lon":37.615712,"x":15398.14,"z":42926.142,"elevation":163.42},{"lat":55.80475,"lon":37.617948,"x":15647.112,"z":42932.411,"elevation":164.96},{"lat":55.804781,"lon":37.620185,"x":15896.084,"z":42938.68,"elevation":163.63}]},{"id":"road-29537","name":"Шереметьевская улица","highway":"secondary","points":[{"lat":55.804718,"lon":37.615712,"x":15398.14,"z":42926.142,"elevation":163.42},{"lat":55.805817,"lon":37.615623,"x":15388.266,"z":43143.885,"elevation":166.22}]},{"id":"road-29538","name":"Веткина улица","highway":"tertiary","points":[{"lat":55.804781,"lon":37.620185,"x":15896.084,"z":42938.68,"elevation":163.63},{"lat":55.803796,"lon":37.620015,"x":15877.153,"z":42743.478,"elevation":162.57},{"lat":55.802877,"lon":37.619394,"x":15808.037,"z":42561.434,"elevation":162.33},{"lat":55.802146,"lon":37.618223,"x":15677.687,"z":42416.731,"elevation":161.5},{"lat":55.80144,"lon":37.616988,"x":15540.206,"z":42276.869,"elevation":160.61}]},{"id":"road-29539","name":"Веткина улица","highway":"tertiary","points":[{"lat":55.804781,"lon":37.620185,"x":15896.084,"z":42938.68,"elevation":163.63},{"lat":55.805021,"lon":37.620155,"x":15892.722,"z":42986.098,"elevation":163.79}]},{"id":"road-29540","name":"12-й проезд Марьиной Рощи","highway":"residential","points":[{"lat":55.804781,"lon":37.620185,"x":15896.084,"z":42938.68,"elevation":163.63},{"lat":55.80475,"lon":37.617948,"x":15647.112,"z":42932.411,"elevation":164.96},{"lat":55.804718,"lon":37.615712,"x":15398.14,"z":42926.142,"elevation":163.42}]},{"id":"road-29541","name":"Веткина улица","highway":"residential","points":[{"lat":55.80144,"lon":37.616988,"x":15540.206,"z":42276.869,"elevation":160.61},{"lat":55.801016,"lon":37.616227,"x":15455.492,"z":42192.954,"elevation":162.85}]},{"id":"road-29542","name":"Веткина улица","highway":"tertiary","points":[{"lat":55.80144,"lon":37.616988,"x":15540.206,"z":42276.869,"elevation":160.61},{"lat":55.801265,"lon":37.6161,"x":15441.31,"z":42242.249,"elevation":163.03}]},{"id":"road-29543","name":"Веткина улица","highway":"tertiary","points":[{"lat":55.80144,"lon":37.616988,"x":15540.206,"z":42276.869,"elevation":160.61},{"lat":55.802146,"lon":37.618223,"x":15677.687,"z":42416.731,"elevation":161.5},{"lat":55.802877,"lon":37.619394,"x":15808.037,"z":42561.434,"elevation":162.33},{"lat":55.803796,"lon":37.620015,"x":15877.153,"z":42743.478,"elevation":162.57},{"lat":55.804781,"lon":37.620185,"x":15896.084,"z":42938.68,"elevation":163.63}]},{"id":"road-29546","name":"Веткина улица","highway":"tertiary","points":[{"lat":55.807055,"lon":37.617867,"x":15638.012,"z":43389.03,"elevation":164.12},{"lat":55.806461,"lon":37.618677,"x":15728.269,"z":43271.479,"elevation":164.83},{"lat":55.805868,"lon":37.619488,"x":15818.527,"z":43153.928,"elevation":164.19}]},{"id":"road-29550","name":"улица Годовикова","highway":"tertiary","points":[{"lat":55.810167,"lon":37.628278,"x":16796.97,"z":44005.452,"elevation":155.41},{"lat":55.809284,"lon":37.629513,"x":16934.428,"z":43830.523,"elevation":160.55},{"lat":55.808367,"lon":37.630612,"x":17056.795,"z":43648.96,"elevation":161.76},{"lat":55.807259,"lon":37.630935,"x":17092.765,"z":43429.412,"elevation":162.46},{"lat":55.80615,"lon":37.631258,"x":17128.735,"z":43209.865,"elevation":165.28}]},{"id":"road-29551","name":"улица Годовикова","highway":"tertiary","points":[{"lat":55.80615,"lon":37.631258,"x":17128.735,"z":43209.865,"elevation":165.28},{"lat":55.807259,"lon":37.630935,"x":17092.765,"z":43429.412,"elevation":162.46},{"lat":55.808367,"lon":37.630612,"x":17056.795,"z":43648.96,"elevation":161.76},{"lat":55.809284,"lon":37.629513,"x":16934.428,"z":43830.523,"elevation":160.55},{"lat":55.810167,"lon":37.628278,"x":16796.97,"z":44005.452,"elevation":155.41}]},{"id":"road-29552","name":"улица Годовикова","highway":"tertiary","points":[{"lat":55.80615,"lon":37.631258,"x":17128.735,"z":43209.865,"elevation":165.28},{"lat":55.805069,"lon":37.631322,"x":17135.882,"z":42995.745,"elevation":164.86}]},{"id":"road-29553","name":"Широкий проезд","highway":"tertiary","points":[{"lat":55.805069,"lon":37.631322,"x":17135.882,"z":42995.745,"elevation":164.86},{"lat":55.804968,"lon":37.632676,"x":17286.581,"z":42975.699,"elevation":163.33},{"lat":55.804867,"lon":37.63403,"x":17437.28,"z":42955.654,"elevation":164.35}]},{"id":"road-29554","name":"улица Годовикова","highway":"tertiary","points":[{"lat":55.805069,"lon":37.631322,"x":17135.882,"z":42995.745,"elevation":164.86},{"lat":55.80615,"lon":37.631258,"x":17128.735,"z":43209.865,"elevation":165.28}]},{"id":"road-29555","name":"улица Годовикова","highway":"tertiary","points":[{"lat":55.805069,"lon":37.631322,"x":17135.882,"z":42995.745,"elevation":164.86},{"lat":55.804143,"lon":37.631184,"x":17120.483,"z":42812.229,"elevation":166.13},{"lat":55.803216,"lon":37.631046,"x":17105.084,"z":42628.714,"elevation":165.17},{"lat":55.80229,"lon":37.630907,"x":17089.685,"z":42445.198,"elevation":162.35}]},{"id":"road-29557","name":"Большая Марьинская улица","highway":"residential","points":[{"lat":55.80594,"lon":37.63421,"x":17457.317,"z":43168.11,"elevation":163.25},{"lat":55.804867,"lon":37.63403,"x":17437.28,"z":42955.654,"elevation":164.35}]},{"id":"road-29558","name":"Большая Марьинская улица","highway":"residential","points":[{"lat":55.80594,"lon":37.63421,"x":17457.317,"z":43168.11,"elevation":163.25},{"lat":55.807238,"lon":37.634406,"x":17479.188,"z":43425.361,"elevation":165.11},{"lat":55.808537,"lon":37.634603,"x":17501.058,"z":43682.611,"elevation":160.73},{"lat":55.809836,"lon":37.634799,"x":17522.929,"z":43939.862,"elevation":160.54}]},{"id":"road-29559","name":"Узкий переулок","highway":"residential","points":[{"lat":55.80594,"lon":37.63421,"x":17457.317,"z":43168.11,"elevation":163.25},{"lat":55.806045,"lon":37.632734,"x":17293.026,"z":43188.988,"elevation":162.79},{"lat":55.80615,"lon":37.631258,"x":17128.735,"z":43209.865,"elevation":165.28}]},{"id":"road-29560","name":"Большая Марьинская улица","highway":"residential","points":[{"lat":55.804867,"lon":37.63403,"x":17437.28,"z":42955.654,"elevation":164.35},{"lat":55.80594,"lon":37.63421,"x":17457.317,"z":43168.11,"elevation":163.25}]},{"id":"road-29561","name":"Широкий проезд","highway":"tertiary","points":[{"lat":55.804867,"lon":37.63403,"x":17437.28,"z":42955.654,"elevation":164.35},{"lat":55.804872,"lon":37.635993,"x":17655.889,"z":42956.625,"elevation":163.71}]},{"id":"road-29562","name":"Широкий проезд","highway":"tertiary","points":[{"lat":55.804867,"lon":37.63403,"x":17437.28,"z":42955.654,"elevation":164.35},{"lat":55.804968,"lon":37.632676,"x":17286.581,"z":42975.699,"elevation":163.33},{"lat":55.805069,"lon":37.631322,"x":17135.882,"z":42995.745,"elevation":164.86}]},{"id":"road-29563","name":"Большая Марьинская улица","highway":"residential","points":[{"lat":55.804867,"lon":37.63403,"x":17437.28,"z":42955.654,"elevation":164.35},{"lat":55.803956,"lon":37.633877,"x":17420.259,"z":42775.203,"elevation":166.26},{"lat":55.803045,"lon":37.633724,"x":17403.238,"z":42594.752,"elevation":166.88},{"lat":55.802134,"lon":37.633571,"x":17386.217,"z":42414.301,"elevation":168.4}]},{"id":"road-29836","name":"3-й проезд Марьиной Рощи","highway":"residential","points":[{"lat":55.796493,"lon":37.619123,"x":15777.851,"z":41297.112,"elevation":162.86},{"lat":55.796545,"lon":37.620607,"x":15943.083,"z":41307.479,"elevation":164.11},{"lat":55.796597,"lon":37.622091,"x":16108.314,"z":41317.846,"elevation":163.21}]},{"id":"road-29837","name":"3-й проезд Марьиной Рощи","highway":"unclassified","points":[{"lat":55.796493,"lon":37.619123,"x":15777.851,"z":41297.112,"elevation":162.86},{"lat":55.796457,"lon":37.617631,"x":15611.729,"z":41290.141,"elevation":160.72},{"lat":55.796422,"lon":37.616138,"x":15445.607,"z":41283.171,"elevation":161.52}]},{"id":"road-29838","name":"2-я улица Марьиной Рощи","highway":"tertiary","points":[{"lat":55.796493,"lon":37.619123,"x":15777.851,"z":41297.112,"elevation":162.86},{"lat":55.797519,"lon":37.619073,"x":15772.296,"z":41500.432,"elevation":161.78}]},{"id":"road-29839","name":"3-й проезд Марьиной Рощи","highway":"unclassified","points":[{"lat":55.796422,"lon":37.616138,"x":15445.607,"z":41283.171,"elevation":161.52},{"lat":55.796457,"lon":37.617631,"x":15611.729,"z":41290.141,"elevation":160.72},{"lat":55.796493,"lon":37.619123,"x":15777.851,"z":41297.112,"elevation":162.86}]},{"id":"road-29840","name":"Шереметьевская улица","highway":"secondary","points":[{"lat":55.796422,"lon":37.616138,"x":15445.607,"z":41283.171,"elevation":161.52},{"lat":55.797433,"lon":37.616086,"x":15439.841,"z":41483.434,"elevation":162.54},{"lat":55.798445,"lon":37.616035,"x":15434.074,"z":41683.696,"elevation":164.2}]},{"id":"road-29926","name":"5-й проезд Марьиной Рощи","highway":"living_street","points":[{"lat":55.798622,"lon":37.621968,"x":16094.566,"z":41718.829,"elevation":163.25},{"lat":55.798602,"lon":37.621513,"x":16043.938,"z":41714.908,"elevation":163.64}]},{"id":"road-29927","name":"3-я улица Марьиной Рощи","highway":"residential","points":[{"lat":55.798622,"lon":37.621968,"x":16094.566,"z":41718.829,"elevation":163.25},{"lat":55.797616,"lon":37.622037,"x":16102.314,"z":41519.543,"elevation":166.66}]},{"id":"road-29928","name":"3-я улица Марьиной Рощи","highway":"residential","points":[{"lat":55.796597,"lon":37.622091,"x":16108.314,"z":41317.846,"elevation":163.21},{"lat":55.795572,"lon":37.62216,"x":16116.006,"z":41114.709,"elevation":165.09}]},{"id":"road-29929","name":"3-й проезд Марьиной Рощи","highway":"residential","points":[{"lat":55.796597,"lon":37.622091,"x":16108.314,"z":41317.846,"elevation":163.21},{"lat":55.796649,"lon":37.624152,"x":16337.71,"z":41327.985,"elevation":162.02}]},{"id":"road-29930","name":"4-я улица Марьиной Рощи","highway":"tertiary","points":[{"lat":55.796649,"lon":37.624152,"x":16337.71,"z":41327.985,"elevation":162.02},{"lat":55.797676,"lon":37.624043,"x":16325.51,"z":41531.425,"elevation":160.29}]},{"id":"road-29931","name":"1-й проезд Марьиной Рощи","highway":"tertiary","points":[{"lat":55.794552,"lon":37.622276,"x":16128.853,"z":40912.785,"elevation":163.05},{"lat":55.79461,"lon":37.624091,"x":16330.886,"z":40924.329,"elevation":162.1}]},{"id":"road-29932","name":"4-я улица Марьиной Рощи","highway":"tertiary","points":[{"lat":55.79461,"lon":37.624091,"x":16330.886,"z":40924.329,"elevation":162.1},{"lat":55.794739,"lon":37.624294,"x":16353.473,"z":40949.953,"elevation":162.01}]},{"id":"road-29933","name":"4-я улица Марьиной Рощи","highway":"tertiary","points":[{"lat":55.79461,"lon":37.624091,"x":16330.886,"z":40924.329,"elevation":162.1},{"lat":55.793712,"lon":37.624128,"x":16335.044,"z":40746.471,"elevation":159.82},{"lat":55.792814,"lon":37.624165,"x":16339.202,"z":40568.613,"elevation":158.0}]},{"id":"road-30087","name":"2-я улица Марьиной Рощи","highway":"tertiary","points":[{"lat":55.795496,"lon":37.619163,"x":15782.304,"z":41099.758,"elevation":162.99},{"lat":55.796493,"lon":37.619123,"x":15777.851,"z":41297.112,"elevation":162.86}]},{"id":"road-30088","name":"3-я улица Марьиной Рощи","highway":"residential","points":[{"lat":55.795572,"lon":37.62216,"x":16116.006,"z":41114.709,"elevation":165.09},{"lat":55.794552,"lon":37.622276,"x":16128.853,"z":40912.785,"elevation":163.05}]},{"id":"road-30089","name":"2-й проезд Марьиной Рощи","highway":"residential","points":[{"lat":55.795572,"lon":37.62216,"x":16116.006,"z":41114.709,"elevation":165.09},{"lat":55.795534,"lon":37.620662,"x":15949.155,"z":41107.233,"elevation":164.44},{"lat":55.795496,"lon":37.619163,"x":15782.304,"z":41099.758,"elevation":162.99}]},{"id":"road-30090","name":"4-я улица Марьиной Рощи","highway":"tertiary","points":[{"lat":55.795633,"lon":37.624222,"x":16345.447,"z":41126.927,"elevation":162.02},{"lat":55.796649,"lon":37.624152,"x":16337.71,"z":41327.985,"elevation":162.02}]},{"id":"road-30091","name":"2-й проезд Марьиной Рощи","highway":"residential","points":[{"lat":55.795633,"lon":37.624222,"x":16345.447,"z":41126.927,"elevation":162.02},{"lat":55.795184,"lon":37.625281,"x":16463.419,"z":41037.967,"elevation":161.24},{"lat":55.794739,"lon":37.624294,"x":16353.473,"z":40949.953,"elevation":162.01}]},{"id":"road-30092","name":"2-й проезд Марьиной Рощи","highway":"residential","points":[{"lat":55.795633,"lon":37.624222,"x":16345.447,"z":41126.927,"elevation":162.02},{"lat":55.795572,"lon":37.62216,"x":16116.006,"z":41114.709,"elevation":165.09}]},{"id":"road-30267","name":"8-й проезд Марьиной Рощи","highway":"tertiary","points":[{"lat":55.800879,"lon":37.610339,"x":14800.043,"z":42165.86,"elevation":163.21},{"lat":55.800953,"lon":37.61204,"x":14989.386,"z":42180.529,"elevation":161.43},{"lat":55.801027,"lon":37.613741,"x":15178.73,"z":42195.198,"elevation":161.82},{"lat":55.801102,"lon":37.615442,"x":15368.073,"z":42209.867,"elevation":163.67}]},{"id":"road-30268","name":"11-й проезд Марьиной Рощи","highway":"residential","points":[{"lat":55.80358,"lon":37.611813,"x":14964.184,"z":42700.818,"elevation":163.42},{"lat":55.803596,"lon":37.613706,"x":15174.889,"z":42703.918,"elevation":164.26},{"lat":55.803612,"lon":37.615599,"x":15385.595,"z":42707.018,"elevation":161.47}]},{"id":"road-30514","name":"Большая Марьинская улица","highway":"residential","points":[{"lat":55.809836,"lon":37.634799,"x":17522.929,"z":43939.862,"elevation":160.54},{"lat":55.808537,"lon":37.634603,"x":17501.058,"z":43682.611,"elevation":160.73},{"lat":55.807238,"lon":37.634406,"x":17479.188,"z":43425.361,"elevation":165.11},{"lat":55.80594,"lon":37.63421,"x":17457.317,"z":43168.11,"elevation":163.25}]},{"id":"road-30711","name":"Мурманский проезд","highway":"tertiary","points":[{"lat":55.807394,"lon":37.621103,"x":15998.275,"z":43456.201,"elevation":164.15},{"lat":55.806536,"lon":37.622684,"x":16174.282,"z":43286.215,"elevation":167.6},{"lat":55.805678,"lon":37.624265,"x":16350.289,"z":43116.229,"elevation":168.24},{"lat":55.804819,"lon":37.625846,"x":16526.297,"z":42946.243,"elevation":167.48},{"lat":55.803961,"lon":37.627427,"x":16702.304,"z":42776.257,"elevation":164.74},{"lat":55.803103,"lon":37.629008,"x":16878.311,"z":42606.271,"elevation":163.96},{"lat":55.802245,"lon":37.63059,"x":17054.318,"z":42436.286,"elevation":161.79}]},{"id":"road-32478","name":"13-й проезд Марьиной Рощи","highway":"residential","points":[{"lat":55.805817,"lon":37.615623,"x":15388.266,"z":43143.885,"elevation":166.22},{"lat":55.805843,"lon":37.617556,"x":15603.397,"z":43148.907,"elevation":165.99},{"lat":55.805868,"lon":37.619488,"x":15818.527,"z":43153.928,"elevation":164.19}]},{"id":"road-32479","name":"Шереметьевская улица","highway":"secondary","points":[{"lat":55.805817,"lon":37.615623,"x":15388.266,"z":43143.885,"elevation":166.22},{"lat":55.806919,"lon":37.61582,"x":15410.152,"z":43362.031,"elevation":165.71}]},{"id":"road-32481","name":"2-я улица Марьиной Рощи","highway":"tertiary","points":[{"lat":55.797519,"lon":37.619073,"x":15772.296,"z":41500.432,"elevation":161.78},{"lat":55.798505,"lon":37.619022,"x":15766.675,"z":41695.678,"elevation":162.48}]},{"id":"road-32482","name":"2-я улица Марьиной Рощи","highway":"tertiary","points":[{"lat":55.797519,"lon":37.619073,"x":15772.296,"z":41500.432,"elevation":161.78},{"lat":55.796493,"lon":37.619123,"x":15777.851,"z":41297.112,"elevation":162.86}]},{"id":"road-32483","name":"3-я улица Марьиной Рощи","highway":"residential","points":[{"lat":55.797616,"lon":37.622037,"x":16102.314,"z":41519.543,"elevation":166.66},{"lat":55.796597,"lon":37.622091,"x":16108.314,"z":41317.846,"elevation":163.21}]},{"id":"road-32484","name":"4-й проезд Марьиной Рощи","highway":"tertiary","points":[{"lat":55.797616,"lon":37.622037,"x":16102.314,"z":41519.543,"elevation":166.66},{"lat":55.797568,"lon":37.620555,"x":15937.305,"z":41509.988,"elevation":165.45},{"lat":55.797519,"lon":37.619073,"x":15772.296,"z":41500.432,"elevation":161.78}]},{"id":"road-32747","name":"1-й проезд Марьиной Рощи","highway":"tertiary","points":[{"lat":55.794381,"lon":37.616255,"x":15458.565,"z":40879.003,"elevation":161.99},{"lat":55.794418,"lon":37.617742,"x":15624.163,"z":40886.21,"elevation":159.79},{"lat":55.794454,"lon":37.61923,"x":15789.762,"z":40893.418,"elevation":163.7}]},{"id":"road-32748","name":"Шереметьевская улица","highway":"secondary","points":[{"lat":55.794381,"lon":37.616255,"x":15458.565,"z":40879.003,"elevation":161.99},{"lat":55.795402,"lon":37.616196,"x":15452.086,"z":41081.087,"elevation":162.82},{"lat":55.796422,"lon":37.616138,"x":15445.607,"z":41283.171,"elevation":161.52}]},{"id":"road-32920","name":"6-й проезд Марьиной Рощи","highway":"unclassified","points":[{"lat":55.799377,"lon":37.612584,"x":15049.978,"z":41868.312,"elevation":165.71},{"lat":55.799425,"lon":37.614446,"x":15257.272,"z":41877.917,"elevation":165.69},{"lat":55.799003,"lon":37.615851,"x":15413.603,"z":41794.263,"elevation":164.17}]},{"id":"road-32924","name":"nan","highway":"tertiary","points":[{"lat":55.801016,"lon":37.616227,"x":15455.492,"z":42192.954,"elevation":162.85},{"lat":55.801265,"lon":37.6161,"x":15441.31,"z":42242.249,"elevation":163.03}]},{"id":"road-32925","name":"Веткина улица","highway":"residential","points":[{"lat":55.801016,"lon":37.616227,"x":15455.492,"z":42192.954,"elevation":162.85},{"lat":55.80144,"lon":37.616988,"x":15540.206,"z":42276.869,"elevation":160.61}]},{"id":"road-32926","name":"9-й проезд Марьиной Рощи","highway":"residential","points":[{"lat":55.801452,"lon":37.615575,"x":15382.968,"z":42279.266,"elevation":164.3},{"lat":55.801435,"lon":37.613874,"x":15193.609,"z":42275.866,"elevation":163.42},{"lat":55.801418,"lon":37.612173,"x":15004.251,"z":42272.466,"elevation":163.1},{"lat":55.8014,"lon":37.610472,"x":14814.893,"z":42269.066,"elevation":163.25}]},{"id":"road-32927","name":"nan","highway":"tertiary","points":[{"lat":55.801452,"lon":37.615575,"x":15382.968,"z":42279.266,"elevation":164.3},{"lat":55.801102,"lon":37.615442,"x":15368.073,"z":42209.867,"elevation":163.67}]},{"id":"road-32928","name":"nan","highway":"tertiary","points":[{"lat":55.801102,"lon":37.615442,"x":15368.073,"z":42209.867,"elevation":163.67},{"lat":55.801016,"lon":37.616227,"x":15455.492,"z":42192.954,"elevation":162.85}]},{"id":"road-32929","name":"8-й проезд Марьиной Рощи","highway":"tertiary","points":[{"lat":55.801102,"lon":37.615442,"x":15368.073,"z":42209.867,"elevation":163.67},{"lat":55.801027,"lon":37.613741,"x":15178.73,"z":42195.198,"elevation":161.82},{"lat":55.800953,"lon":37.61204,"x":14989.386,"z":42180.529,"elevation":161.43},{"lat":55.800879,"lon":37.610339,"x":14800.043,"z":42165.86,"elevation":163.21}]},{"id":"road-32930","name":"Шереметьевская улица","highway":"secondary","points":[{"lat":55.803109,"lon":37.615787,"x":15406.545,"z":42607.411,"elevation":161.92},{"lat":55.803913,"lon":37.61575,"x":15402.343,"z":42766.776,"elevation":161.24},{"lat":55.804718,"lon":37.615712,"x":15398.14,"z":42926.142,"elevation":163.42}]},{"id":"road-32931","name":"nan","highway":"tertiary","points":[{"lat":55.802457,"lon":37.615495,"x":15373.995,"z":42478.274,"elevation":165.97},{"lat":55.801452,"lon":37.615575,"x":15382.968,"z":42279.266,"elevation":164.3}]},{"id":"road-32932","name":"10-й проезд Марьиной Рощи","highway":"residential","points":[{"lat":55.802457,"lon":37.615495,"x":15373.995,"z":42478.274,"elevation":165.97},{"lat":55.802417,"lon":37.613273,"x":15126.627,"z":42470.431,"elevation":168.46},{"lat":55.802378,"lon":37.611051,"x":14879.258,"z":42462.588,"elevation":162.63}]},{"id":"road-32935","name":"10-й проезд Марьиной Рощи","highway":"residential","points":[{"lat":55.802378,"lon":37.611051,"x":14879.258,"z":42462.588,"elevation":162.63},{"lat":55.802417,"lon":37.613273,"x":15126.627,"z":42470.431,"elevation":168.46},{"lat":55.802457,"lon":37.615495,"x":15373.995,"z":42478.274,"elevation":165.97}]},{"id":"road-32938","name":"nan","highway":"tertiary","points":[{"lat":55.801265,"lon":37.6161,"x":15441.31,"z":42242.249,"elevation":163.03},{"lat":55.802211,"lon":37.616137,"x":15445.506,"z":42429.577,"elevation":162.78},{"lat":55.803109,"lon":37.615787,"x":15406.545,"z":42607.411,"elevation":161.92}]},{"id":"road-32939","name":"Веткина улица","highway":"tertiary","points":[{"lat":55.801265,"lon":37.6161,"x":15441.31,"z":42242.249,"elevation":163.03},{"lat":55.80144,"lon":37.616988,"x":15540.206,"z":42276.869,"elevation":160.61}]},{"id":"road-32940","name":"['5-й проезд Марьиной Рощи', '4-я улица Марьиной Рощи']","highway":"residential","points":[{"lat":55.797676,"lon":37.624043,"x":16325.51,"z":41531.425,"elevation":160.29},{"lat":55.798651,"lon":37.623831,"x":16301.926,"z":41724.551,"elevation":158.7},{"lat":55.798622,"lon":37.621968,"x":16094.566,"z":41718.829,"elevation":163.25}]},{"id":"road-32941","name":"4-й проезд Марьиной Рощи","highway":"tertiary","points":[{"lat":55.797676,"lon":37.624043,"x":16325.51,"z":41531.425,"elevation":160.29},{"lat":55.797616,"lon":37.622037,"x":16102.314,"z":41519.543,"elevation":166.66}]},{"id":"road-32942","name":"6-й проезд Марьиной Рощи","highway":"living_street","points":[{"lat":55.799556,"lon":37.618981,"x":15762.122,"z":41903.841,"elevation":162.96},{"lat":55.799571,"lon":37.620442,"x":15924.654,"z":41906.752,"elevation":162.77},{"lat":55.799586,"lon":37.621902,"x":16087.186,"z":41909.664,"elevation":158.85}]},{"id":"road-32943","name":"2-я улица Марьиной Рощи","highway":"residential","points":[{"lat":55.799556,"lon":37.618981,"x":15762.122,"z":41903.841,"elevation":162.96},{"lat":55.800271,"lon":37.618437,"x":15701.497,"z":42045.293,"elevation":159.72},{"lat":55.800252,"lon":37.616686,"x":15506.588,"z":42041.623,"elevation":162.65}]},{"id":"road-32944","name":"2-я улица Марьиной Рощи","highway":"residential","points":[{"lat":55.799556,"lon":37.618981,"x":15762.122,"z":41903.841,"elevation":162.96},{"lat":55.798505,"lon":37.619022,"x":15766.675,"z":41695.678,"elevation":162.48}]},{"id":"road-32945","name":"6-й проезд Марьиной Рощи","highway":"living_street","points":[{"lat":55.799586,"lon":37.621902,"x":16087.186,"z":41909.664,"elevation":158.85},{"lat":55.799571,"lon":37.620442,"x":15924.654,"z":41906.752,"elevation":162.77},{"lat":55.799556,"lon":37.618981,"x":15762.122,"z":41903.841,"elevation":162.96}]},{"id":"road-32946","name":"3-я улица Марьиной Рощи","highway":"residential","points":[{"lat":55.799586,"lon":37.621902,"x":16087.186,"z":41909.664,"elevation":158.85},{"lat":55.798622,"lon":37.621968,"x":16094.566,"z":41718.829,"elevation":163.25}]},{"id":"road-32947","name":"3-я улица Марьиной Рощи","highway":"residential","points":[{"lat":55.799586,"lon":37.621902,"x":16087.186,"z":41909.664,"elevation":158.85},{"lat":55.800542,"lon":37.621851,"x":16081.497,"z":42098.958,"elevation":157.0}]},{"id":"road-36003","name":"2-й проезд Марьиной Рощи","highway":"residential","points":[{"lat":55.794739,"lon":37.624294,"x":16353.473,"z":40949.953,"elevation":162.01},{"lat":55.795184,"lon":37.625281,"x":16463.419,"z":41037.967,"elevation":161.24},{"lat":55.795633,"lon":37.624222,"x":16345.447,"z":41126.927,"elevation":162.02}]},{"id":"road-36004","name":"4-я улица Марьиной Рощи","highway":"tertiary","points":[{"lat":55.794739,"lon":37.624294,"x":16353.473,"z":40949.953,"elevation":162.01},{"lat":55.795633,"lon":37.624222,"x":16345.447,"z":41126.927,"elevation":162.02}]},{"id":"road-36197","name":"Широкий проезд","highway":"tertiary","points":[{"lat":55.804872,"lon":37.635993,"x":17655.889,"z":42956.625,"elevation":163.71},{"lat":55.804867,"lon":37.63403,"x":17437.28,"z":42955.654,"elevation":164.35}]},{"id":"road-36774","name":"Шереметьевская улица","highway":"secondary","points":[{"lat":55.796415,"lon":37.615997,"x":15429.833,"z":41281.765,"elevation":161.71},{"lat":55.795391,"lon":37.616053,"x":15436.145,"z":41078.918,"elevation":163.07},{"lat":55.794366,"lon":37.61611,"x":15442.457,"z":40876.072,"elevation":162.34}]},{"id":"road-36775","name":"Шереметьевская улица","highway":"secondary","points":[{"lat":55.79845,"lon":37.615886,"x":15417.577,"z":41684.825,"elevation":164.69},{"lat":55.797433,"lon":37.615941,"x":15423.705,"z":41483.295,"elevation":162.71},{"lat":55.796415,"lon":37.615997,"x":15429.833,"z":41281.765,"elevation":161.71}]},{"id":"road-36776","name":"5-й проезд Марьиной Рощи","highway":"tertiary","points":[{"lat":55.79845,"lon":37.615886,"x":15417.577,"z":41684.825,"elevation":164.69},{"lat":55.798403,"lon":37.614274,"x":15238.069,"z":41675.379,"elevation":168.75},{"lat":55.798355,"lon":37.612661,"x":15058.56,"z":41665.932,"elevation":166.99}]},{"id":"road-36777","name":"nan","highway":"tertiary","points":[{"lat":55.802994,"lon":37.615628,"x":15388.767,"z":42584.594,"elevation":162.87},{"lat":55.802457,"lon":37.615495,"x":15373.995,"z":42478.274,"elevation":165.97}]},{"id":"road-36778","name":"Шереметьевская улица","highway":"secondary","points":[{"lat":55.802994,"lon":37.615628,"x":15388.767,"z":42584.594,"elevation":162.87},{"lat":55.801996,"lon":37.615683,"x":15394.976,"z":42387.011,"elevation":164.57},{"lat":55.800998,"lon":37.615739,"x":15401.185,"z":42189.428,"elevation":163.86},{"lat":55.800001,"lon":37.615795,"x":15407.394,"z":41991.846,"elevation":164.05},{"lat":55.799003,"lon":37.615851,"x":15413.603,"z":41794.263,"elevation":164.17}]},{"id":"road-36779","name":"Шереметьевская улица","highway":"secondary","points":[{"lat":55.803612,"lon":37.615599,"x":15385.595,"z":42707.018,"elevation":161.47},{"lat":55.802994,"lon":37.615628,"x":15388.767,"z":42584.594,"elevation":162.87}]},{"id":"road-36784","name":"Шереметьевская улица","highway":"secondary","points":[{"lat":55.80681,"lon":37.615471,"x":15371.346,"z":43340.638,"elevation":166.05},{"lat":55.805744,"lon":37.615514,"x":15376.095,"z":43129.431,"elevation":166.25},{"lat":55.804678,"lon":37.615556,"x":15380.845,"z":42918.225,"elevation":163.84},{"lat":55.803612,"lon":37.615599,"x":15385.595,"z":42707.018,"elevation":161.47}]},{"id":"road-37599","name":"nan","highway":"tertiary","points":[{"lat":55.800049,"lon":37.634439,"x":17482.854,"z":42001.32,"elevation":161.41},{"lat":55.800327,"lon":37.633955,"x":17428.975,"z":42056.437,"elevation":163.24}]},{"id":"road-37600","name":"nan","highway":"tertiary","points":[{"lat":55.800049,"lon":37.634439,"x":17482.854,"z":42001.32,"elevation":161.41},{"lat":55.800486,"lon":37.634708,"x":17512.821,"z":42087.887,"elevation":165.08}]},{"id":"road-37601","name":"nan","highway":"tertiary","points":[{"lat":55.800049,"lon":37.634439,"x":17482.854,"z":42001.32,"elevation":161.41},{"lat":55.799451,"lon":37.635591,"x":17611.085,"z":41883.023,"elevation":162.85},{"lat":55.799421,"lon":37.636955,"x":17762.945,"z":41877.065,"elevation":162.98}]},{"id":"road-38204","name":"Большая Марьинская улица","highway":"residential","points":[{"lat":55.802134,"lon":37.633571,"x":17386.217,"z":42414.301,"elevation":168.4},{"lat":55.803045,"lon":37.633724,"x":17403.238,"z":42594.752,"elevation":166.88},{"lat":55.803956,"lon":37.633877,"x":17420.259,"z":42775.203,"elevation":166.26},{"lat":55.804867,"lon":37.63403,"x":17437.28,"z":42955.654,"elevation":164.35}]},{"id":"road-38713","name":"проспект Мира","highway":"primary","points":[{"lat":55.800411,"lon":37.635555,"x":17607.109,"z":42073.113,"elevation":164.81},{"lat":55.799189,"lon":37.635301,"x":17578.773,"z":41831.011,"elevation":162.35},{"lat":55.797966,"lon":37.635046,"x":17550.438,"z":41588.91,"elevation":159.2},{"lat":55.796744,"lon":37.634792,"x":17522.103,"z":41346.809,"elevation":158.86},{"lat":55.795521,"lon":37.634537,"x":17493.768,"z":41104.708,"elevation":158.1},{"lat":55.794298,"lon":37.634283,"x":17465.432,"z":40862.607,"elevation":157.3}]},{"id":"road-39873","name":"Шереметьевская улица","highway":"secondary","points":[{"lat":55.799003,"lon":37.615851,"x":15413.603,"z":41794.263,"elevation":164.17},{"lat":55.79845,"lon":37.615886,"x":15417.577,"z":41684.825,"elevation":164.69}]},{"id":"road-40083","name":"5-й проезд Марьиной Рощи","highway":"living_street","points":[{"lat":55.798555,"lon":37.620684,"x":15951.677,"z":41705.639,"elevation":163.46},{"lat":55.798505,"lon":37.619022,"x":15766.675,"z":41695.678,"elevation":162.48}]},{"id":"road-40084","name":"5-й проезд Марьиной Рощи","highway":"living_street","points":[{"lat":55.798555,"lon":37.620684,"x":15951.677,"z":41705.639,"elevation":163.46},{"lat":55.798602,"lon":37.621513,"x":16043.938,"z":41714.908,"elevation":163.64}]},{"id":"road-40085","name":"5-й проезд Марьиной Рощи","highway":"living_street","points":[{"lat":55.798555,"lon":37.620684,"x":15951.677,"z":41705.639,"elevation":163.46},{"lat":55.798602,"lon":37.621513,"x":16043.938,"z":41714.908,"elevation":163.64}]},{"id":"road-40086","name":"5-й проезд Марьиной Рощи","highway":"living_street","points":[{"lat":55.798602,"lon":37.621513,"x":16043.938,"z":41714.908,"elevation":163.64},{"lat":55.798622,"lon":37.621968,"x":16094.566,"z":41718.829,"elevation":163.25}]},{"id":"road-40087","name":"5-й проезд Марьиной Рощи","highway":"living_street","points":[{"lat":55.798602,"lon":37.621513,"x":16043.938,"z":41714.908,"elevation":163.64},{"lat":55.798555,"lon":37.620684,"x":15951.677,"z":41705.639,"elevation":163.46}]},{"id":"road-40088","name":"5-й проезд Марьиной Рощи","highway":"living_street","points":[{"lat":55.798602,"lon":37.621513,"x":16043.938,"z":41714.908,"elevation":163.64},{"lat":55.798555,"lon":37.620684,"x":15951.677,"z":41705.639,"elevation":163.46}]},{"id":"road-40236","name":"14-й проезд Марьиной Рощи","highway":"tertiary","points":[{"lat":55.807025,"lon":37.615126,"x":15332.952,"z":43383.167,"elevation":166.66},{"lat":55.80681,"lon":37.615471,"x":15371.346,"z":43340.638,"elevation":166.05}]},{"id":"road-42700","name":"nan","highway":"tertiary","points":[{"lat":55.799421,"lon":37.636955,"x":17762.945,"z":41877.065,"elevation":162.98},{"lat":55.799451,"lon":37.635591,"x":17611.085,"z":41883.023,"elevation":162.85},{"lat":55.800049,"lon":37.634439,"x":17482.854,"z":42001.32,"elevation":161.41}]},{"id":"road-43138","name":"nan","highway":"unclassified","points":[{"lat":55.794366,"lon":37.61611,"x":15442.457,"z":40876.072,"elevation":162.34},{"lat":55.794384,"lon":37.614559,"x":15269.817,"z":40879.557,"elevation":166.78},{"lat":55.794402,"lon":37.613008,"x":15097.177,"z":40883.042,"elevation":166.11}]},{"id":"road-43139","name":"Шереметьевская улица","highway":"secondary","points":[{"lat":55.794366,"lon":37.61611,"x":15442.457,"z":40876.072,"elevation":162.34},{"lat":55.793362,"lon":37.615871,"x":15415.874,"z":40677.204,"elevation":162.03}]},{"id":"road-43140","name":"Октябрьская улица","highway":"tertiary","points":[{"lat":55.794402,"lon":37.613008,"x":15097.177,"z":40883.042,"elevation":166.11},{"lat":55.793277,"lon":37.61313,"x":15110.736,"z":40660.313,"elevation":164.12}]},{"id":"road-43141","name":"nan","highway":"unclassified","points":[{"lat":55.794402,"lon":37.613008,"x":15097.177,"z":40883.042,"elevation":166.11},{"lat":55.794384,"lon":37.614559,"x":15269.817,"z":40879.557,"elevation":166.78},{"lat":55.794366,"lon":37.61611,"x":15442.457,"z":40876.072,"elevation":162.34}]},{"id":"road-43466","name":"nan","highway":"secondary_link","points":[{"lat":55.794582,"lon":37.635273,"x":17575.65,"z":40918.805,"elevation":159.15},{"lat":55.79468,"lon":37.6346,"x":17500.754,"z":40938.211,"elevation":158.14}]},{"id":"road-43467","name":"nan","highway":"secondary_link","points":[{"lat":55.794582,"lon":37.635273,"x":17575.65,"z":40918.805,"elevation":159.15},{"lat":55.795158,"lon":37.635386,"x":17588.296,"z":41032.766,"elevation":159.38}]},{"id":"road-43766","name":"nan","highway":"tertiary","points":[{"lat":55.800486,"lon":37.634708,"x":17512.821,"z":42087.887,"elevation":165.08},{"lat":55.800623,"lon":37.634793,"x":17522.239,"z":42115.079,"elevation":166.23}]},{"id":"road-43767","name":"nan","highway":"tertiary","points":[{"lat":55.800486,"lon":37.634708,"x":17512.821,"z":42087.887,"elevation":165.08},{"lat":55.800049,"lon":37.634439,"x":17482.854,"z":42001.32,"elevation":161.41}]},{"id":"road-43768","name":"nan","highway":"tertiary","points":[{"lat":55.800486,"lon":37.634708,"x":17512.821,"z":42087.887,"elevation":165.08},{"lat":55.800327,"lon":37.633955,"x":17428.975,"z":42056.437,"elevation":163.24}]},{"id":"road-43770","name":"Проспект Мира (дублёр)","highway":"tertiary","points":[{"lat":55.804816,"lon":37.636002,"x":17656.869,"z":42945.672,"elevation":163.73},{"lat":55.803943,"lon":37.635829,"x":17637.621,"z":42772.635,"elevation":164.01},{"lat":55.803069,"lon":37.635657,"x":17618.374,"z":42599.598,"elevation":164.85},{"lat":55.802196,"lon":37.635484,"x":17599.127,"z":42426.561,"elevation":166.42}]},{"id":"road-43771","name":"улица Годовикова","highway":"tertiary","points":[{"lat":55.80229,"lon":37.630907,"x":17089.685,"z":42445.198,"elevation":162.35},{"lat":55.802092,"lon":37.630873,"x":17085.922,"z":42406.082,"elevation":161.6}]},{"id":"road-43772","name":"улица Годовикова","highway":"tertiary","points":[{"lat":55.80229,"lon":37.630907,"x":17089.685,"z":42445.198,"elevation":162.35},{"lat":55.803216,"lon":37.631046,"x":17105.084,"z":42628.714,"elevation":165.17},{"lat":55.804143,"lon":37.631184,"x":17120.483,"z":42812.229,"elevation":166.13},{"lat":55.805069,"lon":37.631322,"x":17135.882,"z":42995.745,"elevation":164.86}]},{"id":"road-43773","name":"улица Годовикова","highway":"tertiary","points":[{"lat":55.80229,"lon":37.630907,"x":17089.685,"z":42445.198,"elevation":162.35},{"lat":55.802245,"lon":37.63059,"x":17054.318,"z":42436.286,"elevation":161.79}]},{"id":"road-43793","name":"Веткина улица","highway":"tertiary","points":[{"lat":55.805021,"lon":37.620155,"x":15892.722,"z":42986.098,"elevation":163.79},{"lat":55.804781,"lon":37.620185,"x":15896.084,"z":42938.68,"elevation":163.63}]},{"id":"road-43794","name":"Веткина улица","highway":"tertiary","points":[{"lat":55.805021,"lon":37.620155,"x":15892.722,"z":42986.098,"elevation":163.79},{"lat":55.805868,"lon":37.619488,"x":15818.527,"z":43153.928,"elevation":164.19}]},{"id":"road-43795","name":"Веткин проезд","highway":"unclassified","points":[{"lat":55.805021,"lon":37.620155,"x":15892.722,"z":42986.098,"elevation":163.79},{"lat":55.804171,"lon":37.621785,"x":16074.168,"z":42817.901,"elevation":162.85},{"lat":55.803185,"lon":37.623234,"x":16235.511,"z":42622.469,"elevation":161.9},{"lat":55.802198,"lon":37.624683,"x":16396.854,"z":42427.036,"elevation":160.6}]},{"id":"road-44407","name":"4-я улица Марьиной Рощи","highway":"tertiary","points":[{"lat":55.792814,"lon":37.624165,"x":16339.202,"z":40568.613,"elevation":158.0},{"lat":55.793712,"lon":37.624128,"x":16335.044,"z":40746.471,"elevation":159.82},{"lat":55.79461,"lon":37.624091,"x":16330.886,"z":40924.329,"elevation":162.1}]},{"id":"road-46003","name":"Мурманский проезд","highway":"tertiary","points":[{"lat":55.802092,"lon":37.630873,"x":17085.922,"z":42406.082,"elevation":161.6},{"lat":55.802245,"lon":37.63059,"x":17054.318,"z":42436.286,"elevation":161.79}]},{"id":"road-46004","name":"улица Годовикова","highway":"tertiary","points":[{"lat":55.802092,"lon":37.630873,"x":17085.922,"z":42406.082,"elevation":161.6},{"lat":55.80229,"lon":37.630907,"x":17089.685,"z":42445.198,"elevation":162.35}]},{"id":"road-46005","name":"Мурманский проезд","highway":"tertiary","points":[{"lat":55.802092,"lon":37.630873,"x":17085.922,"z":42406.082,"elevation":161.6},{"lat":55.80121,"lon":37.632414,"x":17257.449,"z":42231.259,"elevation":164.95},{"lat":55.800327,"lon":37.633955,"x":17428.975,"z":42056.437,"elevation":163.24}]},{"id":"road-46006","name":"Мурманский проезд","highway":"tertiary","points":[{"lat":55.802245,"lon":37.63059,"x":17054.318,"z":42436.286,"elevation":161.79},{"lat":55.802092,"lon":37.630873,"x":17085.922,"z":42406.082,"elevation":161.6}]},{"id":"road-46007","name":"Мурманский проезд","highway":"tertiary","points":[{"lat":55.802245,"lon":37.63059,"x":17054.318,"z":42436.286,"elevation":161.79},{"lat":55.803103,"lon":37.629008,"x":16878.311,"z":42606.271,"elevation":163.96},{"lat":55.803961,"lon":37.627427,"x":16702.304,"z":42776.257,"elevation":164.74},{"lat":55.804819,"lon":37.625846,"x":16526.297,"z":42946.243,"elevation":167.48},{"lat":55.805678,"lon":37.624265,"x":16350.289,"z":43116.229,"elevation":168.24},{"lat":55.806536,"lon":37.622684,"x":16174.282,"z":43286.215,"elevation":167.6},{"lat":55.807394,"lon":37.621103,"x":15998.275,"z":43456.201,"elevation":164.15}]},{"id":"road-48354","name":"3-я улица Марьиной Рощи","highway":"residential","points":[{"lat":55.800542,"lon":37.621851,"x":16081.497,"z":42098.958,"elevation":157.0},{"lat":55.799586,"lon":37.621902,"x":16087.186,"z":41909.664,"elevation":158.85}]},{"id":"road-50275","name":"2-я улица Марьиной Рощи","highway":"residential","points":[{"lat":55.800252,"lon":37.616686,"x":15506.588,"z":42041.623,"elevation":162.65},{"lat":55.800271,"lon":37.618437,"x":15701.497,"z":42045.293,"elevation":159.72},{"lat":55.799556,"lon":37.618981,"x":15762.122,"z":41903.841,"elevation":162.96}]},{"id":"road-50276","name":"Шереметьевская улица","highway":"secondary","points":[{"lat":55.798676,"lon":37.616024,"x":15432.872,"z":41729.444,"elevation":164.09},{"lat":55.799784,"lon":37.615965,"x":15426.29,"z":41948.936,"elevation":163.84},{"lat":55.800892,"lon":37.615906,"x":15419.709,"z":42168.427,"elevation":163.81},{"lat":55.802,"lon":37.615846,"x":15413.127,"z":42387.919,"elevation":163.95},{"lat":55.803109,"lon":37.615787,"x":15406.545,"z":42607.411,"elevation":161.92}]},{"id":"road-50277","name":"nan","highway":"residential","points":[{"lat":55.798676,"lon":37.616024,"x":15432.872,"z":41729.444,"elevation":164.09},{"lat":55.799411,"lon":37.616675,"x":15505.328,"z":41875.021,"elevation":163.0},{"lat":55.800252,"lon":37.616686,"x":15506.588,"z":42041.623,"elevation":162.65}]},{"id":"road-50636","name":"nan","highway":"secondary_link","points":[{"lat":55.795158,"lon":37.635386,"x":17588.296,"z":41032.766,"elevation":159.38},{"lat":55.795664,"lon":37.635482,"x":17598.938,"z":41132.967,"elevation":159.12}]},{"id":"road-50637","name":"nan","highway":"secondary_link","points":[{"lat":55.795158,"lon":37.635386,"x":17588.296,"z":41032.766,"elevation":159.38},{"lat":55.795286,"lon":37.636004,"x":17657.002,"z":41058.173,"elevation":159.32}]},{"id":"road-50638","name":"nan","highway":"secondary_link","points":[{"lat":55.795158,"lon":37.635386,"x":17588.296,"z":41032.766,"elevation":159.38},{"lat":55.794582,"lon":37.635273,"x":17575.65,"z":40918.805,"elevation":159.15}]},{"id":"road-50832","name":"13-й проезд Марьиной Рощи","highway":"residential","points":[{"lat":55.805868,"lon":37.619488,"x":15818.527,"z":43153.928,"elevation":164.19},{"lat":55.805843,"lon":37.617556,"x":15603.397,"z":43148.907,"elevation":165.99},{"lat":55.805817,"lon":37.615623,"x":15388.266,"z":43143.885,"elevation":166.22}]},{"id":"road-50833","name":"Веткина улица","highway":"tertiary","points":[{"lat":55.805868,"lon":37.619488,"x":15818.527,"z":43153.928,"elevation":164.19},{"lat":55.805021,"lon":37.620155,"x":15892.722,"z":42986.098,"elevation":163.79}]},{"id":"road-50834","name":"Веткина улица","highway":"tertiary","points":[{"lat":55.805868,"lon":37.619488,"x":15818.527,"z":43153.928,"elevation":164.19},{"lat":55.806461,"lon":37.618677,"x":15728.269,"z":43271.479,"elevation":164.83},{"lat":55.807055,"lon":37.617867,"x":15638.012,"z":43389.03,"elevation":164.12}]},{"id":"road-50835","name":"Веткин проезд","highway":"unclassified","points":[{"lat":55.802198,"lon":37.624683,"x":16396.854,"z":42427.036,"elevation":160.6},{"lat":55.803185,"lon":37.623234,"x":16235.511,"z":42622.469,"elevation":161.9},{"lat":55.804171,"lon":37.621785,"x":16074.168,"z":42817.901,"elevation":162.85},{"lat":55.805021,"lon":37.620155,"x":15892.722,"z":42986.098,"elevation":163.79}]}],"buildings":[{"id":"building-181","name":"Торгово-развлекательный центр \"Райкин плаза\"","building":"retail","height":15.0,"heightSource":"building:levels","baseElevation":161.79,"lat":55.79542,"lon":37.617032,"x":15545.093,"z":41084.609,"footprint":[{"x":15500.12,"z":40899.953},{"x":15493.898,"z":41123.026},{"x":15504.217,"z":41125.997},{"x":15497.56,"z":41175.087},{"x":15486.183,"z":41174.691},{"x":15485.103,"z":41252.675},{"x":15505.074,"z":41262.596},{"x":15493.686,"z":41272.775},{"x":15575.996,"z":41274.616},{"x":15576.341,"z":41264.893},{"x":15604.237,"z":41254.398},{"x":15594.775,"z":41111.541},{"x":15595.944,"z":41061.381},{"x":15608.367,"z":41061.579},{"x":15609.837,"z":41017.38},{"x":15598.237,"z":41017.222},{"x":15608.879,"z":40908.151}]},{"id":"building-1119","name":"","building":"apartments","height":27.0,"heightSource":"building:levels","baseElevation":167.61,"lat":55.80141,"lon":37.63464,"x":17505.269,"z":42271.057,"footprint":[{"x":17488.275,"z":42246.112},{"x":17471.533,"z":42146.966},{"x":17381.464,"z":42154.71},{"x":17271.692,"z":42260.015},{"x":17296.795,"z":42286.277},{"x":17313.448,"z":42269.858},{"x":17305.444,"z":42261.203},{"x":17391.583,"z":42180.199},{"x":17444.894,"z":42175.03},{"x":17458.675,"z":42279.306},{"x":17527.66,"z":42272.255},{"x":17540.05,"z":42395.189},{"x":17565.208,"z":42392.654},{"x":17550.069,"z":42242.527}]},{"id":"building-1982","name":"Планета КВН","building":"public","height":12.0,"heightSource":"building:levels","baseElevation":160.13,"lat":55.794021,"lon":37.617806,"x":15631.292,"z":40807.687,"footprint":[{"x":15586.627,"z":40848.825},{"x":15586.27,"z":40821.36},{"x":15577.988,"z":40821.36},{"x":15587.072,"z":40749.856},{"x":15672.955,"z":40750.252},{"x":15684.276,"z":40860.607}]},{"id":"building-2154","name":"","building":"school","height":12.0,"heightSource":"building:levels","baseElevation":165.47,"lat":55.80362,"lon":37.635108,"x":17557.32,"z":42708.642,"footprint":[{"x":17548.644,"z":42728.35},{"x":17538.97,"z":42712.703},{"x":17514.179,"z":42714.802},{"x":17512.921,"z":42695.649},{"x":17528.183,"z":42694.639},{"x":17526.369,"z":42666.969},{"x":17488.587,"z":42669.465},{"x":17496.034,"z":42644.944},{"x":17444.738,"z":42648.331},{"x":17444.081,"z":42702.166},{"x":17491.359,"z":42690.638},{"x":17508.302,"z":42704.463},{"x":17509.025,"z":42715.416},{"x":17487.218,"z":42716.862},{"x":17487.975,"z":42728.33},{"x":17452.798,"z":42730.648},{"x":17454.379,"z":42754.693},{"x":17541.664,"z":42740.868},{"x":17544.993,"z":42774.024},{"x":17573.568,"z":42771.39},{"x":17561.056,"z":42635.219},{"x":17530.432,"z":42638.052},{"x":17534.451,"z":42681.785},{"x":17544.291,"z":42680.873}]},{"id":"building-2324","name":"","building":"apartments","height":27.0,"heightSource":"building:levels","baseElevation":167.52,"lat":55.802252,"lon":37.613194,"x":15117.838,"z":42437.791,"footprint":[{"x":14938.803,"z":42418.183},{"x":14937.834,"z":42443.634},{"x":15296.873,"z":42457.379},{"x":15297.842,"z":42431.948}]},{"id":"building-3791","name":"","building":"apartments","height":72.0,"heightSource":"building:levels","baseElevation":164.87,"lat":55.799901,"lon":37.615188,"x":15339.805,"z":41972.088,"footprint":[{"x":15200.17,"z":41923.686},{"x":15327.531,"z":41927.726},{"x":15323.556,"z":42020.788},{"x":15352.065,"z":42016.748},{"x":15349.327,"z":41903.584},{"x":15200.971,"z":41898.356}]},{"id":"building-3963","name":"","building":"apartments","height":30.0,"heightSource":"building:levels","baseElevation":164.94,"lat":55.804386,"lon":37.635517,"x":17602.894,"z":42860.303,"footprint":[{"x":17532.391,"z":42901.482},{"x":17599.372,"z":42895.223},{"x":17593.083,"z":42828.988},{"x":17568.704,"z":42831.266},{"x":17566.41,"z":42806.765},{"x":17610.838,"z":42802.606},{"x":17621.603,"z":42917.645},{"x":17503.281,"z":42928.717},{"x":17498.951,"z":42882.348},{"x":17530.321,"z":42879.417}]},{"id":"building-4502","name":"","building":"university","height":12.0,"heightSource":"building:levels","baseElevation":166.62,"lat":55.806466,"lon":37.616742,"x":15512.843,"z":43272.479,"footprint":[{"x":15493.53,"z":43252.215},{"x":15492.729,"z":43276.738},{"x":15532.637,"z":43278.045},{"x":15532.982,"z":43267.448},{"x":15557.094,"z":43268.22},{"x":15558.118,"z":43236.785},{"x":15481.697,"z":43234.289},{"x":15482.476,"z":43218.264},{"x":15447.121,"z":43216.957},{"x":15442.947,"z":43329.546},{"x":15474.394,"z":43330.715},{"x":15467.092,"z":43251.284}]},{"id":"building-4595","name":"","building":"apartments","height":30.0,"heightSource":"building:levels","baseElevation":164.98,"lat":55.805353,"lon":37.617179,"x":15561.472,"z":43051.899,"footprint":[{"x":15491.337,"z":43107.36},{"x":15491.693,"z":43031.121},{"x":15513.49,"z":43031.22},{"x":15513.345,"z":43063.13},{"x":15548.856,"z":43063.288},{"x":15549.145,"z":43001.37},{"x":15574.27,"z":43001.489},{"x":15573.981,"z":43063.407},{"x":15598.861,"z":43063.526},{"x":15598.749,"z":43086.998},{"x":15573.869,"z":43086.879},{"x":15573.769,"z":43106.647},{"x":15548.644,"z":43106.528},{"x":15548.745,"z":43086.76},{"x":15513.234,"z":43086.602},{"x":15513.134,"z":43107.459}]},{"id":"building-6739","name":"","building":"apartments","height":66.0,"heightSource":"building:levels","baseElevation":164.34,"lat":55.803047,"lon":37.614848,"x":15301.932,"z":42595.141,"footprint":[{"x":15243.907,"z":42646.073},{"x":15290.762,"z":42652.53},{"x":15290.439,"z":42540.664},{"x":15316.621,"z":42533.078},{"x":15310.309,"z":42667.088},{"x":15285.229,"z":42662.81},{"x":15284.973,"z":42677.526},{"x":15255.284,"z":42674.773},{"x":15243.529,"z":42667.326}]},{"id":"building-6986","name":"","building":"retail","height":3.0,"heightSource":"building:levels","baseElevation":164.02,"lat":55.805398,"lon":37.635514,"x":17602.544,"z":43060.941,"footprint":[{"x":17595.665,"z":43039.836},{"x":17581.45,"z":43113.917},{"x":17622.471,"z":43111.619},{"x":17609.536,"z":42984.89},{"x":17573.056,"z":42984.019},{"x":17589.899,"z":42998.795},{"x":17577.164,"z":43032.923}]},{"id":"building-7179","name":"","building":"university","height":12.0,"heightSource":"building:levels","baseElevation":163.93,"lat":55.804133,"lon":37.614987,"x":15317.5,"z":42810.34,"footprint":[{"x":15239.065,"z":42857.609},{"x":15250.353,"z":42857.609},{"x":15250.108,"z":42898.571},{"x":15269.834,"z":42899.086},{"x":15270.735,"z":42851.43},{"x":15330.314,"z":42861.551},{"x":15330.169,"z":42758.694},{"x":15307.393,"z":42758.595},{"x":15296.417,"z":42789.256},{"x":15309.085,"z":42789.295},{"x":15308.885,"z":42839.981},{"x":15268.231,"z":42843.804},{"x":15268.398,"z":42831.385},{"x":15239.41,"z":42831.524}]},{"id":"building-7284","name":"","building":"garages","height":3.0,"heightSource":"building:levels","baseElevation":161.4,"lat":55.800342,"lon":37.617162,"x":15559.526,"z":42059.388,"footprint":[{"x":15447.299,"z":42063.27},{"x":15447.811,"z":42047.763},{"x":15744.389,"z":42061.765},{"x":15743.943,"z":42075.371}]},{"id":"building-7780","name":"","building":"apartments","height":30.0,"heightSource":"building:levels","baseElevation":165.82,"lat":55.802875,"lon":37.635233,"x":17571.22,"z":42561.025,"footprint":[{"x":17560.622,"z":42587.763},{"x":17543.0,"z":42589.447},{"x":17545.538,"z":42616.205},{"x":17589.198,"z":42612.066},{"x":17579.034,"z":42504.914},{"x":17533.282,"z":42509.271},{"x":17535.553,"z":42533.197},{"x":17555.267,"z":42531.335}]}]}