{"id":"14_32","col":14,"row":32,"bounds":{"minX":-22397.927,"minZ":-4155.07,"maxX":-19897.927,"maxZ":-1655.07},"roads":[{"id":"road-1215","name":"nan","highway":"unclassified","points":[{"lat":55.565348,"lon":37.287547,"x":-21133.031,"z":-4341.287,"elevation":159.02},{"lat":55.566261,"lon":37.286039,"x":-21300.863,"z":-4161.511,"elevation":157.61},{"lat":55.56671,"lon":37.284039,"x":-21523.529,"z":-4073.234,"elevation":158.28}]},{"id":"road-1216","name":"nan","highway":"residential","points":[{"lat":55.56671,"lon":37.284039,"x":-21523.529,"z":-4073.234,"elevation":158.28},{"lat":55.566362,"lon":37.283994,"x":-21528.572,"z":-4141.606,"elevation":158.7}]},{"id":"road-1217","name":"nan","highway":"unclassified","points":[{"lat":55.56671,"lon":37.284039,"x":-21523.529,"z":-4073.234,"elevation":158.28},{"lat":55.566949,"lon":37.282192,"x":-21729.075,"z":-4026.162,"elevation":159.98},{"lat":55.567188,"lon":37.280346,"x":-21934.621,"z":-3979.09,"elevation":158.53}]},{"id":"road-1218","name":"nan","highway":"unclassified","points":[{"lat":55.56671,"lon":37.284039,"x":-21523.529,"z":-4073.234,"elevation":158.28},{"lat":55.566261,"lon":37.286039,"x":-21300.863,"z":-4161.511,"elevation":157.61},{"lat":55.565348,"lon":37.287547,"x":-21133.031,"z":-4341.287,"elevation":159.02}]},{"id":"road-1219","name":"nan","highway":"unclassified","points":[{"lat":55.567185,"lon":37.279978,"x":-21975.586,"z":-3979.661,"elevation":158.45},{"lat":55.567188,"lon":37.280346,"x":-21934.621,"z":-3979.09,"elevation":158.53}]},{"id":"road-1220","name":"nan","highway":"residential","points":[{"lat":55.567185,"lon":37.279978,"x":-21975.586,"z":-3979.661,"elevation":158.45},{"lat":55.566232,"lon":37.279421,"x":-22037.636,"z":-4167.355,"elevation":159.14},{"lat":55.565278,"lon":37.278863,"x":-22099.685,"z":-4355.048,"elevation":160.43}]},{"id":"road-1221","name":"М-3 «Украина» – Бурцево","highway":"tertiary","points":[{"lat":55.567185,"lon":37.279978,"x":-21975.586,"z":-3979.661,"elevation":158.45},{"lat":55.56796,"lon":37.278645,"x":-22123.993,"z":-3827.009,"elevation":162.95},{"lat":55.569158,"lon":37.277932,"x":-22203.35,"z":-3591.158,"elevation":162.51},{"lat":55.570231,"lon":37.276872,"x":-22321.3,"z":-3380.022,"elevation":164.06},{"lat":55.570652,"lon":37.274778,"x":-22554.469,"z":-3297.092,"elevation":161.15},{"lat":55.570565,"lon":37.272548,"x":-22802.726,"z":-3314.159,"elevation":162.94},{"lat":55.570239,"lon":37.270392,"x":-23042.678,"z":-3378.296,"elevation":167.65},{"lat":55.570778,"lon":37.269087,"x":-23187.956,"z":-3272.325,"elevation":165.35}]},{"id":"road-2697","name":"nan","highway":"residential","points":[{"lat":55.565278,"lon":37.278863,"x":-22099.685,"z":-4355.048,"elevation":160.43},{"lat":55.566232,"lon":37.279421,"x":-22037.636,"z":-4167.355,"elevation":159.14},{"lat":55.567185,"lon":37.279978,"x":-21975.586,"z":-3979.661,"elevation":158.45}]},{"id":"road-2701","name":"nan","highway":"residential","points":[{"lat":55.566362,"lon":37.283994,"x":-21528.572,"z":-4141.606,"elevation":158.7},{"lat":55.56566,"lon":37.283623,"x":-21569.76,"z":-4279.866,"elevation":159.58}]},{"id":"road-2702","name":"nan","highway":"residential","points":[{"lat":55.566362,"lon":37.283994,"x":-21528.572,"z":-4141.606,"elevation":158.7},{"lat":55.56671,"lon":37.284039,"x":-21523.529,"z":-4073.234,"elevation":158.28}]},{"id":"road-2703","name":"nan","highway":"residential","points":[{"lat":55.566362,"lon":37.283994,"x":-21528.572,"z":-4141.606,"elevation":158.7},{"lat":55.565495,"lon":37.284801,"x":-21438.648,"z":-4312.368,"elevation":157.07}]},{"id":"road-2705","name":"nan","highway":"residential","points":[{"lat":55.56566,"lon":37.283623,"x":-21569.76,"z":-4279.866,"elevation":159.58},{"lat":55.566362,"lon":37.283994,"x":-21528.572,"z":-4141.606,"elevation":158.7}]},{"id":"road-2715","name":"nan","highway":"residential","points":[{"lat":55.565495,"lon":37.284801,"x":-21438.648,"z":-4312.368,"elevation":157.07},{"lat":55.566362,"lon":37.283994,"x":-21528.572,"z":-4141.606,"elevation":158.7}]},{"id":"road-2961","name":"nan","highway":"unclassified","points":[{"lat":55.567188,"lon":37.280346,"x":-21934.621,"z":-3979.09,"elevation":158.53},{"lat":55.567185,"lon":37.279978,"x":-21975.586,"z":-3979.661,"elevation":158.45}]},{"id":"road-2962","name":"nan","highway":"residential","points":[{"lat":55.567188,"lon":37.280346,"x":-21934.621,"z":-3979.09,"elevation":158.53},{"lat":55.566245,"lon":37.280383,"x":-21930.535,"z":-4164.758,"elevation":159.19}]},{"id":"road-2963","name":"nan","highway":"unclassified","points":[{"lat":55.567188,"lon":37.280346,"x":-21934.621,"z":-3979.09,"elevation":158.53},{"lat":55.566949,"lon":37.282192,"x":-21729.075,"z":-4026.162,"elevation":159.98},{"lat":55.56671,"lon":37.284039,"x":-21523.529,"z":-4073.234,"elevation":158.28}]},{"id":"road-2964","name":"nan","highway":"residential","points":[{"lat":55.57608,"lon":37.278182,"x":-22175.561,"z":-2228.36,"elevation":177.18},{"lat":55.576257,"lon":37.275895,"x":-22430.07,"z":-2193.388,"elevation":177.58}]},{"id":"road-2967","name":"nan","highway":"residential","points":[{"lat":55.566245,"lon":37.280383,"x":-21930.535,"z":-4164.758,"elevation":159.19},{"lat":55.567188,"lon":37.280346,"x":-21934.621,"z":-3979.09,"elevation":158.53}]},{"id":"road-2970","name":"nan","highway":"residential","points":[{"lat":55.57507,"lon":37.275194,"x":-22508.172,"z":-2427.067,"elevation":172.99},{"lat":55.574684,"lon":37.277074,"x":-22298.888,"z":-2503.163,"elevation":170.62},{"lat":55.575326,"lon":37.277441,"x":-22258.035,"z":-2376.836,"elevation":173.64},{"lat":55.575633,"lon":37.275516,"x":-22472.327,"z":-2316.264,"elevation":175.31}]},{"id":"road-2974","name":"nan","highway":"residential","points":[{"lat":55.573281,"lon":37.274958,"x":-22534.432,"z":-2779.354,"elevation":165.87},{"lat":55.573361,"lon":37.276265,"x":-22388.927,"z":-2763.723,"elevation":164.61},{"lat":55.574297,"lon":37.277142,"x":-22291.244,"z":-2579.318,"elevation":168.21}]},{"id":"road-2975","name":"nan","highway":"residential","points":[{"lat":55.574297,"lon":37.277142,"x":-22291.244,"z":-2579.318,"elevation":168.21},{"lat":55.573361,"lon":37.276265,"x":-22388.927,"z":-2763.723,"elevation":164.61},{"lat":55.573281,"lon":37.274958,"x":-22534.432,"z":-2779.354,"elevation":165.87}]},{"id":"road-2984","name":"nan","highway":"residential","points":[{"lat":55.575633,"lon":37.275516,"x":-22472.327,"z":-2316.264,"elevation":175.31},{"lat":55.575326,"lon":37.277441,"x":-22258.035,"z":-2376.836,"elevation":173.64},{"lat":55.574684,"lon":37.277074,"x":-22298.888,"z":-2503.163,"elevation":170.62},{"lat":55.57507,"lon":37.275194,"x":-22508.172,"z":-2427.067,"elevation":172.99}]},{"id":"road-2985","name":"nan","highway":"residential","points":[{"lat":55.576701,"lon":37.277718,"x":-22227.191,"z":-2105.897,"elevation":180.23},{"lat":55.576824,"lon":37.276172,"x":-22399.213,"z":-2081.715,"elevation":179.53}]},{"id":"road-2994","name":"nan","highway":"residential","points":[{"lat":55.576257,"lon":37.275895,"x":-22430.07,"z":-2193.388,"elevation":177.58},{"lat":55.57608,"lon":37.278182,"x":-22175.561,"z":-2228.36,"elevation":177.18}]},{"id":"road-2995","name":"nan","highway":"residential","points":[{"lat":55.577667,"lon":37.27661,"x":-22350.455,"z":-1915.787,"elevation":185.53},{"lat":55.577145,"lon":37.27635,"x":-22379.409,"z":-2018.542,"elevation":181.67}]},{"id":"road-2997","name":"nan","highway":"residential","points":[{"lat":55.57346,"lon":37.274078,"x":-22632.394,"z":-2744.187,"elevation":166.64},{"lat":55.572643,"lon":37.275552,"x":-22468.252,"z":-2905.127,"elevation":163.68},{"lat":55.572981,"lon":37.27705,"x":-22301.533,"z":-2838.505,"elevation":163.23},{"lat":55.573619,"lon":37.278313,"x":-22160.971,"z":-2712.877,"elevation":165.69},{"lat":55.574542,"lon":37.279653,"x":-22011.754,"z":-2531.129,"elevation":169.58},{"lat":55.574963,"lon":37.281326,"x":-21825.466,"z":-2448.27,"elevation":172.52},{"lat":55.575798,"lon":37.282318,"x":-21715.054,"z":-2283.91,"elevation":174.53}]},{"id":"road-3001","name":"nan","highway":"residential","points":[{"lat":55.577046,"lon":37.277446,"x":-22257.481,"z":-2037.998,"elevation":182.7},{"lat":55.577145,"lon":37.27635,"x":-22379.409,"z":-2018.542,"elevation":181.67}]},{"id":"road-3005","name":"nan","highway":"residential","points":[{"lat":55.576824,"lon":37.276172,"x":-22399.213,"z":-2081.715,"elevation":179.53},{"lat":55.576701,"lon":37.277718,"x":-22227.191,"z":-2105.897,"elevation":180.23}]},{"id":"road-3006","name":"nan","highway":"residential","points":[{"lat":55.576824,"lon":37.276172,"x":-22399.213,"z":-2081.715,"elevation":179.53},{"lat":55.577145,"lon":37.27635,"x":-22379.409,"z":-2018.542,"elevation":181.67}]},{"id":"road-3010","name":"nan","highway":"residential","points":[{"lat":55.577145,"lon":37.27635,"x":-22379.409,"z":-2018.542,"elevation":181.67},{"lat":55.577046,"lon":37.277446,"x":-22257.481,"z":-2037.998,"elevation":182.7}]},{"id":"road-3011","name":"nan","highway":"residential","points":[{"lat":55.577145,"lon":37.27635,"x":-22379.409,"z":-2018.542,"elevation":181.67},{"lat":55.577667,"lon":37.27661,"x":-22350.455,"z":-1915.787,"elevation":185.53}]},{"id":"road-3012","name":"nan","highway":"residential","points":[{"lat":55.577145,"lon":37.27635,"x":-22379.409,"z":-2018.542,"elevation":181.67},{"lat":55.576824,"lon":37.276172,"x":-22399.213,"z":-2081.715,"elevation":179.53}]},{"id":"road-4402","name":"nan","highway":"unclassified","points":[{"lat":55.573324,"lon":37.297465,"x":-20028.965,"z":-2771.064,"elevation":192.29},{"lat":55.573265,"lon":37.29723,"x":-20055.103,"z":-2782.642,"elevation":194.03}]},{"id":"road-4611","name":"М-3 «Украина» – Бурцево","highway":"tertiary","points":[{"lat":55.570778,"lon":37.269087,"x":-23187.956,"z":-3272.325,"elevation":165.35},{"lat":55.570239,"lon":37.270392,"x":-23042.678,"z":-3378.296,"elevation":167.65},{"lat":55.570565,"lon":37.272548,"x":-22802.726,"z":-3314.159,"elevation":162.94},{"lat":55.570652,"lon":37.274778,"x":-22554.469,"z":-3297.092,"elevation":161.15},{"lat":55.570231,"lon":37.276872,"x":-22321.3,"z":-3380.022,"elevation":164.06},{"lat":55.569158,"lon":37.277932,"x":-22203.35,"z":-3591.158,"elevation":162.51},{"lat":55.56796,"lon":37.278645,"x":-22123.993,"z":-3827.009,"elevation":162.95},{"lat":55.567185,"lon":37.279978,"x":-21975.586,"z":-3979.661,"elevation":158.45}]},{"id":"road-5548","name":"nan","highway":"residential","points":[{"lat":55.575798,"lon":37.282318,"x":-21715.054,"z":-2283.91,"elevation":174.53},{"lat":55.574963,"lon":37.281326,"x":-21825.466,"z":-2448.27,"elevation":172.52},{"lat":55.574542,"lon":37.279653,"x":-22011.754,"z":-2531.129,"elevation":169.58},{"lat":55.573619,"lon":37.278313,"x":-22160.971,"z":-2712.877,"elevation":165.69},{"lat":55.572981,"lon":37.27705,"x":-22301.533,"z":-2838.505,"elevation":163.23},{"lat":55.572643,"lon":37.275552,"x":-22468.252,"z":-2905.127,"elevation":163.68},{"lat":55.57346,"lon":37.274078,"x":-22632.394,"z":-2744.187,"elevation":166.64}]},{"id":"road-10989","name":"nan","highway":"unclassified","points":[{"lat":55.573265,"lon":37.29723,"x":-20055.103,"z":-2782.642,"elevation":194.03},{"lat":55.574368,"lon":37.295982,"x":-20194.002,"z":-2565.326,"elevation":197.43},{"lat":55.575572,"lon":37.295196,"x":-20281.471,"z":-2328.256,"elevation":195.67}]},{"id":"road-10990","name":"nan","highway":"unclassified","points":[{"lat":55.573265,"lon":37.29723,"x":-20055.103,"z":-2782.642,"elevation":194.03},{"lat":55.573324,"lon":37.297465,"x":-20028.965,"z":-2771.064,"elevation":192.29}]},{"id":"road-10991","name":"nan","highway":"unclassified","points":[{"lat":55.573265,"lon":37.29723,"x":-20055.103,"z":-2782.642,"elevation":194.03},{"lat":55.572913,"lon":37.295521,"x":-20245.348,"z":-2851.834,"elevation":199.22}]},{"id":"road-10992","name":"nan","highway":"unclassified","points":[{"lat":55.575572,"lon":37.295196,"x":-20281.471,"z":-2328.256,"elevation":195.67},{"lat":55.574368,"lon":37.295982,"x":-20194.002,"z":-2565.326,"elevation":197.43},{"lat":55.573265,"lon":37.29723,"x":-20055.103,"z":-2782.642,"elevation":194.03}]},{"id":"road-11371","name":"шоссе Ракитки","highway":"secondary","points":[{"lat":55.572913,"lon":37.295521,"x":-20245.348,"z":-2851.834,"elevation":199.22},{"lat":55.574189,"lon":37.295095,"x":-20292.761,"z":-2600.567,"elevation":204.36},{"lat":55.575414,"lon":37.294387,"x":-20371.61,"z":-2359.349,"elevation":201.1},{"lat":55.576593,"lon":37.293424,"x":-20478.73,"z":-2127.168,"elevation":198.95},{"lat":55.577722,"lon":37.292314,"x":-20602.348,"z":-1905.032,"elevation":198.89},{"lat":55.578746,"lon":37.290903,"x":-20759.454,"z":-1703.288,"elevation":194.89},{"lat":55.579722,"lon":37.289406,"x":-20926.066,"z":-1511.005,"elevation":198.33},{"lat":55.580525,"lon":37.2876,"x":-21127.056,"z":-1352.936,"elevation":196.94},{"lat":55.58116,"lon":37.285611,"x":-21348.55,"z":-1227.904,"elevation":200.71},{"lat":55.581654,"lon":37.283496,"x":-21583.999,"z":-1130.652,"elevation":201.04},{"lat":55.581975,"lon":37.28127,"x":-21831.763,"z":-1067.439,"elevation":200.48},{"lat":55.582108,"lon":37.278993,"x":-22085.266,"z":-1041.158,"elevation":202.86},{"lat":55.58211,"lon":37.276703,"x":-22340.109,"z":-1040.766,"elevation":204.53},{"lat":55.58196,"lon":37.274422,"x":-22594.087,"z":-1070.404,"elevation":206.26},{"lat":55.581809,"lon":37.27214,"x":-22848.064,"z":-1100.041,"elevation":205.04}]},{"id":"road-11372","name":"nan","highway":"unclassified","points":[{"lat":55.572913,"lon":37.295521,"x":-20245.348,"z":-2851.834,"elevation":199.22},{"lat":55.573265,"lon":37.29723,"x":-20055.103,"z":-2782.642,"elevation":194.03}]},{"id":"road-11373","name":"улица Мешковский Лес","highway":"unclassified","points":[{"lat":55.572913,"lon":37.295521,"x":-20245.348,"z":-2851.834,"elevation":199.22},{"lat":55.571926,"lon":37.294151,"x":-20397.819,"z":-3046.279,"elevation":195.25},{"lat":55.570759,"lon":37.293475,"x":-20473.139,"z":-3275.95,"elevation":192.96},{"lat":55.56951,"lon":37.293679,"x":-20450.398,"z":-3521.997,"elevation":185.89}]},{"id":"road-11374","name":"шоссе Ракитки","highway":"secondary","points":[{"lat":55.572913,"lon":37.295521,"x":-20245.348,"z":-2851.834,"elevation":199.22},{"lat":55.571856,"lon":37.295577,"x":-20239.08,"z":-3060.094,"elevation":195.89},{"lat":55.570798,"lon":37.295634,"x":-20232.813,"z":-3268.355,"elevation":195.7},{"lat":55.56974,"lon":37.29569,"x":-20226.546,"z":-3476.615,"elevation":192.91}]},{"id":"road-11650","name":"шоссе Ракитки","highway":"secondary","points":[{"lat":55.559362,"lon":37.328547,"x":-16568.899,"z":-5519.582,"elevation":159.9},{"lat":55.559744,"lon":37.326386,"x":-16809.419,"z":-5444.412,"elevation":158.87},{"lat":55.560126,"lon":37.324226,"x":-17049.94,"z":-5369.242,"elevation":160.92},{"lat":55.560335,"lon":37.322015,"x":-17296.08,"z":-5328.109,"elevation":168.58},{"lat":55.560366,"lon":37.319752,"x":-17547.998,"z":-5321.979,"elevation":166.11},{"lat":55.560397,"lon":37.317489,"x":-17799.917,"z":-5315.848,"elevation":171.93},{"lat":55.560428,"lon":37.315226,"x":-18051.836,"z":-5309.717,"elevation":182.28},{"lat":55.56054,"lon":37.312986,"x":-18301.145,"z":-5287.777,"elevation":185.71},{"lat":55.560922,"lon":37.310825,"x":-18541.675,"z":-5212.637,"elevation":181.92},{"lat":55.561303,"lon":37.308665,"x":-18782.205,"z":-5137.498,"elevation":175.7},{"lat":55.56186,"lon":37.306655,"x":-19005.872,"z":-5027.872,"elevation":175.63},{"lat":55.56259,"lon":37.304796,"x":-19212.883,"z":-4884.18,"elevation":181.6},{"lat":55.563436,"lon":37.303114,"x":-19400.062,"z":-4717.764,"elevation":189.98},{"lat":55.564379,"lon":37.301584,"x":-19570.447,"z":-4532.105,"elevation":187.67},{"lat":55.565322,"lon":37.300053,"x":-19740.833,"z":-4346.445,"elevation":184.49},{"lat":55.566329,"lon":37.298664,"x":-19895.479,"z":-4148.25,"elevation":183.42},{"lat":55.567383,"lon":37.297381,"x":-20038.309,"z":-3940.644,"elevation":189.61},{"lat":55.568528,"lon":37.296416,"x":-20145.745,"z":-3715.303,"elevation":194.5},{"lat":55.56974,"lon":37.29569,"x":-20226.546,"z":-3476.615,"elevation":192.91}]},{"id":"road-12199","name":"шоссе Ракитки","highway":"secondary","points":[{"lat":55.581809,"lon":37.27214,"x":-22848.064,"z":-1100.041,"elevation":205.04},{"lat":55.58196,"lon":37.274422,"x":-22594.087,"z":-1070.404,"elevation":206.26},{"lat":55.58211,"lon":37.276703,"x":-22340.109,"z":-1040.766,"elevation":204.53},{"lat":55.582108,"lon":37.278993,"x":-22085.266,"z":-1041.158,"elevation":202.86},{"lat":55.581975,"lon":37.28127,"x":-21831.763,"z":-1067.439,"elevation":200.48},{"lat":55.581654,"lon":37.283496,"x":-21583.999,"z":-1130.652,"elevation":201.04},{"lat":55.58116,"lon":37.285611,"x":-21348.55,"z":-1227.904,"elevation":200.71},{"lat":55.580525,"lon":37.2876,"x":-21127.056,"z":-1352.936,"elevation":196.94},{"lat":55.579722,"lon":37.289406,"x":-20926.066,"z":-1511.005,"elevation":198.33},{"lat":55.578746,"lon":37.290903,"x":-20759.454,"z":-1703.288,"elevation":194.89},{"lat":55.577722,"lon":37.292314,"x":-20602.348,"z":-1905.032,"elevation":198.89},{"lat":55.576593,"lon":37.293424,"x":-20478.73,"z":-2127.168,"elevation":198.95},{"lat":55.575414,"lon":37.294387,"x":-20371.61,"z":-2359.349,"elevation":201.1},{"lat":55.574189,"lon":37.295095,"x":-20292.761,"z":-2600.567,"elevation":204.36},{"lat":55.572913,"lon":37.295521,"x":-20245.348,"z":-2851.834,"elevation":199.22}]},{"id":"road-12447","name":"шоссе Ракитки","highway":"secondary","points":[{"lat":55.56974,"lon":37.29569,"x":-20226.546,"z":-3476.615,"elevation":192.91},{"lat":55.568528,"lon":37.296416,"x":-20145.745,"z":-3715.303,"elevation":194.5},{"lat":55.567383,"lon":37.297381,"x":-20038.309,"z":-3940.644,"elevation":189.61},{"lat":55.566329,"lon":37.298664,"x":-19895.479,"z":-4148.25,"elevation":183.42},{"lat":55.565322,"lon":37.300053,"x":-19740.833,"z":-4346.445,"elevation":184.49},{"lat":55.564379,"lon":37.301584,"x":-19570.447,"z":-4532.105,"elevation":187.67},{"lat":55.563436,"lon":37.303114,"x":-19400.062,"z":-4717.764,"elevation":189.98},{"lat":55.56259,"lon":37.304796,"x":-19212.883,"z":-4884.18,"elevation":181.6},{"lat":55.56186,"lon":37.306655,"x":-19005.872,"z":-5027.872,"elevation":175.63},{"lat":55.561303,"lon":37.308665,"x":-18782.205,"z":-5137.498,"elevation":175.7},{"lat":55.560922,"lon":37.310825,"x":-18541.675,"z":-5212.637,"elevation":181.92},{"lat":55.56054,"lon":37.312986,"x":-18301.145,"z":-5287.777,"elevation":185.71},{"lat":55.560428,"lon":37.315226,"x":-18051.836,"z":-5309.717,"elevation":182.28},{"lat":55.560397,"lon":37.317489,"x":-17799.917,"z":-5315.848,"elevation":171.93},{"lat":55.560366,"lon":37.319752,"x":-17547.998,"z":-5321.979,"elevation":166.11},{"lat":55.560335,"lon":37.322015,"x":-17296.08,"z":-5328.109,"elevation":168.58},{"lat":55.560126,"lon":37.324226,"x":-17049.94,"z":-5369.242,"elevation":160.92},{"lat":55.559744,"lon":37.326386,"x":-16809.419,"z":-5444.412,"elevation":158.87},{"lat":55.559362,"lon":37.328547,"x":-16568.899,"z":-5519.582,"elevation":159.9}]},{"id":"road-12448","name":"шоссе Ракитки","highway":"secondary","points":[{"lat":55.56974,"lon":37.29569,"x":-20226.546,"z":-3476.615,"elevation":192.91},{"lat":55.570798,"lon":37.295634,"x":-20232.813,"z":-3268.355,"elevation":195.7},{"lat":55.571856,"lon":37.295577,"x":-20239.08,"z":-3060.094,"elevation":195.89},{"lat":55.572913,"lon":37.295521,"x":-20245.348,"z":-2851.834,"elevation":199.22}]},{"id":"road-12449","name":"улица Братьев Бромлей","highway":"unclassified","points":[{"lat":55.56974,"lon":37.29569,"x":-20226.546,"z":-3476.615,"elevation":192.91},{"lat":55.56951,"lon":37.293679,"x":-20450.398,"z":-3521.997,"elevation":185.89}]},{"id":"road-12450","name":"улица Мешковский Лес","highway":"unclassified","points":[{"lat":55.56951,"lon":37.293679,"x":-20450.398,"z":-3521.997,"elevation":185.89},{"lat":55.570759,"lon":37.293475,"x":-20473.139,"z":-3275.95,"elevation":192.96},{"lat":55.571926,"lon":37.294151,"x":-20397.819,"z":-3046.279,"elevation":195.25},{"lat":55.572913,"lon":37.295521,"x":-20245.348,"z":-2851.834,"elevation":199.22}]},{"id":"road-12451","name":"улица Братьев Бромлей","highway":"unclassified","points":[{"lat":55.56951,"lon":37.293679,"x":-20450.398,"z":-3521.997,"elevation":185.89},{"lat":55.56974,"lon":37.29569,"x":-20226.546,"z":-3476.615,"elevation":192.91}]},{"id":"road-12452","name":"улица Братьев Бромлей","highway":"unclassified","points":[{"lat":55.56951,"lon":37.293679,"x":-20450.398,"z":-3521.997,"elevation":185.89},{"lat":55.569148,"lon":37.292247,"x":-20609.811,"z":-3593.249,"elevation":186.78},{"lat":55.568786,"lon":37.290815,"x":-20769.224,"z":-3664.5,"elevation":180.24},{"lat":55.568424,"lon":37.289383,"x":-20928.638,"z":-3735.752,"elevation":170.58}]},{"id":"road-12566","name":"Проектируемый проезд № 7077","highway":"residential","points":[{"lat":55.567009,"lon":37.28673,"x":-21223.935,"z":-4014.31,"elevation":159.28},{"lat":55.567708,"lon":37.285066,"x":-21409.163,"z":-3876.772,"elevation":159.87},{"lat":55.568406,"lon":37.283402,"x":-21594.391,"z":-3739.234,"elevation":160.1},{"lat":55.569105,"lon":37.281738,"x":-21779.62,"z":-3601.696,"elevation":161.84}]},{"id":"road-12567","name":"улица Братьев Бромлей","highway":"unclassified","points":[{"lat":55.567009,"lon":37.28673,"x":-21223.935,"z":-4014.31,"elevation":159.28},{"lat":55.567716,"lon":37.288056,"x":-21076.286,"z":-3875.031,"elevation":163.46},{"lat":55.568424,"lon":37.289383,"x":-20928.638,"z":-3735.752,"elevation":170.58}]},{"id":"road-12568","name":"улица Братьев Бромлей","highway":"unclassified","points":[{"lat":55.567009,"lon":37.28673,"x":-21223.935,"z":-4014.31,"elevation":159.28},{"lat":55.566939,"lon":37.285225,"x":-21391.462,"z":-4028.038,"elevation":157.74},{"lat":55.56766,"lon":37.283518,"x":-21581.458,"z":-3886.174,"elevation":157.71},{"lat":55.56838,"lon":37.281812,"x":-21771.453,"z":-3744.309,"elevation":160.88},{"lat":55.569101,"lon":37.280105,"x":-21961.449,"z":-3602.444,"elevation":166.52}]},{"id":"road-12569","name":"улица Усадебный Парк","highway":"residential","points":[{"lat":55.568424,"lon":37.289383,"x":-20928.638,"z":-3735.752,"elevation":170.58},{"lat":55.569133,"lon":37.287694,"x":-21116.592,"z":-3596.189,"elevation":172.73},{"lat":55.569842,"lon":37.286006,"x":-21304.547,"z":-3456.627,"elevation":179.04},{"lat":55.57055,"lon":37.284318,"x":-21492.502,"z":-3317.064,"elevation":176.31},{"lat":55.571259,"lon":37.282629,"x":-21680.456,"z":-3177.502,"elevation":168.87}]},{"id":"road-12570","name":"улица Братьев Бромлей","highway":"unclassified","points":[{"lat":55.568424,"lon":37.289383,"x":-20928.638,"z":-3735.752,"elevation":170.58},{"lat":55.568786,"lon":37.290815,"x":-20769.224,"z":-3664.5,"elevation":180.24},{"lat":55.569148,"lon":37.292247,"x":-20609.811,"z":-3593.249,"elevation":186.78},{"lat":55.56951,"lon":37.293679,"x":-20450.398,"z":-3521.997,"elevation":185.89}]},{"id":"road-12571","name":"улица Братьев Бромлей","highway":"unclassified","points":[{"lat":55.568424,"lon":37.289383,"x":-20928.638,"z":-3735.752,"elevation":170.58},{"lat":55.567716,"lon":37.288056,"x":-21076.286,"z":-3875.031,"elevation":163.46},{"lat":55.567009,"lon":37.28673,"x":-21223.935,"z":-4014.31,"elevation":159.28}]},{"id":"road-12572","name":"улица Братьев Бромлей","highway":"unclassified","points":[{"lat":55.569101,"lon":37.280105,"x":-21961.449,"z":-3602.444,"elevation":166.52},{"lat":55.569101,"lon":37.280105,"x":-21961.449,"z":-3602.444,"elevation":166.52}]},{"id":"road-12573","name":"улица Братьев Бромлей","highway":"unclassified","points":[{"lat":55.569101,"lon":37.280105,"x":-21961.449,"z":-3602.444,"elevation":166.52},{"lat":55.569101,"lon":37.280105,"x":-21961.449,"z":-3602.444,"elevation":166.52}]},{"id":"road-12574","name":"улица Братьев Бромлей","highway":"unclassified","points":[{"lat":55.569101,"lon":37.280105,"x":-21961.449,"z":-3602.444,"elevation":166.52},{"lat":55.56838,"lon":37.281812,"x":-21771.453,"z":-3744.309,"elevation":160.88},{"lat":55.56766,"lon":37.283518,"x":-21581.458,"z":-3886.174,"elevation":157.71},{"lat":55.566939,"lon":37.285225,"x":-21391.462,"z":-4028.038,"elevation":157.74},{"lat":55.567009,"lon":37.28673,"x":-21223.935,"z":-4014.31,"elevation":159.28}]},{"id":"road-13016","name":"улица Усадебный Парк","highway":"residential","points":[{"lat":55.571259,"lon":37.282629,"x":-21680.456,"z":-3177.502,"elevation":168.87},{"lat":55.571259,"lon":37.282629,"x":-21680.456,"z":-3177.502,"elevation":168.87}]},{"id":"road-13017","name":"улица Усадебный Парк","highway":"residential","points":[{"lat":55.571259,"lon":37.282629,"x":-21680.456,"z":-3177.502,"elevation":168.87},{"lat":55.571259,"lon":37.282629,"x":-21680.456,"z":-3177.502,"elevation":168.87}]},{"id":"road-13018","name":"улица Усадебный Парк","highway":"residential","points":[{"lat":55.571259,"lon":37.282629,"x":-21680.456,"z":-3177.502,"elevation":168.87},{"lat":55.57055,"lon":37.284318,"x":-21492.502,"z":-3317.064,"elevation":176.31},{"lat":55.569842,"lon":37.286006,"x":-21304.547,"z":-3456.627,"elevation":179.04},{"lat":55.569133,"lon":37.287694,"x":-21116.592,"z":-3596.189,"elevation":172.73},{"lat":55.568424,"lon":37.289383,"x":-20928.638,"z":-3735.752,"elevation":170.58}]},{"id":"road-13019","name":"Проектируемый проезд № 7077","highway":"residential","points":[{"lat":55.569105,"lon":37.281738,"x":-21779.62,"z":-3601.696,"elevation":161.84},{"lat":55.568406,"lon":37.283402,"x":-21594.391,"z":-3739.234,"elevation":160.1},{"lat":55.567708,"lon":37.285066,"x":-21409.163,"z":-3876.772,"elevation":159.87},{"lat":55.567009,"lon":37.28673,"x":-21223.935,"z":-4014.31,"elevation":159.28}]}],"buildings":[]}